Workbook

Sheet Balance
A1: PACKAGE | B1: TAXCODE | C1: TIN | D1: NAME | E1: NS10_CODE | F1: NS11_CODE | G1: NS13_CODE | H1: NA1_CODE | I1: YEAR | J1: PERIOD | K1: PTYPE | L1: TYPE | M1: STATE | O1: MAX(T.DATESENT) | P1: SUM010 | Q1: SUM010 | R1: SUM011 | S1: SUM011 | T1: SUM012 | U1: SUM012 | V1: SUM020 | W1: SUM020 | X1: SUM021 | Y1: SUM021 | Z1: SUM022 | AA1: SUM022 | AB1: SUM030 | AC1: SUM030 | AD1: SUM040 | AE1: SUM040 | AF1: SUM050 | AG1: SUM050 | AH1: SUM060 | AI1: SUM060 | AJ1: SUM070 | AK1: SUM070 | AL1: SUM080 | AM1: SUM080 | AN1: SUM090 | AO1: SUM090 | AP1: SUM100 | AQ1: SUM100 | AR1: SUM110 | AS1: SUM110 | AT1: SUM120 | AU1: SUM120 | AV1: SUM130 | AW1: SUM130 | AX1: SUM140 | AY1: SUM140 | AZ1: SUM150 | BA1: SUM150 | BB1: SUM160 | BC1: SUM160 | BD1: SUM170 | BE1: SUM170 | BF1: SUM180 | BG1: SUM180 | BH1: SUM190 | BI1: SUM190 | BJ1: SUM200 | BK1: SUM200 | BL1: SUM210 | BM1: SUM210 | BN1: SUM211 | BO1: SUM211 | BP1: SUM220 | BQ1: SUM220 | BR1: SUM230 | BS1: SUM230 | BT1: SUM240 | BU1: SUM240 | BV1: SUM250 | BW1: SUM250 | BX1: SUM260 | BY1: SUM260 | BZ1: SUM270 | CA1: SUM270 | CB1: SUM280 | CC1: SUM280 | CD1: SUM290 | CE1: SUM290 | CF1: SUM300 | CG1: SUM300 | CH1: SUM310 | CI1: SUM310 | CJ1: SUM320 | CK1: SUM320 | CL1: SUM330 | CM1: SUM330 | CN1: SUM340 | CO1: SUM340 | CP1: SUM350 | CQ1: SUM350 | CR1: SUM360 | CS1: SUM360 | CT1: SUM370 | CU1: SUM370 | CV1: SUM380 | CW1: SUM380 | CX1: SUM390 | CY1: SUM390 | CZ1: SUM400 | DA1: SUM400 | DB1: SUM410 | DC1: SUM410 | DD1: SUM420 | DE1: SUM420 | DF1: SUM430 | DG1: SUM430 | DH1: SUM440 | DI1: SUM440 | DJ1: SUM450 | DK1: SUM450 | DL1: SUM460 | DM1: SUM460 | DN1: SUM470 | DO1: SUM470 | DP1: SUM480 | DQ1: SUM480 | DR1: SUM490 | DS1: SUM490 | DT1: SUM491 | DU1: SUM491 | DV1: SUM500 | DW1: SUM500 | DX1: SUM510 | DY1: SUM510 | DZ1: SUM520 | EA1: SUM520 | EB1: SUM530 | EC1: SUM530 | ED1: SUM540 | EE1: SUM540 | EF1: SUM550 | EG1: SUM550 | EH1: SUM560 | EI1: SUM560 | EJ1: SUM570 | EK1: SUM570 | EL1: SUM580 | EM1: SUM580 | EN1: SUM590 | EO1: SUM590 | EP1: SUM600 | EQ1: SUM600 | ER1: SUM601 | ES1: SUM601 | ET1: SUM602 | EU1: SUM602 | EV1: SUM610 | EW1: SUM610 | EX1: SUM620 | EY1: SUM620 | EZ1: SUM630 | FA1: SUM630 | FB1: SUM640 | FC1: SUM640 | FD1: SUM650 | FE1: SUM650 | FF1: SUM660 | FG1: SUM660 | FH1: SUM670 | FI1: SUM670 | FJ1: SUM680 | FK1: SUM680 | FL1: SUM690 | FM1: SUM690 | FN1: SUM700 | FO1: SUM700 | FP1: SUM710 | FQ1: SUM710 | FR1: SUM720 | FS1: SUM720 | FT1: SUM730 | FU1: SUM730 | FV1: SUM740 | FW1: SUM740 | FX1: SUM750 | FY1: SUM750 | FZ1: SUM760 | GA1: SUM760 | GB1: SUM770 | GC1: SUM770 | GD1: SUM780 | GE1: SUM780
A2: 20006 | B2: 0 | C2: 200240131 | D2: "ANDIJONYOG'MOY" AJ | E2: 3 | F2: 1 | G2: 0 | H2: 1 | I2: 2021 | J2: 4 | K2: N | L2: 2 | M2: 30 | N2: 0 | O2: 44660.822 | P2: 14891463 | Q2: 14891463 | R2: 8241593 | S2: 9098100 | T2: 6649870 | U2: 5793363 | V2: 556007 | W2: 556007 | X2: 556007 | Y2: 556007 | Z2: 0 | AA2: 0 | AB2: 311230 | AC2: 311230 | AD2: 9117 | AE2: 9117 | AF2: 272113 | AG2: 272113 | AL2: 30000 | AM2: 30000 | AN2: 136832 | AO2: 136832 | AP2: 263866 | AQ2: 269165 | AR2: 1906630 | AS2: 2067215 | AV2: 9268428 | AW2: 8577805 | AX2: 24531306 | AY2: 12162334 | AZ2: 5022094 | BA2: 6156656 | BD2: 19509212 | BE2: 6005678 | BJ2: 29627260 | BK2: 12327260 | BL2: 12443201 | BM2: 66922943 | BP2: 336240 | BQ2: 63486711 | BV2: 6521 | BW2: 6652 | BX2: 8649559 | BY2: 2773870 | BZ2: 3049127 | CA2: 315110 | CB2: 4137 | CC2: 4711 | CH2: 397617 | CI2: 335889 | CJ2: 585490 | CK2: 546670 | CN2: 1 | CP2: 3417 | CQ2: 3535 | CR2: 582072 | CS2: 543135 | CT2: 296711 | CU2: 291961 | CX2: 67483968 | CY2: 92251168 | CZ2: 76752396 | DA2: 100828973 | DB2: 1833238 | DC2: 1833238 | DF2: 3402704 | DG2: 3402704 | DJ2: -12319063 | DK2: -12313502 | DL2: 511230 | DM2: 511230 | DP2: -6571891 | DQ2: -6566330 | DR2: 30642279 | DS2: 32607213 | EL2: 30642279 | EM2: 32607213 | EP2: 50094788 | EQ2: 74788090 | ER2: 10942777 | ES2: 38128531 | EV2: 7913339 | EW2: 30667667 | FH2: 1655 | FI2: 416759 | FJ2: 250654 | FK2: 2893455 | FN2: 99218 | FO2: 244921 | FP2: 886565 | FQ2: 885581 | FR2: 1154369 | FS2: 1737003 | FT2: 15745000 | FU2: 3931000 | FV2: 23407011 | FW2: 32728559 | FZ2: 636977 | GA2: 1283145 | GB2: 80737067 | GC2: 107395303 | GD2: 74165176 | GE2: 100828973
A3: 20006 | B3: 0 | C3: 200240131 | D3: "ANDIJONYOG'MOY" AJ | E3: 3 | F3: 1 | G3: 0 | H3: 1 | I3: 2020 | J3: 4 | K3: N | L3: 1 | M3: 30 | N3: 0 | O3: 44240.648 | P3: 15160699 | Q3: 14891463 | R3: 7565795 | S3: 8241711 | T3: 7594904 | U3: 6649752 | V3: 556007 | W3: 556007 | X3: 444806 | Y3: 556007 | Z3: 111201 | AA3: 0 | AB3: 325356 | AC3: 311230 | AD3: 23243 | AE3: 9117 | AF3: 272113 | AG3: 272113 | AL3: 30000 | AM3: 30000 | AN3: 136832 | AO3: 136832 | AP3: 432398 | AQ3: 263867 | AR3: 1556214 | AS3: 1906629 | AV3: 10156905 | AW3: 9268310 | AX3: 22172154 | AY3: 24433848 | AZ3: 6924978 | BA3: 5022149 | BD3: 15247176 | BE3: 19411699 | BH3: 2920 | BJ3: 28899167 | BK3: 29744238 | BL3: 5477009 | BM3: 12632393 | BN3: 785597 | BO3: 622280 | BP3: 857301 | BQ3: 336240 | BV3: 31599 | BW3: 6520 | BX3: 834064 | BY3: 8535906 | BZ3: 1401435 | CA3: 2660945 | CB3: 4137 | CC3: 4594 | CH3: 2348473 | CI3: 1088188 | CJ3: 25208 | CK3: 8454 | CN3: 16659 | CP3: 3101 | CQ3: 3417 | CR3: 5448 | CS3: 5037 | CT3: 531046 | CU3: 296711 | CX3: 57107504 | CY3: 67115644 | CZ3: 67264409 | DA3: 76383954 | DB3: 1833238 | DC3: 1833238 | DF3: 3433449 | DG3: 3390157 | DJ3: 2342361 | DK3: -12453753 | DL3: 262047 | DM3: 478723 | DP3: 7871095 | DQ3: -6751635 | DR3: 29569418 | DS3: 33152642 | EL3: 29569418 | EM3: 33152642 | EP3: 29823896 | EQ3: 49982947 | ER3: 8308735 | ES3: 10830936 | ET3: 100184 | EU3: 72240 | EV3: 3957634 | EW3: 7456941 | FH3: 6517 | FI3: 1655 | FJ3: 138090 | FK3: 244060 | FN3: 193310 | FP3: 131444 | FQ3: 886565 | FR3: 859826 | FS3: 1149170 | FT3: 21400000 | FU3: 15745000 | FV3: 115161 | FW3: 23407011 | FZ3: 3021914 | GA3: 1092545 | GB3: 59393314 | GC3: 83135589 | GD3: 67264409 | GE3: 76383954
A4: 20006 | B4: 0 | C4: 200240131 | D4: "ANDIJONYOG'MOY" AJ | E4: 3 | F4: 1 | G4: 0 | H4: 1 | I4: 2019 | J4: 4 | K4: N | L4: 1 | M4: 30 | N4: 0 | O4: 43875.627 | P4: 12335367 | Q4: 14370848 | R4: 7184838 | S4: 7175500 | T4: 5150529 | U4: 7195348 | V4: 556007 | W4: 556007 | X4: 333604 | Y4: 444806 | Z4: 222403 | AA4: 111201 | AB4: 325356 | AC4: 325356 | AD4: 23243 | AE4: 23243 | AF4: 272113 | AG4: 272113 | AL4: 30000 | AM4: 30000 | AN4: 237348 | AO4: 127523 | AP4: 275234 | AQ4: 401843 | AR4: 1266868 | AS4: 1556214 | AV4: 7477738 | AW4: 9717485 | AX4: 11734265 | AY4: 22172154 | AZ4: 7196771 | BA4: 6924978 | BD4: 4537494 | BE4: 15247176 | BH4: 20832 | BI4: 2920 | BJ4: 26899637 | BK4: 28899167 | BL4: 6124106 | BM4: 5477009 | BN4: 610583 | BO4: 785597 | BP4: 1839893 | BQ4: 857301 | BV4: 35497 | BW4: 31599 | BX4: 1220116 | BY4: 834064 | BZ4: 692024 | CA4: 1401435 | CC4: 4137 | CH4: 2336576 | CI4: 2348473 | CJ4: 863321 | CK4: 25208 | CN4: 23612 | CO4: 16659 | CP4: 832163 | CQ4: 3101 | CR4: 7546 | CS4: 5448 | CT4: 1362271 | CU4: 531046 | CX4: 47004432 | CY4: 57107504 | CZ4: 54482170 | DA4: 66824989 | DB4: 1833238 | DC4: 1833238 | DF4: 3529736 | DG4: 2994029 | DJ4: 2063462 | DK4: 2342361 | DL4: 100798 | DM4: 262047 | DP4: 7527234 | DQ4: 7431675 | DR4: 28001815 | DS4: 29569418 | EL4: 28001815 | EM4: 29569418 | EP4: 18953121 | EQ4: 29823896 | ER4: 3300023 | ES4: 8308735 | ET4: 53590 | EU4: 100184 | EV4: 764985 | EW4: 3957634 | FH4: 43485 | FI4: 6517 | FJ4: 73580 | FK4: 138090 | FN4: 699074 | FO4: 193310 | FP4: 82224 | FQ4: 131444 | FR4: 507432 | FS4: 859826 | FT4: 15594752 | FU4: 21400000 | FV4: 58346 | FW4: 115161 | FZ4: 1129243 | GA4: 3021914 | GB4: 46954936 | GC4: 59393314 | GD4: 54482170 | GE4: 66824989
A5: 20006 | B5: 0 | C5: 200240131 | D5: "ANDIJONYOG'MOY" AJ | E5: 3 | F5: 1 | G5: 0 | H5: 1 | I5: 2018 | J5: 4 | K5: N | L5: 1 | M5: 30 | N5: 0 | O5: 43508.483 | P5: 11101851 | Q5: 11540839 | R5: 6422483 | S5: 6775850 | T5: 4679368 | U5: 4764989 | V5: 556007 | W5: 556007 | X5: 333604 | Y5: 333604 | Z5: 222403 | AA5: 222403 | AB5: 345057 | AC5: 325356 | AD5: 21694 | AE5: 23243 | AF5: 272113 | AG5: 272113 | AL5: 51250 | AM5: 30000 | AN5: 561985 | AO5: 227345 | AP5: 128798 | AQ5: 258400 | AR5: 84711 | AS5: 1266868 | AV5: 6022322 | AW5: 7065361 | AX5: 7450861 | AY5: 11734265 | AZ5: 4662038 | BA5: 7196771 | BD5: 2788823 | BE5: 4537494 | BH5: 25639 | BI5: 20832 | BJ5: 27089450 | BK5: 26899637 | BL5: 2750262 | BM5: 6124106 | BN5: 650380 | BO5: 610583 | BP5: 415796 | BQ5: 1839893 | BV5: 28118 | BW5: 35497 | BX5: 501253 | BY5: 1220116 | BZ5: 102081 | CA5: 692024 | CH5: 1703014 | CI5: 2336576 | CJ5: 273182 | CK5: 863321 | CN5: 265873 | CO5: 23612 | CP5: 2649 | CQ5: 832163 | CR5: 4660 | CS5: 7546 | CT5: 227223 | CU5: 1362271 | CX5: 37816617 | CY5: 47004432 | CZ5: 43838939 | DA5: 54069793 | DB5: 1833238 | DC5: 1833238 | DF5: 3349287 | DG5: 3117359 | DJ5: 1119975 | DK5: 2063462 | DM5: 100798 | DP5: 6302500 | DQ5: 7114857 | DR5: 28571453 | DS5: 28001815 | EL5: 28571453 | EM5: 28001815 | EP5: 8964986 | EQ5: 18953121 | ER5: 5314486 | ES5: 3300023 | ET5: 68898 | EU5: 53590 | EV5: 2673586 | EW5: 764985 | FH5: 64591 | FI5: 43485 | FJ5: 1128237 | FK5: 73580 | FN5: 468669 | FO5: 699074 | FP5: 113691 | FQ5: 82224 | FR5: 494076 | FS5: 507432 | FT5: 3650500 | FU5: 15594752 | FW5: 58346 | FZ5: 371636 | GA5: 1129243 | GB5: 37536439 | GC5: 46954936 | GD5: 43838939 | GE5: 54069793
A6: 20006 | B6: 0 | C6: 200244553 | D6: "ASAKA YOG'" AJ | E6: 3 | F6: 15 | G6: 0 | H6: 1 | I6: 2021 | J6: 4 | K6: N | L6: 2 | M6: 30 | N6: 0 | O6: 44606.898 | P6: 26237285 | Q6: 26170297 | R6: 13742606 | S6: 14786616 | T6: 12494679 | U6: 11383681 | V6: 14000 | W6: 14000 | X6: 14000 | Y6: 14000 | Z6: 0 | AA6: 0 | AB6: 414991 | AC6: 414991 | AD6: 5000 | AE6: 5000 | AF6: 11000 | AG6: 11000 | AL6: 398991 | AM6: 398991 | AR6: 2262786 | AS6: 2372291 | AV6: 15172456 | AW6: 14170963 | AX6: 24715469 | AY6: 20709898 | AZ6: 12313497 | BA6: 7908816 | BC6: 342483 | BD6: 12401972 | BE6: 12458599 | BL6: 14504336 | BM6: 14251183 | BP6: 1929624 | BQ6: 159965 | BX6: 10920306 | BY6: 13477525 | BZ6: 1578988 | CA6: 416440 | CB6: 5 | CC6: 1266 | CF6: 17878 | CG6: 14663 | CH6: 57535 | CI6: 181324 | CJ6: 1899 | CK6: 1316 | CN6: 303 | CO6: 1232 | CP6: 84 | CQ6: 84 | CR6: 1512 | CS6: 0 | CX6: 39221704 | CY6: 34962397 | CZ6: 54394160 | DA6: 49133360 | DB6: 2747464 | DC6: 2747464 | DF6: 9133488 | DG6: 9101428 | DJ6: -2026350 | DK6: -4856219 | DL6: 9362 | DM6: 9362 | DP6: 9863964 | DQ6: 7002035 | DR6: 25423419 | DS6: 12437863 | DT6: 4632169 | DU6: 4457863 | DV6: 4632169 | DW6: 4457863 | EJ6: 20670000 | EK6: 7980000 | EL6: 121250 | EM6: 0 | EP6: 19106777 | EQ6: 29693462 | ER6: 14726777 | ES6: 29693462 | EV6: 12005655 | EW6: 18023530 | EZ6: 169210 | FA6: 0 | FH6: 518979 | FI6: 5060002 | FJ6: 94511 | FK6: 1260084 | FN6: 94118 | FO6: 168533 | FR6: 1562043 | FS6: 1938283 | FT6: 4100000 | FU6: 0 | FV6: 280000 | FW6: 0 | FZ6: 282261 | GA6: 3243030 | GB6: 44530196 | GC6: 42131325 | GD6: 54394160 | GE6: 49133360
A7: 20006 | B7: 0 | C7: 200244553 | D7: "ASAKA YOG'" AJ | E7: 3 | F7: 15 | G7: 0 | H7: 1 | I7: 2020 | J7: 4 | K7: N | L7: 1 | M7: 30 | N7: 0 | O7: 44247.95 | P7: 23467083 | Q7: 26237285 | R7: 12688746 | S7: 13742606 | T7: 10778337 | U7: 12494679 | V7: 14000 | W7: 14000 | X7: 14000 | Y7: 14000 | Z7: 0 | AA7: 0 | AB7: 416606 | AC7: 414991 | AD7: 6615 | AE7: 5000 | AF7: 11000 | AG7: 11000 | AL7: 398991 | AM7: 398991 | AP7: 2125 | AR7: 1500404 | AS7: 2262786 | AV7: 12697472 | AW7: 15172456 | AX7: 21831719 | AY7: 24715469 | AZ7: 8580879 | BA7: 12313497 | BD7: 13250840 | BE7: 12401972 | BJ7: 920076 | BK7: 0 | BL7: 9060302 | BM7: 14504336 | BP7: 1454162 | BQ7: 1929624 | BX7: 6044188 | BY7: 10920306 | BZ7: 1318393 | CA7: 1578988 | CB7: 5 | CC7: 5 | CF7: 51757 | CG7: 17878 | CH7: 191797 | CI7: 57535 | CJ7: 4114 | CK7: 1899 | CN7: 496 | CO7: 303 | CP7: 76 | CQ7: 84 | CR7: 3542 | CS7: 1512 | CT7: 68000 | CU7: 0 | CX7: 31884211 | CY7: 39221704 | CZ7: 44581683 | DA7: 54394160 | DB7: 2747464 | DC7: 2747464 | DF7: 6072144 | DG7: 9133488 | DJ7: 4289308 | DK7: -2026350 | DM7: 9362 | DP7: 13108916 | DQ7: 9863964 | DR7: 5170448 | DS7: 25423419 | DT7: 5049198 | DU7: 4632169 | DV7: 5049198 | DW7: 4632169 | EK7: 20670000 | EL7: 121250 | EM7: 121250 | EP7: 26302319 | EQ7: 19106777 | ER7: 5272319 | ES7: 14726777 | EV7: 3282688 | EW7: 12005655 | EZ7: 110397 | FA7: 169210 | FH7: 538362 | FI7: 518979 | FJ7: 9640 | FK7: 94511 | FN7: 159000 | FO7: 94118 | FR7: 827737 | FS7: 1562043 | FT7: 20750000 | FU7: 4100000 | FV7: 280000 | FW7: 280000 | FZ7: 344495 | GA7: 282261 | GB7: 31472767 | GC7: 44530196 | GD7: 44581683 | GE7: 54394160
A8: 20006 | B8: 0 | C8: 200244553 | D8: "ASAKA YOG'" AJ | E8: 3 | F8: 15 | G8: 0 | H8: 1 | I8: 2019 | J8: 4 | K8: N | L8: 2 | M8: 30 | N8: 0 | O8: 43885.466 | P8: 19883971 | Q8: 22051424 | R8: 11044042 | S8: 11949849 | T8: 8839929 | U8: 10101575 | V8: 14000 | W8: 14000 | X8: 14000 | Y8: 14000 | Z8: 0 | AA8: 0 | AB8: 385927 | AC8: 416606 | AD8: 6615 | AE8: 6615 | AF8: 11000 | AG8: 11000 | AL8: 368312 | AM8: 398991 | AP8: 1097442 | AQ8: 2125 | AR8: 1254566 | AS8: 1500404 | AV8: 11577864 | AW8: 12020710 | AX8: 15470495 | AY8: 21831719 | AZ8: 9366375 | BA8: 8580879 | BD8: 6104120 | BE8: 13250840 | BH8: 4000 | BI8: 0 | BJ8: 1236408 | BK8: 920076 | BL8: 8323255 | BM8: 9060302 | BP8: 322830 | BQ8: 1454162 | BX8: 7279458 | BY8: 6044188 | BZ8: 556009 | CA8: 1318393 | CB8: 5 | CC8: 5 | CF8: 80921 | CG8: 51757 | CH8: 84032 | CI8: 191797 | CJ8: 1880557 | CK8: 4114 | CN8: 3488 | CO8: 496 | CP8: 270791 | CQ8: 76 | CR8: 1606278 | CS8: 3542 | CT8: 1000000 | CU8: 68000 | CX8: 27914715 | CY8: 31884211 | CZ8: 39492579 | DA8: 43904921 | DB8: 2747464 | DC8: 2747464 | DF8: 5423139 | DG8: 5395382 | DJ8: 3907136 | DK8: 4289308 | DL8: 916348 | DN8: 600000 | DP8: 13594087 | DQ8: 12432154 | DR8: 4798669 | DS8: 5170448 | DT8: 4677419 | DU8: 5049198 | DV8: 4677419 | DW8: 5049198 | EL8: 121250 | EM8: 121250 | EP8: 21099823 | EQ8: 26302319 | ER8: 4045823 | ES8: 5272319 | EV8: 2403040 | EW8: 3282688 | FA8: 110397 | FH8: 9486 | FI8: 538362 | FJ8: 64260 | FK8: 9640 | FN8: 732175 | FO8: 159000 | FR8: 579228 | FS8: 827737 | FT8: 17054000 | FU8: 20750000 | FW8: 280000 | FZ8: 257634 | GA8: 344495 | GB8: 25898492 | GC8: 31472767 | GD8: 39492579 | GE8: 43904921
A9: 20006 | B9: 0 | C9: 200244553 | D9: "ASAKA YOG'" AJ | E9: 3 | F9: 15 | G9: 0 | H9: 1 | I9: 2018 | J9: 4 | K9: N | L9: 1 | M9: 30 | N9: 0 | O9: 43507.649 | P9: 17272650 | Q9: 18767080 | R9: 9449550 | S9: 10437463 | T9: 7823100 | U9: 8329617 | V9: 14000 | W9: 14000 | X9: 14000 | Y9: 14000 | Z9: 0 | AA9: 0 | AB9: 432177 | AC9: 385927 | AD9: 6615 | AE9: 6615 | AF9: 11000 | AG9: 11000 | AL9: 414562 | AM9: 368312 | AP9: 27975 | AQ9: 1097442 | AR9: 949618 | AS9: 1254566 | AV9: 9232870 | AW9: 11067552 | AX9: 6116393 | AY9: 15470495 | AZ9: 4115249 | BA9: 9366375 | BD9: 2001144 | BE9: 6104120 | BH9: 16525 | BI9: 4000 | BJ9: 2627728 | BK9: 1236408 | BL9: 4462160 | BM9: 8323255 | BP9: 20911 | BQ9: 322830 | BX9: 4150542 | BY9: 7279458 | BZ9: 82796 | CA9: 556009 | CB9: 0 | CC9: 5 | CF9: 56670 | CG9: 80921 | CH9: 151241 | CI9: 84032 | CJ9: 337865 | CK9: 1880557 | CN9: 244633 | CO9: 3488 | CQ9: 270791 | CR9: 93232 | CS9: 1606278 | CU9: 1000000 | CX9: 13560671 | CY9: 27914715 | CZ9: 22793541 | DA9: 38982267 | DB9: 2747464 | DC9: 2747464 | DF9: 4860058 | DG9: 4912827 | DJ9: 2055379 | DK9: 3907136 | DL9: 916348 | DM9: 916348 | DO9: 600000 | DP9: 10579249 | DQ9: 13083775 | DR9: 5549671 | DS9: 4798669 | DT9: 5307171 | DU9: 4677419 | DV9: 5307171 | DW9: 4677419 | EL9: 242500 | EM9: 121250 | EP9: 6664621 | EQ9: 21099823 | ER9: 5210621 | ES9: 4045823 | EV9: 2394477 | EW9: 2403040 | FH9: 375662 | FI9: 9486 | FJ9: 998758 | FK9: 64260 | FN9: 541012 | FO9: 732175 | FR9: 360536 | FS9: 579228 | FT9: 1454000 | FU9: 17054000 | FZ9: 540176 | GA9: 257634 | GB9: 12214292 | GC9: 25898492 | GD9: 22793541 | GE9: 38982267
A10: 20006 | B10: 0 | C10: 200323067 | D10: "GULISTON EKSTRAKT-YOG'" AJ | E10: 24 | F10: 10 | G10: 2 | H10: 1 | I10: 2021 | J10: 4 | K10: N | L10: 2 | M10: 30 | N10: 0 | O10: 44621.623 | P10: 22697474 | Q10: 23314015 | R10: 16631362 | S10: 18409072 | T10: 6066112 | U10: 4904943 | Z10: 0 | AB10: 546150 | AC10: 546150 | AD10: 51 | AE10: 51 | AF10: 546099 | AG10: 546099 | AN10: 53751 | AO10: 53751 | AP10: 3728002 | AQ10: 3728002 | AR10: 1332940 | AS10: 1477780 | AV10: 11726955 | AW10: 10710626 | AX10: 14952895 | AY10: 11699951 | AZ10: 8992752 | BA10: 7054057 | BB10: 4766559 | BC10: 4480498 | BD10: 1029495 | BE10: 1307 | BF10: 164089 | BG10: 164089 | BH10: 13719893 | BI10: 13719893 | BJ10: 26217392 | BK10: 26217392 | BL10: 29634491 | BM10: 12793429 | BP10: 1403961 | BQ10: 1795605 | BT10: 363 | BU10: 363 | BV10: 40039 | BW10: 85478 | BX10: 22863454 | BY10: 5200106 | BZ10: 933770 | CA10: 1363617 | CC10: 164050 | CF10: 164608 | CG10: 101246 | CH10: 4228296 | CI10: 4082964 | CJ10: 14758 | CK10: 10295 | CN10: 14106 | CO10: 9643 | CP10: 652 | CQ10: 652 | CV10: 23346 | CW10: 23346 | CX10: 84562775 | CY10: 64464306 | CZ10: 96289730 | DA10: 75174932 | DB10: 986966 | DC10: 986966 | DD10: 993961 | DE10: 993961 | DF10: 5697194 | DG10: 5904769 | DJ10: 44889 | DK10: -7028738 | DP10: 7723010 | DQ10: 856958 | DR10: 29814057 | DS10: 29814057 | DT10: 4375439 | DU10: 4375439 | EL10: 25438618 | EM10: 25438618 | EN10: 4375439 | EO10: 4375439 | EP10: 58752663 | EQ10: 44503917 | ER10: 16968384 | ES10: 15818850 | EV10: 1154824 | EW10: 1381522 | FB10: 1220261 | FC10: 1220261 | FH10: 7371399 | FI10: 1058361 | FJ10: 510135 | FK10: 2134850 | FL10: 10 | FM10: 10 | FN10: 225579 | FO10: 169400 | FP10: 5424739 | FQ10: 5361499 | FR10: 460169 | FS10: 1774440 | FT10: 32291906 | FU10: 19192694 | FV10: 8272112 | FW10: 8272112 | FZ10: 1821529 | GA10: 3938768 | GB10: 88566720 | GC10: 74317974 | GD10: 96289730 | GE10: 75174932
A11: 20006 | B11: 0 | C11: 200323067 | D11: "GULISTON EKSTRAKT-YOG'" AJ | E11: 24 | F11: 10 | G11: 2 | H11: 1 | I11: 2020 | J11: 4 | K11: N | L11: 2 | M11: 30 | N11: 0 | O11: 44596.374 | P11: 21196752 | Q11: 22697474 | R11: 14286423 | S11: 16631362 | T11: 6910329 | U11: 6066112 | Z11: 0 | AB11: 546150 | AC11: 546150 | AD11: 51 | AE11: 51 | AF11: 546099 | AG11: 546099 | AN11: 53751 | AO11: 53751 | AP11: 3743002 | AQ11: 3728002 | AR11: 1616025 | AS11: 1332940 | AV11: 12869257 | AW11: 11726955 | AX11: 40270414 | AY11: 14952895 | AZ11: 15107486 | BA11: 8992752 | BB11: 315300 | BC11: 4766559 | BD11: 24683539 | BE11: 1029495 | BF11: 164089 | BG11: 164089 | BH11: 10950000 | BI11: 13719893 | BJ11: 26217477 | BK11: 26217392 | BL11: 12929570 | BM11: 29634491 | BP11: 1061166 | BQ11: 1403961 | BU11: 363 | BV11: 12346 | BW11: 40039 | BX11: 5627229 | BY11: 22863454 | BZ11: 2211307.3 | CA11: 933770 | CF11: 15241 | CG11: 164608 | CH11: 4002281 | CI11: 4228296 | CJ11: 52090 | CK11: 14758 | CO11: 14106 | CP11: 52090 | CQ11: 652 | CV11: 23346 | CW11: 23346 | CX11: 90442897 | CY11: 84562775 | CZ11: 1.0331215e+08 | DA11: 96289730 | DB11: 986966 | DC11: 986966 | DD11: 993961 | DE11: 993961 | DF11: 5137538 | DG11: 5697194 | DJ11: 16000542 | DK11: 44889 | DP11: 23119007 | DQ11: 7723010 | DR11: 25910546 | DS11: 29814057 | DT11: 2573744 | DU11: 4375439 | EL11: 23336802 | EM11: 25438618 | EN11: 2573744 | EO11: 4375439 | EP11: 54282601 | EQ11: 58752663 | ER11: 18818349 | ES11: 16968384 | EV11: 3786546 | EW11: 1154824 | FB11: 875607.56 | FC11: 1220261 | FH11: 2629151 | FI11: 7371399 | FJ11: 63926.74 | FK11: 510135 | FL11: 10 | FM11: 10 | FN11: 406076 | FO11: 225579 | FP11: 7747100 | FQ11: 5424739 | FR11: 1622297 | FS11: 460169 | FT11: 27000000 | FU11: 32291906 | FV11: 7588645 | FW11: 8272112 | FZ11: 2563242 | GA11: 1821529 | GB11: 80193147 | GC11: 88566720 | GD11: 1.0331215e+08 | GE11: 96289730
A12: 20006 | B12: 0 | C12: 200323067 | D12: "GULISTON EKSTRAKT-YOG'" AJ | E12: 24 | F12: 10 | G12: 2 | H12: 1 | I12: 2019 | J12: 4 | K12: N | L12: 2 | M12: 30 | N12: 0 | O12: 44594.979 | P12: 20668479 | Q12: 21196752 | R12: 13026810 | S12: 14286423 | T12: 7641669 | U12: 6910329 | AB12: 636963 | AC12: 546150 | AD12: 51 | AE12: 51 | AF12: 636912 | AG12: 546099 | AN12: 60791 | AO12: 53751 | AP12: 1343828 | AQ12: 3743002 | AR12: 1907821 | AS12: 1616025 | AV12: 11591072 | AW12: 12869257 | AX12: 26705266 | AY12: 40270414 | AZ12: 7956790 | BA12: 15107486 | BB12: 39283 | BC12: 315300 | BD12: 18507049 | BE12: 24683539 | BF12: 202144 | BG12: 164089 | BI12: 10950000 | BJ12: 26218995 | BK12: 26217477 | BL12: 8416276 | BM12: 12929570 | BN12: 271889 | BP12: 722163 | BQ12: 1061166 | BV12: 3515 | BW12: 12346 | BX12: 5535509 | BY12: 5627229 | BZ12: 444132 | CA12: 2211307.3 | CF12: 13411 | CG12: 15241 | CH12: 1697546 | CI12: 4002281 | CJ12: 1444811 | CK12: 52090 | CN12: 1141965 | CP12: 302846 | CQ12: 52090 | CV12: 23346 | CW12: 23346 | CX12: 62808694 | CY12: 90442897 | CZ12: 74399766 | DA12: 1.0331215e+08 | DB12: 986966 | DC12: 986966 | DD12: 993961 | DE12: 993961 | DF12: 4341974 | DG12: 5137538 | DJ12: 25140915 | DK12: 16000542 | DP12: 31463816 | DQ12: 23119007 | DR12: 20416519 | DS12: 25910546 | DU12: 2573744 | EL12: 20416519 | EM12: 23336802 | EO12: 2573744 | EP12: 22519431 | EQ12: 54282601 | ER12: 3915435 | ES12: 18818349 | EV12: 322577 | EW12: 3786546 | FC12: 875607.56 | FF12: 1234677 | FH12: 47634 | FI12: 2629151 | FJ12: 378988 | FK12: 63926.74 | FM12: 10 | FN12: 1113039 | FO12: 406076 | FP12: 106751 | FQ12: 7747100 | FR12: 1213233 | FS12: 1622297 | FT12: 10996354 | FU12: 27000000 | FV12: 6372965 | FW12: 7588645 | FZ12: 733213 | GA12: 2563242 | GB12: 42935950 | GC12: 80193147 | GD12: 74399766 | GE12: 1.0331215e+08
A13: 20006 | B13: 0 | C13: 200323067 | D13: "GULISTON EKSTRAKT-YOG'" AJ | E13: 24 | F13: 10 | G13: 2 | H13: 1 | I13: 2018 | J13: 4 | K13: N | L13: 2 | M13: 30 | N13: 0 | O13: 43620.446 | P13: 17952322 | Q13: 19833890 | R13: 11258028 | S13: 12550134 | T13: 6694294 | U13: 7283756 | AB13: 737864 | AC13: 636963 | AD13: 32772 | AE13: 51 | AF13: 705092 | AG13: 636912 | AN13: 125691 | AO13: 60791 | AP13: 1313477 | AQ13: 1343828 | AR13: 1670039 | AS13: 1907821 | AV13: 10541365 | AW13: 11233159 | AX13: 12723107 | AY13: 26705266 | AZ13: 5608314 | BA13: 7956790 | BB13: 321973 | BC13: 39283 | BD13: 6792820 | BE13: 18507049 | BG13: 202144 | BH13: 206633 | BI13: 0 | BJ13: 25489415 | BK13: 26218995 | BL13: 6602767 | BM13: 8416276 | BN13: 21905 | BO13: 271889 | BP13: 2939786 | BQ13: 722163 | BV13: 2792 | BW13: 3515 | BX13: 2674689 | BY13: 5535509 | BZ13: 367210 | CA13: 444132 | CB13: 6 | CC13: 0 | CF13: 30248 | CG13: 13411 | CH13: 588036 | CI13: 1697546 | CJ13: 235456 | CK13: 1444811 | CN13: 14870 | CO13: 1141965 | CP13: 8502 | CQ13: 302846 | CR13: 212084 | CS13: 0 | CT13: 21500 | CU13: 0 | CV13: 23346 | CW13: 23346 | CX13: 45302224 | CY13: 62808694 | CZ13: 55843589 | DA13: 74041853 | DB13: 986966 | DC13: 986966 | DD13: 993961 | DE13: 993961 | DF13: 3952380 | DG13: 3984061 | DJ13: 10002726 | DK13: 25140915 | DP13: 15936033 | DQ13: 31105903 | DR13: 21365658 | DS13: 20416519 | EL13: 21365658 | EM13: 20416519 | EP13: 18541898 | EQ13: 22519431 | ER13: 5817543 | ES13: 3915435 | EV13: 3227911 | EW13: 322577 | FF13: 100817 | FG13: 1234677 | FH13: 5296 | FI13: 47634 | FJ13: 655534 | FK13: 378988 | FN13: 499702 | FO13: 1113039 | FP13: 226638 | FQ13: 106751 | FR13: 211634 | FS13: 1213233 | FT13: 6700000 | FU13: 10996354 | FV13: 5923538 | FW13: 6372965 | FZ13: 990828 | GA13: 733213 | GB13: 39907556 | GC13: 42935950 | GD13: 55843589 | GE13: 74041853
A14: 20006 | B14: 0 | C14: 200466854 | D14: "YANGIYO'L YOG'-MOY" AJ | E14: 27 | F14: 22 | G14: 0 | H14: 8 | I14: 2021 | J14: 4 | K14: N | L14: 1 | M14: 30 | N14: 0 | O14: 44624.645 | P14: 46482344 | Q14: 46528972 | R14: 29880530 | S14: 31474475 | T14: 16601814 | U14: 15054497 | V14: 74882 | W14: 74882 | Z14: 74882 | AA14: 74882 | AB14: 1551476 | AC14: 1551476 | AD14: 536 | AE14: 536 | AL14: 1550940 | AM14: 1550940 | AN14: 5761806 | AO14: 7298353 | AP14: 159559 | AQ14: 241658 | AR14: 295354 | AS14: 202155 | AV14: 24444891 | AW14: 24423021 | AX14: 15336232 | AY14: 14845788 | AZ14: 10649173 | BA14: 7757475 | BB14: 12145 | BC14: 0 | BD14: 4674914 | BE14: 7088313 | BH14: 310950 | BI14: 415258 | BL14: 13343480 | BM14: 12266351 | BN14: 997445 | BO14: 917923 | BP14: 2230541 | BQ14: 4800787 | BX14: 7856469 | BY14: 3320560 | BZ14: 1368334 | CA14: 2088283 | CB14: 19046 | CC14: 9657 | CF14: 299926 | CG14: 252860 | CH14: 1569164 | CI14: 1794204 | CJ14: 8866295 | CK14: 2071749 | CN14: 30281 | CO14: 662023 | CP14: 8500722 | CQ14: 70925 | CR14: 335292 | CS14: 1338801 | CT14: 157711 | CU14: 37944 | CV14: 1982 | CW14: 1760 | CX14: 38016650 | CY14: 29638850 | CZ14: 62461541 | DA14: 54061871 | DB14: 8452563 | DC14: 8452563 | DD14: 13982173 | DE14: 13982173 | DF14: 12802057 | DG14: 12757918 | DJ14: 14115899 | DK14: 8435898 | DP14: 49352692 | DQ14: 43628552 | EP14: 13108849 | EQ14: 10433319 | ER14: 3107284 | ES14: 2431754 | EV14: 853490 | EW14: 899385 | FH14: 41121 | FI14: 52594 | FJ14: 365795 | FK14: 173450 | FN14: 265522 | FO14: 193985 | FP14: 894890 | FQ14: 395756 | FR14: 610078 | FS14: 629797 | FT14: 10001565 | FU14: 8001565 | FZ14: 76388 | GA14: 86787 | GB14: 13108849 | GC14: 10433319 | GD14: 62461541 | GE14: 54061871
A15: 20006 | B15: 0 | C15: 200466854 | D15: "YANGIYO'L YOG'-MOY" AJ | E15: 27 | F15: 22 | G15: 0 | H15: 8 | I15: 2020 | J15: 4 | K15: N | L15: 1 | M15: 30 | N15: 0 | O15: 44264.45 | P15: 43742333 | Q15: 46482344 | R15: 26813671 | S15: 29880530 | T15: 16928662 | U15: 16601814 | V15: 74882 | W15: 74882 | Z15: 74882 | AA15: 74882 | AB15: 1551476 | AC15: 1551476 | AD15: 536 | AE15: 536 | AL15: 1550940 | AM15: 1550940 | AN15: 1586341 | AO15: 5761806 | AP15: 77451 | AQ15: 159559 | AR15: 401169 | AS15: 295354 | AV15: 20619981 | AW15: 24444891 | AX15: 30951383 | AY15: 15336232 | AZ15: 7811552 | BA15: 10649173 | BB15: 77080 | BC15: 12145 | BD15: 23062751 | BE15: 4674914 | BH15: 388499 | BI15: 310950 | BL15: 10350372 | BM15: 13343480 | BO15: 991032 | BP15: 762559 | BQ15: 2230541 | BX15: 2144142 | BY15: 7856469 | BZ15: 1080732 | CA15: 1368334 | CB15: 13198 | CC15: 19046 | CF15: 221512 | CG15: 299926 | CH15: 6128229 | CI15: 1569164 | CJ15: 15729422 | CK15: 8866295 | CN15: 228814 | CO15: 30281 | CP15: 14103868 | CQ15: 8500722 | CR15: 1396740 | CS15: 335292 | CT15: 999850 | CU15: 157711 | CV15: 1761 | CW15: 1982 | CX15: 58421287 | CY15: 38016650 | CZ15: 79041268 | DA15: 62461541 | DB15: 8452563 | DC15: 8452563 | DD15: 13982173 | DE15: 13982173 | DF15: 12030422 | DG15: 12802057 | DJ15: 25325241 | DK15: 14115899 | DP15: 59790399 | DQ15: 49352692 | DR15: 44405 | DT15: 44405 | DV15: 44405 | EP15: 19206464 | EQ15: 13108849 | ER15: 3828865 | ES15: 3107284 | EV15: 752773 | EW15: 853490 | FH15: 187196 | FI15: 41121 | FJ15: 361790 | FK15: 365795 | FN15: 527815 | FO15: 265522 | FP15: 906155 | FQ15: 894890 | FR15: 980676 | FS15: 610078 | FT15: 15377599 | FU15: 10001565 | FZ15: 112460 | GA15: 76388 | GB15: 19250869 | GC15: 13108849 | GD15: 79041268 | GE15: 62461541
A16: 20006 | B16: 0 | C16: 200466854 | D16: "YANGIYO'L YOG'-MOY" AJ | E16: 27 | F16: 22 | G16: 0 | H16: 8 | I16: 2019 | J16: 4 | K16: N | L16: 2 | M16: 30 | N16: 0 | O16: 43997.685 | P16: 42338370 | Q16: 43742333 | R16: 25924747 | S16: 26813671 | T16: 16413623 | U16: 16928662 | W16: 74882 | AA16: 74882 | AB16: 1551476 | AC16: 1551476 | AD16: 536 | AE16: 536 | AL16: 1550940 | AM16: 1550940 | AN16: 90032 | AO16: 1586341 | AP16: 39370 | AQ16: 77451 | AR16: 272151 | AS16: 401169 | AV16: 18366652 | AW16: 20619981 | AX16: 23253138 | AY16: 30951383 | AZ16: 15902901 | BA16: 7811552 | BB16: 218545 | BC16: 77080 | BD16: 7131692 | BE16: 23062751 | BH16: 88373 | BI16: 388499 | BL16: 12413149 | BM16: 10350372 | BP16: 159385 | BQ16: 762559 | BX16: 9076440 | BY16: 2144142 | BZ16: 448085 | CA16: 1080732 | CB16: 14446 | CC16: 13198 | CF16: 86982 | CG16: 221512 | CH16: 2627811 | CI16: 6128229 | CJ16: 16264021 | CK16: 15729422 | CN16: 1088384 | CO16: 228814 | CP16: 15161537 | CQ16: 14103868 | CR16: 14100 | CS16: 1396740 | CT16: 820944 | CU16: 999850 | CV16: 1761 | CW16: 1761 | CX16: 52841386 | CY16: 58421287 | CZ16: 71208038 | DA16: 79041268 | DB16: 8452563 | DC16: 8452563 | DD16: 13982173 | DE16: 13982173 | DF16: 12289497 | DG16: 12030422 | DJ16: 24391431 | DK16: 25325241 | DP16: 59115664 | DQ16: 59790399 | DR16: 606406 | DS16: 44405 | DT16: 606406 | DU16: 44405 | DV16: 606406 | DW16: 44405 | EP16: 11485968 | EQ16: 19206464 | ER16: 7485968 | ES16: 3828865 | EV16: 1377308 | EW16: 752773 | FH16: 147615 | FI16: 187196 | FJ16: 2339696 | FK16: 361790 | FN16: 1334535 | FO16: 527815 | FP16: 244538 | FQ16: 906155 | FR16: 1562310 | FS16: 980676 | FT16: 4000000 | FU16: 15377599 | FZ16: 479966 | GA16: 112460 | GB16: 12092374 | GC16: 19250869 | GD16: 71208038 | GE16: 79041268
A17: 20006 | B17: 0 | C17: 200466854 | D17: "YANGIYO'L YOG'-MOY" AJ | E17: 27 | F17: 22 | G17: 0 | H17: 8 | I17: 2018 | J17: 4 | K17: N | L17: 1 | M17: 30 | N17: 0 | O17: 43544.547 | P17: 38932932 | Q17: 39502704 | R17: 23923877 | S17: 24901822 | T17: 15009055 | U17: 14600882 | W17: 926625 | AA17: 926625 | AB17: 1585976 | AC17: 1551476 | AD17: 536 | AE17: 536 | AL17: 1585440 | AM17: 1550940 | AN17: 86875 | AO17: 90032 | AP17: 31000 | AQ17: 39370 | AR17: 303658 | AS17: 272151 | AV17: 17016564 | AW17: 17480536 | AX17: 16452963 | AY17: 23253138 | AZ17: 11836039 | BA17: 15902901 | BC17: 218545 | BD17: 4616924 | BE17: 7131692 | BH17: 9788 | BI17: 88373 | BL17: 7348754 | BM17: 12413149 | BP17: 1151498 | BQ17: 159385 | BX17: 1408778 | BY17: 9076440 | BZ17: 921978 | CA17: 448085 | CC17: 14446 | CF17: 8692 | CG17: 86982 | CH17: 3857808 | CI17: 2627811 | CJ17: 15248287 | CK17: 16264021 | CN17: 783436 | CO17: 1088384 | CP17: 14454614 | CQ17: 15161537 | CR17: 10237 | CS17: 14100 | CT17: 944 | CU17: 820944 | CV17: 1761 | CW17: 1761 | CX17: 39062497 | CY17: 52841386 | CZ17: 56079061 | DA17: 70321922 | DB17: 8452563 | DC17: 8452563 | DD17: 13982173 | DE17: 13982173 | DF17: 11890634 | DG17: 11403381 | DJ17: 18841837 | DK17: 24391431 | DP17: 53167207 | DQ17: 58229548 | DS17: 606406 | DU17: 606406 | DW17: 606406 | EP17: 2911854 | EQ17: 11485968 | ER17: 2905854 | ES17: 7485968 | EV17: 352496 | EW17: 1377308 | FH17: 178572 | FI17: 147615 | FJ17: 911150 | FK17: 2339696 | FN17: 264278 | FO17: 1334535 | FP17: 210021 | FQ17: 244538 | FR17: 700720 | FS17: 1562310 | FU17: 4000000 | FV17: 6000 | FZ17: 288617 | GA17: 479966 | GB17: 2911854 | GC17: 12092374 | GD17: 56079061 | GE17: 70321922
A18: 20006 | B18: 0 | C18: 200670095 | D18: "QARSHI YOG'-EKSTRAKSIYA" AJ | E18: 10 | F18: 1 | G18: 0 | H18: 1 | I18: 2021 | J18: 4 | K18: N | L18: 2 | M18: 30 | N18: 0 | O18: 44621.453 | P18: 38755239 | Q18: 41486818 | R18: 17301764 | S18: 19150112 | T18: 21453475 | U18: 22336706 | AB18: 509341 | AC18: 509341 | AD18: 215004 | AE18: 215004 | AJ18: 11942 | AK18: 11942 | AL18: 282395 | AM18: 282395 | AN18: 588673 | AO18: 1982818 | AP18: 10383 | AQ18: 10383 | AR18: 373730 | AS18: 299376 | AV18: 22935602 | AW18: 25138624 | AX18: 35357080 | AY18: 49329800 | AZ18: 8849286 | BA18: 29709719 | BD18: 26507794 | BE18: 19620081 | BI18: 3489625 | BL18: 8448636 | BM18: 33056011 | BN18: 1522422 | BO18: 10772721 | BP18: 548462 | BQ18: 306115 | BV18: 30446 | BW18: 22434 | BX18: 6404756 | BY18: 23976058 | BZ18: 1331998 | CA18: 8588531 | CB18: 114557 | CC18: 75832 | CH18: 18417 | CI18: 87041 | CJ18: 677 | CK18: 603476 | CL18: 427 | CM18: 603476 | CR18: 250 | CT18: 26283 | CU18: 26283 | CW18: 12151188 | CX18: 43832676 | CY18: 98656383 | CZ18: 66768278 | DA18: 123795007 | DB18: 4772647 | DC18: 4772647 | DD18: 2707888 | DE18: 2707888 | DF18: 11998348 | DG18: 11985120 | DJ18: -3992054 | DK18: -13835557 | DL18: 2437191 | DM18: 28055601 | DP18: 17924020 | DQ18: 33685699 | DR18: 1016863 | DS18: 1016863 | EL18: 1016863 | EM18: 1016863 | EP18: 47827395 | EQ18: 89092445 | ER18: 28087395 | ES18: 31097565 | ET18: 602683 | EU18: 23677476 | EV18: 25277643 | EW18: 28095664 | EZ18: 434742 | FA18: 426833 | FH18: 200297 | FI18: 294354 | FJ18: 66697 | FK18: 92505 | FM18: 2085 | FN18: 3627 | FP18: 1233472 | FQ18: 666715 | FR18: 763362 | FS18: 1408714 | FT18: 17000000 | FU18: 57994880 | FV18: 2740000 | FZ18: 107555 | GA18: 110695 | GB18: 48844258 | GC18: 90109308 | GD18: 66768278 | GE18: 123795007
A19: 20006 | B19: 0 | C19: 200670095 | D19: "QARSHI YOG'-EKSTRAKSIYA" AJ | E19: 10 | F19: 1 | G19: 0 | H19: 1 | I19: 2020 | J19: 4 | K19: N | L19: 2 | M19: 30 | N19: 0 | O19: 44257.576 | P19: 36554370 | Q19: 38755239 | R19: 15120747 | S19: 17301764 | T19: 21433623 | U19: 21453475 | AB19: 509341 | AC19: 509341 | AD19: 215004 | AE19: 215004 | AJ19: 11942 | AK19: 11942 | AL19: 282395 | AM19: 282395 | AN19: 302740 | AO19: 588673 | AP19: 10383 | AQ19: 10383 | AR19: 523647 | AS19: 373730 | AV19: 22779734 | AW19: 22935602 | AX19: 28200670 | AY19: 35357080 | AZ19: 4456301 | BA19: 8849286 | BD19: 23744369 | BE19: 26507794 | BL19: 7568598 | BM19: 8448636 | BN19: 5195141 | BO19: 1522422 | BP19: 1282780 | BQ19: 548462 | BT19: 6666 | BV19: 12874 | BW19: 30446 | BX19: 6224967 | BY19: 6404756 | BZ19: 32126 | CA19: 1331998 | CC19: 114557 | CH19: 9185 | CI19: 18417 | CJ19: 934254 | CK19: 677 | CN19: 905574 | CO19: 427 | CP19: 28680 | CS19: 250 | CT19: 26283 | CU19: 26283 | CX19: 36729805 | CY19: 43832676 | CZ19: 59509539 | DA19: 66768278 | DB19: 4772647 | DC19: 4772647 | DD19: 2707888 | DE19: 2707888 | DF19: 10342534 | DG19: 11998348 | DJ19: -4039924 | DK19: -3992054 | DM19: 2437191 | DP19: 13783145 | DQ19: 17924020 | DR19: 422493 | DS19: 1016863 | EL19: 422493 | EM19: 1016863 | EP19: 45303931 | EQ19: 47827395 | ER19: 32079402 | ES19: 28087395 | ET19: 2933741 | EU19: 602683 | EV19: 28229203 | EW19: 25277643 | EZ19: 434742 | FA19: 434742 | FH19: 314663 | FI19: 200297 | FJ19: 51700 | FK19: 66697 | FN19: 122904 | FO19: 3627 | FP19: 1732589 | FQ19: 1233472 | FR19: 1123636 | FS19: 763362 | FT19: 13224529 | FU19: 17000000 | FW19: 2740000 | FZ19: 69965 | GA19: 107555 | GB19: 45726424 | GC19: 48844258 | GD19: 59509569 | GE19: 66768278
A20: 20006 | B20: 0 | C20: 200670095 | D20: "QARSHI YOG'-EKSTRAKSIYA" AJ | E20: 10 | F20: 1 | G20: 0 | H20: 1 | I20: 2019 | J20: 4 | K20: N | L20: 1 | M20: 30 | N20: 0 | O20: 43882.724 | P20: 32192851 | Q20: 36554370 | R20: 13377959 | S20: 15120747 | T20: 18814892 | U20: 21433623 | AB20: 732341 | AC20: 509341 | AD20: 215004 | AE20: 215004 | AJ20: 11942 | AK20: 11942 | AL20: 505395 | AM20: 282395 | AN20: 497788 | AO20: 302740 | AP20: 10383 | AQ20: 10383 | AR20: 555408 | AS20: 523647 | AV20: 20610812 | AW20: 22779734 | AX20: 25075365 | AY20: 28200670 | AZ20: 9446085 | BA20: 4456301 | BD20: 15629280 | BE20: 23744369 | BL20: 9836674 | BM20: 7568598 | BN20: 843875 | BO20: 5195141 | BP20: 242076 | BQ20: 1282780 | BT20: 51188 | BU20: 6666 | BV20: 47463 | BW20: 12874 | BX20: 8221968 | BY20: 6224967 | BZ20: 1262466 | CA20: 32126 | CH20: 11513 | CI20: 9185 | CJ20: 4340687 | CK20: 934254 | CN20: 572 | CO20: 905574 | CP20: 4335013 | CQ20: 28680 | CR20: 5102 | CT20: 26283 | CU20: 26283 | CX20: 39279009 | CY20: 36729805 | CZ20: 59889821 | DA20: 59509539 | DB20: 4772647 | DC20: 4772647 | DD20: 2707888 | DE20: 2707888 | DF20: 10247646 | DG20: 10342534 | DJ20: 6390216 | DK20: -4039924 | DP20: 24118397 | DQ20: 13783145 | DR20: 2878900 | DS20: 422493 | EJ20: 1900000 | EL20: 978900 | EM20: 422493 | EP20: 32892524 | EQ20: 45303901 | ER20: 9868252 | ES20: 32079372 | EU20: 2933741 | EV20: 6140150 | EW20: 28229203 | EZ20: 593217 | FA20: 434742 | FH20: 999805 | FI20: 314633 | FJ20: 426748 | FK20: 51700 | FL20: 47734 | FN20: 499023 | FO20: 122904 | FP20: 727605 | FQ20: 1732589 | FR20: 398054 | FS20: 1123636 | FT20: 23024272 | FU20: 13224529 | FZ20: 35916 | GA20: 69965 | GB20: 35771424 | GC20: 45726394 | GD20: 59889821 | GE20: 59509539
A21: 20006 | B21: 0 | C21: 200670095 | D21: "QARSHI YOG'-EKSTRAKSIYA" AJ | E21: 10 | F21: 1 | G21: 0 | H21: 1 | I21: 2018 | J21: 4 | K21: N | L21: 1 | M21: 30 | N21: 0 | O21: 43511.626 | P21: 29022058 | Q21: 30225010 | R21: 12024197 | S21: 12821659 | T21: 16997861 | U21: 17403351 | AB21: 766841 | AC21: 732341 | AD21: 215004 | AE21: 215004 | AJ21: 11942 | AK21: 11942 | AL21: 539895 | AM21: 505395 | AN21: 513260 | AO21: 497788 | AP21: 10383 | AQ21: 10383 | AR21: 578029 | AS21: 555408 | AV21: 18866374 | AW21: 19199271 | AX21: 10412913 | AY21: 25075365 | AZ21: 6725532 | BA21: 9446085 | BD21: 3687381 | BE21: 15629280 | BL21: 4364393 | BM21: 9836674 | BN21: 347597 | BO21: 843875 | BP21: 236062 | BQ21: 242076 | BT21: 1245671 | BU21: 51188 | BV21: 68023 | BW21: 47463 | BX21: 2517022 | BY21: 8221968 | BZ21: 265298 | CA21: 1262466 | CH21: 32317 | CI21: 11513 | CJ21: 7274295 | CK21: 4340687 | CN21: 13007 | CO21: 572 | CP21: 7248247 | CQ21: 4335013 | CR21: 13041 | CS21: 5102 | CT21: 26283 | CU21: 26283 | CX21: 22077884 | CY21: 39279009 | CZ21: 40944258 | DA21: 58478280 | DB21: 4772647 | DC21: 4772647 | DD21: 2707888 | DE21: 2707888 | DF21: 8704826 | DG21: 8836105 | DJ21: 5972767 | DK21: 6390216 | DP21: 22158128 | DQ21: 22706856 | DR21: 1117220 | DS21: 2878900 | EJ21: 649773 | EK21: 1900000 | EL21: 467447 | EM21: 978900 | EP21: 17668910 | EQ21: 32892524 | ER21: 8978910 | ES21: 9868252 | EV21: 2004504 | EW21: 6140150 | EZ21: 1235305 | FA21: 593217 | FH21: 53719 | FI21: 999805 | FJ21: 3319504 | FK21: 426748 | FL21: 39918 | FM21: 47734 | FN21: 867171 | FO21: 499023 | FP21: 1111142 | FQ21: 727605 | FR21: 330691 | FS21: 398054 | FU21: 23024272 | FX21: 8690000 | FZ21: 16956 | GA21: 35916 | GB21: 18786130 | GC21: 35771424 | GD21: 40944258 | GE21: 58478280
A22: 20006 | B22: 0 | C22: 200930049 | D22: YOG`GAR AJ | E22: 35 | F22: 9 | G22: 0 | H22: 1 | I22: 2021 | J22: 4 | K22: N | L22: 2 | M22: 30 | N22: 0 | O22: 44664.438 | P22: 10176690 | Q22: 10203817 | R22: 7071583 | S22: 7379656 | T22: 3105107 | U22: 2824161 | V22: 15049 | W22: 15049 | X22: 2947 | Y22: 3699 | Z22: 12102 | AA22: 11350 | AB22: 151215 | AC22: 151215 | AD22: 1215 | AE22: 1215 | AF22: 150000 | AG22: 150000 | AP22: 426716 | AQ22: 512888 | AR22: 163020 | AS22: 110789 | AV22: 3858160 | AW22: 3610403 | AX22: 6429817 | AY22: 6485315 | AZ22: 4093609 | BA22: 1822448 | BC22: 1859681 | BD22: 2336208 | BE22: 2803186 | BL22: 4839014 | BM22: 3465451 | BP22: 1724868 | BQ22: 918473 | BV22: 237404 | BW22: 7333 | BX22: 75408 | BY22: 1699394 | BZ22: 2753537 | CA22: 449530 | CB22: 47797 | CC22: 45412 | CI22: 345309 | CJ22: 16037 | CK22: 4716 | CN22: 8295 | CO22: 1967 | CQ22: 2749 | CR22: 7742 | CX22: 11284868 | CY22: 9955482 | CZ22: 15143028 | DA22: 13565885 | DB22: 4093375 | DC22: 4093375 | DF22: 3153869 | DG22: 1677036 | DJ22: 1962589 | DK22: 45347 | DN22: 3716069 | DP22: 12925902 | DQ22: 5815758 | EP22: 2217126 | EQ22: 7750127 | ER22: 2017126 | ES22: 7368309 | EV22: 1033119 | EW22: 1096467 | FI22: 5079908 | FJ22: 364245 | FK22: 295255 | FN22: 351185 | FO22: 1828 | FQ22: 171263 | FR22: 192300 | FS22: 487764 | FU22: 181818 | FV22: 200000 | FW22: 200000 | FZ22: 76277 | GA22: 235824 | GB22: 2217126 | GC22: 7750127 | GD22: 15143028 | GE22: 13565885
A23: 60131 | B23: 0 | C23: 200930049 | D23: YOG`GAR AJ | E23: 35 | F23: 9 | G23: 0 | H23: 1 | I23: 2020 | J23: 4 | K23: N | L23: 1 | M23: 30 | N23: 0 | O23: 44209.598 | P23: 10176690 | Q23: 10176690 | R23: 6980732 | S23: 7071583 | T23: 3195958 | U23: 3105107 | V23: 15049 | W23: 15049 | X23: 2759 | Y23: 2947 | Z23: 12290 | AA23: 12102 | AB23: 151251 | AC23: 151251 | AD23: 1251 | AE23: 1251 | AF23: 150000 | AG23: 150000 | AH23: 0 | AJ23: 0 | AL23: 0 | AN23: 0 | AP23: 426716 | AQ23: 426716 | AR23: 202465 | AS23: 163020 | AT23: 0 | AV23: 3988680 | AW23: 3858196 | AX23: 8492107 | AY23: 6429817 | AZ23: 5620014 | BA23: 4093609 | BB23: 0 | BD23: 2872093 | BE23: 2336208 | BF23: 0 | BH23: 0 | BJ23: 0 | BL23: 4772154 | BM23: 4839014 | BN23: 0 | BP23: 1770515 | BQ23: 1724868 | BR23: 0 | BT23: 0 | BV23: 107453 | BW23: 237404 | BX23: 434648 | BY23: 75408 | BZ23: 2322931 | CA23: 2753537 | CB23: 47797 | CC23: 47797 | CD23: 0 | CF23: 0 | CH23: 88810 | CJ23: 0 | CK23: 16037 | CL23: 0 | CN23: 0 | CO23: 8295 | CP23: 0 | CR23: 0 | CS23: 7742 | CT23: 0 | CV23: 0 | CX23: 13264261 | CY23: 11284868 | CZ23: 17252941 | DA23: 15143064 | DB23: 4093375 | DC23: 4093375 | DD23: 0 | DF23: 3153869 | DG23: 3153869 | DH23: 0 | DJ23: 543536 | DK23: 1962589 | DL23: 0 | DN23: 3716069 | DO23: 3716069 | DP23: 11506849 | DQ23: 12925902 | DR23: 0 | DT23: 0 | DV23: 0 | DX23: 0 | DZ23: 0 | EB23: 0 | ED23: 0 | EF23: 0 | EH23: 0 | EJ23: 0 | EL23: 0 | EN23: 0 | EP23: 5746092 | EQ23: 2217162 | ER23: 3008273 | ES23: 2017162 | ET23: 0 | EV23: 1512139 | EW23: 1033119 | EX23: 0 | EZ23: 0 | FB23: 0 | FD23: 0 | FF23: 0 | FH23: 3399 | FJ23: 125748 | FK23: 364245 | FL23: 0 | FN23: 340266 | FO23: 351185 | FP23: 754883 | FR23: 215918 | FS23: 192336 | FT23: 2477819 | FV23: 260000 | FW23: 200000 | FX23: 0 | FZ23: 55920 | GA23: 76277 | GB23: 5746092 | GC23: 2217162 | GD23: 17252941 | GE23: 15143064
A24: 20006 | B24: 0 | C24: 200930049 | D24: YOG`GAR AJ | E24: 35 | F24: 9 | G24: 0 | H24: 1 | I24: 2019 | J24: 4 | K24: N | L24: 1 | M24: 30 | N24: 0 | O24: 43879.874 | P24: 9322105 | Q24: 9597307 | R24: 6084929 | S24: 6368075 | T24: 3237176 | U24: 3229232 | V24: 15049 | W24: 15049 | X24: 1442 | Y24: 2195 | Z24: 13607 | AA24: 12854 | AB24: 151215 | AC24: 151215 | AD24: 1215 | AE24: 1215 | AF24: 150000 | AG24: 150000 | AN24: 124020 | AQ24: 422075 | AR24: 211375 | AS24: 256572 | AV24: 3737393 | AW24: 4071948 | AX24: 19942373 | AY24: 11712756 | AZ24: 14420867 | BA24: 3996582 | BD24: 5521506 | BE24: 7716174 | BL24: 3307895 | BM24: 6567410 | BP24: 321710 | BQ24: 1497591 | BV24: 196837 | BW24: 125764 | BX24: 1642965 | BY24: 2025246 | BZ24: 1056353 | CA24: 2739864 | CB24: 47797 | CC24: 47797 | CH24: 42233 | CI24: 131148 | CJ24: 113826 | CK24: 216640 | CN24: 6746 | CO24: 49362 | CP24: 49469 | CR24: 57611 | CS24: 167278 | CX24: 23364094 | CY24: 18496806 | CZ24: 27101487 | DA24: 22568754 | DB24: 4093375 | DC24: 4093375 | DF24: 1241684 | DG24: 2797795 | DJ24: 2820741 | DK24: 2898705 | DN24: 3716592 | DO24: 3716592 | DP24: 11872392 | DQ24: 13506467 | EP24: 15229095 | EQ24: 9062287 | ER24: 8072645 | ES24: 3136211 | EV24: 6022404 | EW24: 1075220 | FH24: 45510 | FJ24: 779058 | FK24: 1531723 | FN24: 839105 | FO24: 169225 | FP24: 1455 | FQ24: 42607 | FR24: 366892 | FS24: 205885 | FT24: 6906450 | FU24: 5045576 | FV24: 250000 | FW24: 880500 | FZ24: 18221 | GA24: 111551 | GB24: 15229095 | GC24: 9062287 | GD24: 27101487 | GE24: 22568754
A25: 20006 | B25: 0 | C25: 200930049 | D25: YOG`GAR AJ | E25: 35 | F25: 9 | G25: 0 | H25: 1 | I25: 2018 | J25: 4 | K25: N | L25: 2 | M25: 30 | N25: 0 | O25: 43537.405 | P25: 9213443 | Q25: 9322105 | R25: 5739706 | S25: 6084929 | T25: 3473737 | U25: 3237176 | V25: 15049 | W25: 15049 | X25: 1254 | Y25: 1442 | Z25: 13795 | AA25: 13607 | AB25: 185715 | AC25: 151215 | AD25: 1215 | AE25: 1215 | AF25: 184500 | AG25: 150000 | AN25: 124020 | AO25: 124020 | AR25: 170650 | AS25: 211375 | AV25: 3967917 | AW25: 3737393 | AX25: 4107960 | AY25: 19942373 | AZ25: 2979906 | BA25: 14420867 | BD25: 1128054 | BE25: 5521506 | BL25: 4208839 | BM25: 3307895 | BQ25: 321710 | BV25: 122912 | BW25: 196837 | BX25: 3735230 | BY25: 1642965 | BZ25: 247058 | CA25: 1056353 | CB25: 58322 | CC25: 47797 | CH25: 45317 | CI25: 42233 | CJ25: 143786 | CK25: 113826 | CN25: 143786 | CO25: 6746 | CQ25: 49469 | CS25: 57611 | CX25: 8460585 | CY25: 23364094 | CZ25: 12428502 | DA25: 27101487 | DB25: 4093375 | DC25: 4093375 | DF25: 1419885 | DG25: 1241684 | DJ25: 1826964 | DK25: 2820741 | DO25: 3716592 | DP25: 7340224 | DQ25: 11872392 | EP25: 5088278 | EQ25: 15229095 | ER25: 2115450 | ES25: 8072645 | EV25: 649182 | EW25: 6022404 | FH25: 112163 | FI25: 45510 | FJ25: 805858 | FK25: 779058 | FN25: 303968 | FO25: 839105 | FP25: 5827 | FQ25: 1455 | FR25: 147966 | FS25: 366892 | FT25: 2722828 | FU25: 6906450 | FV25: 250000 | FW25: 250000 | FZ25: 90486 | GA25: 18221 | GB25: 5088278 | GC25: 15229095 | GD25: 12428502 | GE25: 27101487
A26: 20006 | B26: 0 | C26: 200595877 | D26: "YEROSTIGAZ" AJ | E26: 27 | F26: 16 | G26: 0 | H26: 1 | I26: 2021 | J26: 4 | K26: N | L26: 2 | M26: 30 | N26: 0 | O26: 44619.886 | P26: 7161829 | Q26: 7163161 | R26: 3979643 | S26: 4386868 | T26: 3182186 | U26: 2776293 | V26: 1949 | W26: 1949 | X26: 891 | Y26: 1200 | Z26: 1058 | AA26: 749 | AB26: 20437 | AC26: 20437 | AD26: 205 | AE26: 205 | AH26: 20232 | AI26: 20232 | AV26: 3203681 | AW26: 2797479 | AX26: 1753197 | AY26: 1459124 | AZ26: 1753197 | BA26: 1459124 | BH26: 149357 | BI26: 143389 | BL26: 5941938 | BM26: 10302419 | BP26: 5789622 | BQ26: 7008656 | BX26: 58786 | BY26: 3189567 | BZ26: 15433 | CA26: 20609 | CB26: 434 | CC26: 1379 | CH26: 77663 | CI26: 82208 | CJ26: 1216812 | CK26: 5330 | CN26: 1214484 | CO26: 5318 | CR26: 2328 | CS26: 12 | CV26: 12330 | CW26: 12330 | CX26: 9073634 | CY26: 11922592 | CZ26: 12277315 | DA26: 14720071 | DB26: 677310 | DC26: 677310 | DD26: 601753 | DE26: 601753 | DF26: 5049241 | DG26: 5049241 | DJ26: 5150926 | DK26: 7081657 | DP26: 11479230 | DQ26: 13409961 | EP26: 798085 | EQ26: 1310110 | ER26: 798085 | ES26: 1281711 | EV26: 1407 | EW26: 209123 | FI26: 3863 | FJ26: 326445 | FK26: 353265 | FO26: 2 | FP26: 84563 | FQ26: 4640 | FR26: 369298 | FS26: 685363 | FW26: 28399 | FZ26: 16372 | GA26: 25455 | GB26: 798085 | GC26: 1310110 | GD26: 12277315 | GE26: 14720071
A27: 20006 | B27: 0 | C27: 200595877 | D27: "YEROSTIGAZ" AJ | E27: 27 | F27: 16 | G27: 0 | H27: 1 | I27: 2020 | J27: 4 | K27: N | L27: 1 | M27: 30 | N27: 0 | O27: 44242.694 | P27: 6994308.8 | Q27: 7161828.6 | R27: 3560122.5 | S27: 3979642.7 | T27: 3434186.4 | U27: 3182185.9 | V27: 1948.56 | W27: 1948.56 | X27: 581.85 | Y27: 890.53 | Z27: 1366.71 | AA27: 1058.03 | AB27: 205.33 | AC27: 20436.85 | AD27: 205.33 | AE27: 205.33 | AF27: 0 | AG27: 0 | AH27: 0 | AI27: 20231.52 | AJ27: 0 | AK27: 0 | AL27: 0 | AM27: 0 | AN27: 0 | AO27: 0 | AP27: 0 | AQ27: 0 | AR27: 0 | AS27: 0 | AT27: 0 | AU27: 0 | AV27: 3435758.4 | AW27: 3203680.8 | AX27: 1862462.7 | AY27: 1753196.7 | AZ27: 1862462.7 | BA27: 1753196.7 | BB27: 0 | BC27: 0 | BD27: 0 | BE27: 0 | BF27: 0 | BG27: 0 | BH27: 5002.61 | BI27: 149357.09 | BJ27: 0 | BK27: 0 | BL27: 1793026.9 | BM27: 5941937.6 | BN27: 0 | BO27: 0 | BP27: 689173.49 | BQ27: 5789621.6 | BR27: 0 | BS27: 0 | BT27: 0 | BU27: 0 | BV27: 0 | BW27: 0 | BX27: 997079.53 | BY27: 58785.69 | BZ27: 6000.23 | CA27: 15433.17 | CB27: 1933.9 | CC27: 434.1 | CD27: 0 | CE27: 0 | CF27: 0 | CG27: 0 | CH27: 98839.7 | CI27: 77663.03 | CJ27: 108439.44 | CK27: 1216812.5 | CL27: 0 | CM27: 0 | CN27: 107106.14 | CO27: 1214484.5 | CP27: 0 | CQ27: 0 | CR27: 1333.3 | CS27: 2328.02 | CT27: 0 | CU27: 0 | CV27: 12330.13 | CW27: 12330.13 | CX27: 3781261.8 | CY27: 9073634 | CZ27: 7217020.2 | DA27: 12277315 | DB27: 677310 | DC27: 677310 | DD27: 601753.05 | DE27: 601753.05 | DF27: 4842600.4 | DG27: 5049241.3 | DH27: 0 | DI27: 0 | DJ27: 398402.65 | DK27: 5150925.9 | DL27: 0 | DM27: 0 | DN27: 0 | DO27: 0 | DP27: 6520066.1 | DQ27: 11479230 | DR27: 0 | DS27: 0 | DT27: 0 | DU27: 0 | DV27: 0 | DW27: 0 | DX27: 0 | DY27: 0 | DZ27: 0 | EA27: 0 | EB27: 0 | EC27: 0 | ED27: 0 | EE27: 0 | EF27: 0 | EG27: 0 | EH27: 0 | EI27: 0 | EJ27: 0 | EK27: 0 | EL27: 0 | EM27: 0 | EN27: 0 | EO27: 0 | EP27: 696954.05 | EQ27: 798084.58 | ER27: 696954.05 | ES27: 798084.58 | ET27: 0 | EU27: 0 | EV27: 8673.84 | EW27: 1407.06 | EX27: 0 | EY27: 0 | EZ27: 0 | FA27: 0 | FB27: 0 | FC27: 0 | FD27: 0 | FE27: 0 | FF27: 0 | FG27: 0 | FH27: 0 | FI27: 0 | FJ27: 383718.41 | FK27: 326445.24 | FL27: 0 | FM27: 0 | FN27: 34198.19 | FO27: 0 | FP27: 0 | FQ27: 84563.23 | FR27: 244663.57 | FS27: 369296.67 | FT27: 0 | FU27: 0 | FV27: 0 | FW27: 0 | FX27: 0 | FY27: 0 | FZ27: 25700.04 | GA27: 16372.38 | GB27: 696954.05 | GC27: 798084.58 | GD27: 7217020.2 | GE27: 12277315
A28: 20006 | B28: 0 | C28: 200595877 | D28: "YEROSTIGAZ" AJ | E28: 27 | F28: 16 | G28: 0 | H28: 1 | I28: 2019 | J28: 4 | K28: N | L28: 1 | M28: 30 | N28: 0 | O28: 43876.893 | P28: 6566119 | Q28: 6565983.8 | R28: 3117837.5 | S28: 3368444.2 | T28: 3448281.4 | U28: 3197539.6 | V28: 1948.56 | W28: 1948.56 | X28: 273.16 | Y28: 581.85 | Z28: 1675.4 | AA28: 1366.71 | AB28: 205.33 | AC28: 205.33 | AD28: 205.33 | AE28: 205.33 | AF28: 0 | AG28: 0 | AH28: 0 | AI28: 0 | AJ28: 0 | AK28: 0 | AL28: 0 | AM28: 0 | AN28: 0 | AO28: 0 | AP28: 0 | AQ28: 0 | AR28: 0 | AS28: 0 | AT28: 0 | AU28: 0 | AV28: 3450162.1 | AW28: 3199111.6 | AX28: 2042345.2 | AY28: 1862462.7 | AZ28: 2042345.2 | BA28: 1862462.7 | BB28: 0 | BC28: 0 | BD28: 0 | BE28: 0 | BF28: 0 | BG28: 0 | BH28: 118759.5 | BI28: 5002.61 | BJ28: 0 | BK28: 0 | BL28: 608726.32 | BM28: 1793026.9 | BN28: 0 | BO28: 0 | BP28: 54164.39 | BQ28: 689173.49 | BR28: 0 | BS28: 0 | BT28: 0 | BU28: 0 | BV28: 0 | BW28: 0 | BX28: 499684.08 | BY28: 997079.53 | BZ28: 0 | CA28: 6000.23 | CB28: 0.47 | CC28: 1933.9 | CD28: 0 | CE28: 0 | CF28: 0 | CG28: 0 | CH28: 54877.38 | CI28: 98839.7 | CJ28: 1.32 | CK28: 108439.44 | CL28: 0 | CM28: 0 | CN28: 0 | CO28: 107106.14 | CP28: 0 | CQ28: 0 | CR28: 1.32 | CS28: 1333.3 | CT28: 0 | CU28: 0 | CV28: 12330.13 | CW28: 12330.13 | CX28: 2782162.5 | CY28: 3781261.8 | CZ28: 6232324.7 | DA28: 6980373.4 | DB28: 677310 | DC28: 677310 | DD28: 601753.05 | DE28: 601753.05 | DF28: 4574681.8 | DG28: 4605953.6 | DH28: 0 | DI28: 0 | DJ28: -3155119.3 | DK28: 398402.65 | DL28: 0 | DM28: 0 | DN28: 0 | DO28: 0 | DP28: 2698625.5 | DQ28: 6283419.3 | DR28: 0 | DS28: 0 | DT28: 0 | DU28: 0 | DV28: 0 | DW28: 0 | DX28: 0 | DY28: 0 | DZ28: 0 | EA28: 0 | EB28: 0 | EC28: 0 | ED28: 0 | EE28: 0 | EF28: 0 | EG28: 0 | EH28: 0 | EI28: 0 | EJ28: 0 | EK28: 0 | EL28: 0 | EM28: 0 | EN28: 0 | EO28: 0 | EP28: 3533699.1 | EQ28: 696954.05 | ER28: 3531971.1 | ES28: 696954.05 | ET28: 0 | EU28: 0 | EV28: 908460.4 | EW28: 8673.84 | EX28: 0 | EY28: 0 | EZ28: 0 | FA28: 0 | FB28: 0 | FC28: 0 | FD28: 0 | FE28: 0 | FF28: 0 | FG28: 0 | FH28: 1717.07 | FI28: 0 | FJ28: 1056823.3 | FK28: 383718.41 | FL28: 0 | FM28: 0 | FN28: 595957.14 | FO28: 34198.19 | FP28: 0 | FQ28: 0 | FR28: 913961.13 | FS28: 244663.57 | FT28: 0 | FU28: 0 | FV28: 1728 | FW28: 0 | FX28: 0 | FY28: 0 | FZ28: 55052.09 | GA28: 25700.04 | GB28: 3533699.1 | GC28: 696954.05 | GD28: 6232324.7 | GE28: 6980373.4
A29: 20006 | B29: 0 | C29: 200595877 | D29: "YEROSTIGAZ" AJ | E29: 27 | F29: 16 | G29: 0 | H29: 1 | I29: 2018 | J29: 4 | K29: N | L29: 1 | M29: 30 | N29: 0 | O29: 43507.829 | P29: 6291881 | Q29: 6291764 | R29: 2759272 | S29: 3006686 | T29: 3532609 | U29: 3285078 | V29: 1375 | W29: 1949 | X29: 242 | Y29: 273 | Z29: 1133 | AA29: 1676 | AB29: 205 | AC29: 205 | AD29: 205 | AE29: 205 | AF29: 0 | AG29: 0 | AH29: 0 | AI29: 0 | AJ29: 0 | AK29: 0 | AL29: 0 | AM29: 0 | AN29: 0 | AO29: 0 | AP29: 0 | AQ29: 0 | AR29: 0 | AS29: 0 | AT29: 0 | AU29: 0 | AV29: 3533947 | AW29: 3286959 | AX29: 2092362 | AY29: 2042345 | AZ29: 2092362 | BA29: 2042345 | BB29: 0 | BC29: 0 | BD29: 0 | BE29: 0 | BF29: 0 | BG29: 0 | BH29: 54369 | BI29: 118760 | BJ29: 0 | BK29: 0 | BL29: 39785 | BM29: 608726 | BN29: 0 | BO29: 0 | BP29: 4865 | BQ29: 54164 | BR29: 0 | BS29: 0 | BT29: 0 | BU29: 0 | BV29: 20 | BW29: 0 | BX29: 17355 | BY29: 499684 | BZ29: 13222 | CA29: 0 | CB29: 442 | CC29: 1 | CD29: 0 | CE29: 0 | CF29: 0 | CG29: 0 | CH29: 3881 | CI29: 54877 | CJ29: 4067 | CK29: 1 | CL29: 0 | CM29: 0 | CN29: 0 | CO29: 0 | CP29: 0 | CQ29: 0 | CR29: 4067 | CS29: 1 | CT29: 0 | CU29: 0 | CV29: 12330 | CW29: 12330 | CX29: 2202913 | CY29: 2782162 | CZ29: 5736860 | DA29: 6069121 | DB29: 677310 | DC29: 677310 | DD29: 601753 | DE29: 601753 | DF29: 4381316 | DG29: 4411478 | DH29: 0 | DI29: 0 | DJ29: -3356669 | DK29: -3155119 | DL29: 0 | DM29: 0 | DN29: 0 | DO29: 0 | DP29: 2303710 | DQ29: 2535422 | DR29: 0 | DS29: 0 | DT29: 0 | DU29: 0 | DV29: 0 | DW29: 0 | DX29: 0 | DY29: 0 | DZ29: 0 | EA29: 0 | EB29: 0 | EC29: 0 | ED29: 0 | EE29: 0 | EF29: 0 | EG29: 0 | EH29: 0 | EI29: 0 | EJ29: 0 | EK29: 0 | EL29: 0 | EM29: 0 | EN29: 0 | EO29: 0 | EP29: 3433150 | EQ29: 3533699 | ER29: 3431422 | ES29: 3531971 | ET29: 0 | EU29: 0 | EV29: 1881561 | EW29: 908461 | EX29: 0 | EY29: 0 | EZ29: 0 | FA29: 0 | FB29: 0 | FC29: 0 | FD29: 0 | FE29: 0 | FF29: 0 | FG29: 0 | FH29: 932773 | FI29: 1717 | FJ29: 180195 | FK29: 1056823 | FL29: 0 | FM29: 0 | FN29: 156022 | FO29: 595957 | FP29: 0 | FQ29: 0 | FR29: 267262 | FS29: 913961 | FT29: 0 | FU29: 0 | FV29: 1728 | FW29: 1728 | FX29: 0 | FY29: 0 | FZ29: 13609 | GA29: 55052 | GB29: 3433150 | GC29: 3533699 | GD29: 5736860 | GE29: 6069121
A30: 20006 | B30: 0 | C30: 200002854 | D30: "JANUBSANOATMONTAJ" AJ | E30: 12 | F30: 1 | G30: 0 | H30: 1 | I30: 2021 | J30: 4 | K30: N | L30: 2 | M30: 30 | N30: 0 | O30: 44691.537 | P30: 29929641 | Q30: 35339106 | R30: 6544899 | S30: 11062046 | T30: 23384742 | U30: 24277060 | V30: 1162 | W30: 1162 | X30: 1162 | Y30: 1162 | Z30: 0 | AA30: 0 | AB30: 8928 | AC30: 8928 | AD30: 8928 | AE30: 8928 | AP30: 736366 | AQ30: 344680 | AV30: 24130036 | AW30: 24630668 | AX30: 8748785 | AY30: 9807735 | AZ30: 7310198 | BA30: 8702322 | BB30: 264441 | BC30: 0 | BD30: 1174146 | BE30: 1105413 | BH30: 0 | BI30: 0 | BL30: 75479688 | BM30: 92686231 | BP30: 61473743 | BQ30: 83951446 | BR30: 58898450 | BS30: 78468313 | BV30: 14978 | BW30: 40797 | BX30: 13002587 | BY30: 7558109 | BZ30: 775690 | CA30: 1626 | CB30: 4333 | CC30: 0 | CH30: 208357 | CI30: 1134253 | CJ30: 4950169 | CK30: 601917 | CN30: 4045428 | CO30: 597998 | CP30: 892109 | CQ30: 0 | CR30: 12632 | CS30: 3919 | CT30: 0 | CU30: 275000 | CV30: 0 | CW30: 0 | CX30: 89178642 | CY30: 103370883 | CZ30: 113308678 | DA30: 128001551 | DB30: 1633137 | DC30: 1633137 | DD30: 28485952 | DE30: 28485952 | DF30: 10635874 | DG30: 12431004 | DJ30: 1797941 | DK30: 1691711 | DP30: 42552904 | DQ30: 44241804 | EP30: 70755774 | EQ30: 83759747 | ER30: 70755774 | ES30: 83759747 | EV30: 52323795 | EW30: 78333978 | EX30: 50056498 | EY30: 76641872 | FA30: 0 | FH30: 16503347 | FI30: 3196471 | FJ30: 172410 | FK30: 689029 | FM30: 0 | FN30: 325134 | FO30: 233647 | FP30: 5834 | FQ30: 0 | FR30: 1018539 | FS30: 940042 | FV30: 0 | FW30: 0 | FZ30: 406715 | GA30: 366580 | GB30: 70755774 | GC30: 83759747 | GD30: 113308678 | GE30: 128001551
A31: 20006 | B31: 0 | C31: 200002854 | D31: "JANUBSANOATMONTAJ" AJ | E31: 12 | F31: 1 | G31: 0 | H31: 1 | I31: 2020 | J31: 4 | K31: N | L31: 2 | M31: 30 | N31: 0 | O31: 44303.46 | P31: 29326938 | Q31: 29929641 | R31: 2991007 | S31: 6544899 | T31: 26335931 | U31: 23384742 | V31: 1162 | W31: 1162 | X31: 1162 | Y31: 1162 | Z31: 0 | AA31: 0 | AB31: 8928 | AC31: 8928 | AD31: 8928 | AE31: 8928 | AQ31: 736366 | AV31: 26344859 | AW31: 24130036 | AX31: 7155635 | AY31: 8748785 | AZ31: 6757080 | BA31: 7310198 | BB31: 0 | BC31: 264441 | BD31: 398555 | BE31: 1174146 | BH31: 390 | BI31: 0 | BL31: 43636157 | BM31: 75479688 | BP31: 38220441 | BQ31: 61473743 | BS31: 58898450 | BV31: 11396 | BW31: 14978 | BX31: 0 | BY31: 13002587 | BZ31: 5010416 | CA31: 775690 | CB31: 4350 | CC31: 4333 | CH31: 389554 | CI31: 208357 | CJ31: 4518546 | CK31: 4950169 | CN31: 4495554 | CO31: 4045428 | CP31: 517 | CQ31: 892109 | CR31: 22475 | CS31: 12632 | CT31: 90000 | CU31: 0 | CV31: 0 | CW31: 0 | CX31: 55400728 | CY31: 89178642 | CZ31: 81745587 | DA31: 113308678 | DB31: 1633137 | DC31: 1633137 | DD31: 28485952 | DE31: 28485952 | DF31: 2853911 | DG31: 10635874 | DJ31: 7325796 | DK31: 1797941 | DP31: 40298796 | DQ31: 42552904 | EP31: 41446791 | EQ31: 70755774 | ER31: 41446791 | ES31: 70755774 | EV31: 34002810 | EW31: 52323795 | EY31: 50056498 | FA31: 0 | FH31: 0 | FI31: 16503347 | FJ31: 575371 | FK31: 172410 | FN31: 238386 | FO31: 325134 | FP31: 5834 | FQ31: 5834 | FR31: 1210463 | FS31: 1018539 | FV31: 0 | FW31: 0 | FZ31: 5413927 | GA31: 406715 | GB31: 41446791 | GC31: 70755774 | GD31: 81745587 | GE31: 113308678
A32: 20006 | B32: 0 | C32: 200002854 | D32: "JANUBSANOATMONTAJ" AJ | E32: 12 | F32: 1 | G32: 0 | H32: 1 | I32: 2019 | J32: 4 | K32: N | L32: 2 | M32: 30 | N32: 0 | O32: 44013.63 | P32: 4441262 | Q32: 29379938 | R32: 2929584 | S32: 2998957 | T32: 1511678 | U32: 26380981 | V32: 1162 | W32: 1162 | X32: 1162 | Y32: 1162 | Z32: 0 | AA32: 0 | AB32: 8590 | AC32: 8928 | AD32: 8590 | AE32: 8928 | AV32: 1520268 | AW32: 26389909 | AX32: 2036828 | AY32: 7165222 | AZ32: 1877340 | BA32: 6766667 | BB32: 0 | BD32: 159488 | BE32: 398555 | BH32: 840 | BI32: 390 | BL32: 18099356 | BM32: 43626495 | BP32: 2688471 | BQ32: 38210978 | BV32: 8385 | BW32: 11278 | BX32: 12784715 | BY32: 0 | CA32: 5011195 | CC32: 4350 | CH32: 2617785 | CI32: 388694 | CJ32: 2098015 | CK32: 4517319 | CN32: 1569845 | CO32: 4495554 | CP32: 22632 | CQ32: 517 | CR32: 505538 | CS32: 21248 | CU32: 90000 | CV32: 28802 | CW32: 0 | CX32: 22263841 | CY32: 55399426 | CZ32: 23784109 | DA32: 81789335 | DB32: 967500 | DC32: 1633137 | DE32: 28485952 | DF32: 654735 | DG32: 2853911 | DJ32: 3373120 | DK32: 7362340 | DP32: 4995355 | DQ32: 40335340 | EP32: 18788754 | EQ32: 41453995 | ER32: 17088754 | ES32: 41453995 | EV32: 13376998 | EW32: 34002090 | FH32: 324290 | FI32: 0 | FJ32: 1149512 | FK32: 585582 | FN32: 535810 | FO32: 238386 | FP32: 5903 | FQ32: 5834 | FR32: 586387 | FS32: 1207909 | FV32: 1700000 | FW32: 0 | FZ32: 1109854 | GA32: 5414194 | GB32: 18788754 | GC32: 41453995 | GD32: 23784109 | GE32: 81789335
A33: 20006 | B33: 0 | C33: 200002854 | D33: "JANUBSANOATMONTAJ" AJ | E33: 12 | F33: 1 | G33: 0 | H33: 1 | I33: 2018 | J33: 4 | K33: N | L33: 2 | M33: 30 | N33: 0 | O33: 43550.785 | P33: 3045346 | Q33: 4441262 | R33: 2325222 | S33: 2929584 | T33: 720124 | U33: 1511678 | V33: 1162 | W33: 1162 | X33: 1162 | Y33: 1162 | Z33: 0 | AA33: 0 | AB33: 8590 | AC33: 8590 | AD33: 8590 | AE33: 8590 | AP33: 132239 | AQ33: 0 | AV33: 860953 | AW33: 1520268 | AX33: 1058008 | AY33: 2036828 | AZ33: 784566 | BA33: 1877340 | BB33: 22119 | BC33: 0 | BD33: 251323 | BE33: 159488 | BH33: 3252 | BI33: 840 | BL33: 760728 | BM33: 18099356 | BP33: 616801 | BQ33: 2688471 | BV33: 10495 | BW33: 8385 | BX33: 55214 | BY33: 12784715 | BZ33: 1272 | CA33: 0 | CB33: 2956 | CC33: 0 | CH33: 73990 | CI33: 2617785 | CJ33: 100402 | CK33: 2098015 | CN33: 13947 | CO33: 1569845 | CP33: 83104 | CQ33: 22632 | CR33: 3351 | CS33: 505538 | CV33: 28802 | CW33: 28802 | CX33: 1951192 | CY33: 22263841 | CZ33: 2812145 | DA33: 23784109 | DB33: 967500 | DC33: 967500 | DF33: 634728 | DG33: 654735 | DJ33: 553598 | DK33: 3373120 | DP33: 2155826 | DQ33: 4995355 | EP33: 656319 | EQ33: 18788754 | ER33: 656319 | ES33: 17088754 | EV33: 109507 | EW33: 13376998 | FH33: 93206 | FI33: 324290 | FJ33: 209117 | FK33: 1149512 | FN33: 84624 | FO33: 535810 | FQ33: 5903 | FR33: 113091 | FS33: 586387 | FV33: 0 | FW33: 1700000 | FZ33: 46774 | GA33: 1109854 | GB33: 656319 | GC33: 18788754 | GD33: 2812145 | GE33: 23784109
A34: 20006 | B34: 0 | C34: 200049218 | D34: "O'ZELEKTROTERM" AJ | E34: 14 | F34: 1 | G34: 0 | H34: 1 | I34: 2021 | J34: 4 | K34: N | L34: 1 | M34: 30 | N34: 0 | O34: 44607.99 | P34: 416868 | Q34: 508883 | R34: 307213 | S34: 314492 | T34: 109655 | U34: 194391 | AB34: 160430 | AC34: 160430 | AD34: 20222 | AE34: 20222 | AF34: 140208 | AG34: 140208 | AV34: 270085 | AW34: 354821 | AX34: 262630 | AY34: 486657 | AZ34: 155975 | BA34: 379459 | BB34: 899 | BC34: 1619 | BD34: 11989 | BE34: 11989 | BF34: 93767 | BG34: 93590 | BH34: 161318 | BL34: 589706 | BM34: 336872 | BP34: 219390 | BQ34: 24368 | BT34: 295340 | BU34: 237310 | BW34: 231 | BX34: 68139 | BY34: 74963 | CH34: 6837 | CJ34: 277852 | CK34: 6983 | CN34: 277852 | CO34: 6983 | CX34: 1291506 | CY34: 830512 | CZ34: 1561591 | DA34: 1185333 | DB34: 643677 | DC34: 643677 | DF34: 51477 | DG34: 80547 | DJ34: 63101 | DK34: 63101 | DN34: 8377 | DO34: 315477 | DP34: 766632 | DQ34: 1102802 | EP34: 794959 | EQ34: 82531 | ER34: 794959 | ES34: 82531 | EV34: 2095 | EW34: 2273 | FH34: 700891 | FI34: 2746 | FJ34: 10137 | FK34: 32215 | FN34: 5816 | FO34: 5549 | FR34: 31180 | FZ34: 44840 | GA34: 39748 | GB34: 794959 | GC34: 82531 | GD34: 1561591 | GE34: 1185333
A35: 20006 | B35: 0 | C35: 200049218 | D35: "O'ZELEKTROTERM" AJ | E35: 14 | F35: 1 | G35: 0 | H35: 1 | I35: 2020 | J35: 4 | K35: N | L35: 1 | M35: 30 | N35: 0 | O35: 44244.676 | P35: 416868 | Q35: 508883 | R35: 307213 | S35: 314492 | T35: 109655 | U35: 194391 | AB35: 160430 | AC35: 160430 | AD35: 20222 | AE35: 20222 | AF35: 140208 | AG35: 140208 | AV35: 270085 | AW35: 354821 | AX35: 262630 | AY35: 486657 | AZ35: 155975 | BA35: 379459 | BB35: 899 | BC35: 1619 | BD35: 11989 | BE35: 11989 | BF35: 93767 | BG35: 93590 | BH35: 161318 | BL35: 589706 | BM35: 336872 | BP35: 219390 | BQ35: 24368 | BT35: 295340 | BU35: 237310 | BW35: 231 | BX35: 68139 | BY35: 74963 | CH35: 6837 | CJ35: 277852 | CK35: 6983 | CN35: 277852 | CO35: 6983 | CX35: 1291506 | CY35: 830512 | CZ35: 1561591 | DA35: 1185333 | DB35: 643677 | DC35: 643677 | DF35: 51477 | DG35: 80547 | DJ35: 63101 | DK35: 63101 | DN35: 8377 | DO35: 315477 | DP35: 766632 | DQ35: 1102802 | EP35: 794959 | EQ35: 82531 | ER35: 794959 | ES35: 82531 | EV35: 2095 | EW35: 2273 | FH35: 700891 | FI35: 2746 | FJ35: 10137 | FK35: 32215 | FN35: 5816 | FO35: 5549 | FR35: 31180 | FZ35: 44840 | GA35: 39748 | GB35: 794959 | GC35: 82531 | GD35: 1561591 | GE35: 1185333
A36: 20006 | B36: 0 | C36: 200049218 | D36: "O'ZELEKTROTERM" AJ | E36: 14 | F36: 1 | G36: 0 | H36: 1 | I36: 2019 | J36: 4 | K36: N | L36: 2 | M36: 30 | N36: 0 | O36: 44082.479 | P36: 422543 | Q36: 416868 | R36: 309484 | S36: 307213 | T36: 113059 | U36: 109655 | AB36: 157707 | AC36: 160430 | AD36: 17499 | AE36: 20222 | AF36: 140208 | AG36: 140208 | AV36: 270766 | AW36: 270085 | AX36: 260632 | AY36: 262630 | AZ36: 151395 | BA36: 155975 | BB36: 3394 | BC36: 899 | BD36: 11989 | BE36: 11989 | BF36: 93854 | BG36: 93767 | BH36: 110000 | BL36: 265920 | BM36: 589706 | BP36: 36275 | BQ36: 219390 | BT36: 190049 | BU36: 295340 | BX36: 36070 | BY36: 68139 | CH36: 3526 | CI36: 6837 | CJ36: 8223 | CK36: 277852 | CN36: 8223 | CO36: 277852 | CX36: 644775 | CY36: 1130188 | CZ36: 915541 | DA36: 1400273 | DB36: 643677 | DC36: 643677 | DF36: 46561 | DG36: 51477 | DJ36: 111525 | DK36: -89840 | DL36: 6852 | DP36: 808615 | DQ36: 605314 | EP36: 106926 | EQ36: 794959 | ER36: 106926 | ES36: 794959 | EV36: 3 | EW36: 2095 | FH36: 5657 | FI36: 700891 | FJ36: 28528 | FK36: 10137 | FN36: 5675 | FO36: 5816 | FR36: 27061 | FS36: 31180 | FZ36: 40002 | GA36: 44840 | GB36: 106926 | GC36: 794959 | GD36: 915541 | GE36: 1400273
A37: 20006 | B37: 0 | C37: 200049218 | D37: "O'ZELEKTROTERM" AJ | E37: 14 | F37: 1 | G37: 0 | H37: 1 | I37: 2018 | J37: 4 | K37: N | L37: 1 | M37: 30 | N37: 0 | O37: 43510.724 | P37: 422008 | Q37: 422543 | R37: 303059 | S37: 309484 | T37: 118949 | U37: 113059 | AB37: 157707 | AC37: 157707 | AD37: 17499 | AE37: 17499 | AF37: 140208 | AG37: 140208 | AV37: 276656 | AW37: 270766 | AX37: 265991 | AY37: 260632 | AZ37: 150444 | BA37: 151395 | BB37: 653 | BC37: 3394 | BD37: 13582 | BE37: 11989 | BF37: 101312 | BG37: 93854 | BI37: 110000 | BL37: 307960 | BM37: 265920 | BP37: 23006 | BQ37: 36275 | BT37: 269804 | BU37: 190049 | BX37: 11695 | BY37: 36070 | CH37: 3455 | CI37: 3526 | CJ37: 54720 | CK37: 8223 | CN37: 54720 | CO37: 8223 | CX37: 628671 | CY37: 644775 | CZ37: 905327 | DA37: 915541 | DB37: 643677 | DC37: 643677 | DF37: 30412 | DG37: 46561 | DJ37: 0 | DK37: 111525 | DL37: 175917 | DM37: 6852 | DP37: 850006 | DQ37: 808615 | EP37: 55321 | EQ37: 106926 | ER37: 55321 | ES37: 106926 | EV37: 79 | EW37: 3 | FH37: 4906 | FI37: 5657 | FJ37: 16040 | FK37: 28528 | FO37: 5675 | FP37: 3563 | FR37: 823 | FS37: 27061 | FZ37: 29910 | GA37: 40002 | GB37: 55321 | GC37: 106926 | GD37: 905327 | GE37: 915541
A38: 20006 | B38: 0 | C38: 200049541 | D38: "NAMANGANMASH" AJ | E38: 14 | F38: 1 | G38: 0 | H38: 1 | I38: 2021 | J38: 4 | K38: N | L38: 1 | M38: 30 | N38: 0 | O38: 44607.852 | P38: 3376243 | Q38: 3830792 | R38: 2384285 | S38: 2580408 | T38: 991958 | U38: 1250384 | AB38: 34092 | AC38: 34092 | AD38: 3516 | AE38: 3516 | AF38: 30576 | AG38: 30576 | AV38: 1026050 | AW38: 1284476 | AX38: 4887885 | AY38: 8529269 | AZ38: 1206018 | BA38: 2398715 | BD38: 3681867 | BE38: 6130554 | BH38: 7932 | BI38: 13626 | BL38: 2808173 | BM38: 1912300 | BP38: 2061627 | BQ38: 951722 | BX38: 625722 | BY38: 413157 | BZ38: 83 | CA38: 205996 | CB38: 688 | CC38: 52 | CF38: 1538 | CG38: 1583 | CH38: 118515 | CI38: 339790 | CJ38: 22108 | CK38: 217047 | CN38: 13694 | CO38: 520 | CP38: 8414 | CQ38: 8704 | CS38: 207823 | CX38: 7726098 | CY38: 10672242 | CZ38: 8752148 | DA38: 11956718 | DB38: 941427 | DC38: 941427 | DD38: 16351 | DE38: 16351 | DF38: 823991 | DG38: 820870 | DH38: 225 | DJ38: 5379961 | DK38: 6264247 | DL38: 135 | DM38: 135 | DP38: 7161640 | DQ38: 8043030 | DS38: 551192 | EK38: 551192 | EP38: 1590508 | EQ38: 3362496 | ER38: 1590508 | ES38: 3362496 | EV38: 655824 | EW38: 2725923 | FH38: 2510 | FI38: 20286 | FJ38: 237512 | FK38: 82612 | FN38: 80300 | FO38: 80494 | FR38: 343642 | FS38: 355660 | FZ38: 270720 | GA38: 97521 | GB38: 1590508 | GC38: 3913688 | GD38: 8752148 | GE38: 11956718
A39: 20006 | B39: 0 | C39: 200049541 | D39: "NAMANGANMASH" AJ | E39: 14 | F39: 1 | G39: 0 | H39: 1 | I39: 2020 | J39: 4 | K39: N | L39: 2 | M39: 30 | N39: 0 | O39: 44323.532 | P39: 3155741 | Q39: 3376243 | R39: 2207635 | S39: 2384285 | T39: 948106 | U39: 991958 | AB39: 34092 | AC39: 34092 | AD39: 3516 | AE39: 3516 | AF39: 30576 | AG39: 30576 | AT39: 1000 | AV39: 983198 | AW39: 1026050 | AX39: 5648590 | AY39: 4887885 | AZ39: 1888836 | BA39: 1206018 | BD39: 3759754 | BE39: 3681867 | BH39: 9722 | BI39: 7932 | BL39: 389597 | BM39: 2808173 | BP39: 354 | BQ39: 2061627 | BX39: 171624 | BY39: 625722 | BZ39: 45629 | CA39: 83 | CB39: 943 | CC39: 688 | CF39: 927 | CG39: 1538 | CH39: 170120 | CI39: 118515 | CJ39: 7697 | CK39: 22108 | CN39: 61 | CO39: 13694 | CP39: 7636 | CQ39: 8414 | CX39: 6055606 | CY39: 7726098 | CZ39: 7038804 | DA39: 8752148 | DB39: 941427 | DC39: 941427 | DD39: 16351 | DE39: 16351 | DF39: 800601 | DG39: 823991 | DH39: 225 | DI39: 225 | DJ39: 4006571 | DK39: 5379961 | DL39: 135 | DM39: 135 | DP39: 5764860 | DQ39: 7161640 | EP39: 1273944 | EQ39: 1590508 | ER39: 1273944 | ES39: 1590508 | EV39: 500509 | EW39: 655824 | FH39: 99236 | FI39: 2510 | FJ39: 78928 | FK39: 237512 | FN39: 112249 | FO39: 80300 | FR39: 306032 | FS39: 343642 | FZ39: 176990 | GA39: 270720 | GB39: 1273944 | GC39: 1590508 | GD39: 7038804 | GE39: 8752148
A40: 20006 | B40: 0 | C40: 200049541 | D40: "NAMANGANMASH" AJ | E40: 14 | F40: 1 | G40: 0 | H40: 1 | I40: 2019 | J40: 4 | K40: N | L40: 1 | M40: 30 | N40: 0 | O40: 43875.665 | P40: 2945463 | Q40: 3007702 | R40: 1883998 | S40: 2118280 | T40: 1061465 | U40: 889422 | AB40: 34092 | AC40: 34092 | AD40: 3516 | AE40: 3516 | AF40: 30576 | AG40: 30576 | AT40: 755 | AU40: 1000 | AV40: 1096312 | AW40: 924514 | AX40: 4379258 | AY40: 5648590 | AZ40: 2197520 | BA40: 1888836 | BD40: 2181738 | BE40: 3759754 | BH40: 8123 | BI40: 9722 | BL40: 765522 | BM40: 389597 | BP40: 193967 | BQ40: 354 | BV40: 19064 | BX40: 413357 | BY40: 171624 | BZ40: 6133 | CA40: 45629 | CC40: 943 | CF40: 3623 | CG40: 927 | CH40: 129378 | CI40: 170120 | CJ40: 199906 | CK40: 7697 | CN40: 192306 | CO40: 61 | CP40: 6697 | CQ40: 7636 | CR40: 903 | CX40: 5352809 | CY40: 6055606 | CZ40: 6449121 | DA40: 6980120 | DB40: 941427 | DC40: 941427 | DD40: 16351 | DE40: 16351 | DF40: 693588 | DG40: 741917 | DH40: 4850 | DI40: 225 | DJ40: 3427670 | DK40: 4006571 | DL40: 135 | DM40: 135 | DP40: 5074321 | DQ40: 5706176 | EP40: 1374800 | EQ40: 1273944 | ER40: 1366800 | ES40: 1273944 | EV40: 83619 | EW40: 500509 | FB40: 8000 | FH40: 185446 | FI40: 99236 | FJ40: 532015 | FK40: 78928 | FN40: 227989 | FO40: 112249 | FR40: 242491 | FS40: 306032 | FZ40: 95240 | GA40: 176990 | GB40: 1374800 | GC40: 1273944 | GD40: 6449121 | GE40: 6980120
A41: 20006 | B41: 0 | C41: 200049541 | D41: "NAMANGANMASH" AJ | E41: 14 | F41: 1 | G41: 0 | H41: 1 | I41: 2018 | J41: 4 | K41: N | L41: 2 | M41: 30 | N41: 0 | O41: 43616.423 | P41: 2559684 | Q41: 2840948 | R41: 1645954 | S41: 1831783 | T41: 913730 | U41: 1009165 | AB41: 34092 | AC41: 34092 | AD41: 3516 | AE41: 3516 | AF41: 30576 | AG41: 30576 | AN41: 207847 | AT41: 2595 | AU41: 755 | AV41: 1158264 | AW41: 1044012 | AX41: 3321307 | AY41: 4379258 | AZ41: 1703876 | BA41: 2197520 | BD41: 1617431 | BE41: 2181738 | BH41: 12787 | BI41: 8123 | BL41: 651662 | BM41: 765521 | BP41: 467997 | BQ41: 193967 | BV41: 3251 | BW41: 19063 | BX41: 161412 | BY41: 413357 | BZ41: 44 | CA41: 6133 | CF41: 115 | CG41: 3623 | CH41: 18843 | CI41: 129378 | CJ41: 44646 | CK41: 199906 | CN41: 19798 | CO41: 192306 | CP41: 24848 | CQ41: 6697 | CS41: 903 | CX41: 4030402 | CY41: 5352808 | CZ41: 5188666 | DA41: 6396820 | DB41: 941427 | DC41: 941427 | DD41: 16351 | DE41: 16351 | DF41: 595402 | DG41: 641287 | DH41: 2132 | DI41: 4850 | DJ41: 2396618 | DK41: 3427670 | DL41: 135 | DM41: 135 | DP41: 3947801 | DQ41: 5022020 | EP41: 1240865 | EQ41: 1374800 | ER41: 1232865 | ES41: 1366800 | EV41: 14752 | EW41: 83619 | FB41: 8000 | FC41: 8000 | FH41: 341724 | FI41: 185446 | FJ41: 284391 | FK41: 532015 | FN41: 200202 | FO41: 227989 | FR41: 276021 | FS41: 242491 | FZ41: 115775 | GA41: 95240 | GB41: 1240865 | GC41: 1374800 | GD41: 5188666 | GE41: 6396820
A42: 20006 | B42: 0 | C42: 200340624 | D42: "KARBONAT" AJ | E42: 8 | F42: 11 | G42: 0 | H42: 1 | I42: 2021 | J42: 4 | K42: N | L42: 1 | M42: 30 | N42: 0 | O42: 44608.435 | P42: 9221637.9 | Q42: 15139824 | R42: 5149905.2 | S42: 5763121 | T42: 4071732.7 | U42: 9376703 | W42: 2009 | Y42: 16 | AA42: 1993 | AB42: 19173 | AC42: 19173 | AD42: 19173 | AE42: 19173 | AN42: 8497968.5 | AO42: 8542723 | AP42: 36060.4 | AU42: 1126523 | AV42: 12624935 | AW42: 19067115 | AX42: 4130076.1 | AY42: 8183484 | AZ42: 1542807.7 | BA42: 2660160 | BB42: 2524894.2 | BC42: 5096754 | BD42: 62374.12 | BE42: 426570 | BF42: 0 | BH42: 199802.94 | BI42: 135795 | BL42: 27461927 | BM42: 29924771 | BP42: 9989481.9 | BQ42: 9930271 | BV42: 2495.47 | BW42: 2491 | BX42: 16306106 | BY42: 18579639 | BZ42: 1069887.6 | CA42: 1250489 | CB42: 73077.12 | CC42: 131 | CF42: 20576.46 | CH42: 302.54 | CI42: 161750 | CJ42: 147181.85 | CK42: 691162 | CN42: 147181.85 | CO42: 254377 | CQ42: 436785 | CT42: 67644.82 | CU42: 2900 | CX42: 32006633 | CY42: 38938112 | CZ42: 44631567 | DA42: 58005227 | DB42: 6279423.5 | DC42: 6279423 | DD42: 16218540 | DE42: 16218540 | DF42: 1161293.6 | DG42: 1575004 | DJ42: 11157920 | DK42: 16372559 | DL42: 241721.2 | DM42: 241721 | DP42: 35058898 | DQ42: 40687247 | DR42: 2629706.9 | DS42: 9983743 | DU42: 8351635 | EJ42: 2629706.9 | EK42: 1632108 | EO42: 8351635 | EP42: 6942962.5 | EQ42: 7334237 | ER42: 6818165.7 | ES42: 5937250 | EV42: 2964386.4 | EW42: 3160259 | FH42: 1287955.2 | FI42: 1316991 | FJ42: 673513.84 | FK42: 577776 | FN42: 212238.89 | FO42: 90490 | FR42: 487058.85 | FS42: 712962 | FU42: 1083766 | FV42: 37647.62 | FX42: 87149.14 | FY42: 313221 | FZ42: 1193012.5 | GA42: 78772 | GB42: 9572669.4 | GC42: 17317980 | GD42: 44631567 | GE42: 58005227
A43: 20006 | B43: 0 | C43: 200340624 | D43: "KARBONAT" AJ | E43: 8 | F43: 11 | G43: 0 | H43: 1 | I43: 2020 | J43: 4 | K43: N | L43: 2 | M43: 30 | N43: 0 | O43: 44245.697 | P43: 6551344 | Q43: 9221637.9 | R43: 4864081 | S43: 5149905.2 | T43: 1687263 | U43: 4071732.7 | AB43: 19173 | AC43: 19173 | AD43: 19173 | AE43: 19173 | AO43: 8497968.5 | AP43: 8497968 | AQ43: 36060.4 | AV43: 10204404 | AW43: 12624935 | AX43: 877354 | AY43: 4130076.1 | AZ43: 550723 | BA43: 1542807.7 | BB43: 323592 | BC43: 2524894.2 | BD43: 3039 | BE43: 62374.12 | BF43: 0 | BG43: 0 | BH43: 581137 | BI43: 199802.94 | BL43: 22536437 | BM43: 27461927 | BP43: 6008448 | BQ43: 9989481.9 | BW43: 2495.47 | BX43: 16475585 | BY43: 16306106 | BZ43: 35337 | CA43: 1069887.6 | CB43: 247 | CC43: 73077.12 | CF43: 14489 | CG43: 20576.46 | CH43: 2331 | CI43: 302.54 | CJ43: 85 | CK43: 147181.85 | CO43: 147181.85 | CR43: 85 | CT43: 72119 | CU43: 67644.82 | CX43: 24067132 | CY43: 32006633 | CZ43: 34271536 | DA43: 44631567 | DB43: 6279424 | DC43: 6279423.5 | DD43: 16218540 | DE43: 16218540 | DF43: 1116500 | DG43: 1161293.6 | DJ43: 6961673 | DK43: 11157920 | DL43: 241721 | DM43: 241721.2 | DP43: 30817858 | DQ43: 35058898 | DS43: 2629706.9 | EK43: 2629706.9 | EP43: 3453678 | EQ43: 6942962.5 | ER43: 2934272 | ES43: 6818165.7 | EV43: 1693564 | EW43: 2964386.4 | EX43: 0 | EZ43: 78044 | FH43: 71548 | FI43: 1287955.2 | FJ43: 661195 | FK43: 673513.84 | FN43: 113137 | FO43: 212238.89 | FR43: 283003 | FS43: 487058.85 | FV43: 106073 | FW43: 37647.62 | FX43: 413333 | FY43: 87149.14 | FZ43: 33781 | GA43: 1193012.5 | GB43: 3453678 | GC43: 9572669.4 | GD43: 34271536 | GE43: 44631567
A44: 20006 | B44: 0 | C44: 200340624 | D44: "KARBONAT" AJ | E44: 8 | F44: 11 | G44: 0 | H44: 1 | I44: 2019 | J44: 4 | K44: N | L44: 1 | M44: 30 | N44: 0 | O44: 43875.578 | P44: 5464121 | Q44: 6551344 | R44: 4430994 | S44: 4864081 | T44: 1033127 | U44: 1687263 | AB44: 19173 | AC44: 19173 | AD44: 19173 | AE44: 19173 | AP44: 6665605 | AQ44: 8497968 | AV44: 7717905 | AW44: 10204404 | AX44: 1139518 | AY44: 877354 | AZ44: 529986 | BA44: 550723 | BB44: 606493 | BC44: 323592 | BD44: 3039 | BE44: 3039 | BF44: 0 | BG44: 0 | BH44: 537642 | BI44: 581137 | BL44: 22431370 | BM44: 22536437 | BP44: 2136191 | BQ44: 6008448 | BX44: 20221210 | BY44: 16475585 | BZ44: 42463 | CA44: 35337 | CB44: 13243 | CC44: 247 | CF44: 17125 | CG44: 14489 | CH44: 1138 | CI44: 2331 | CJ44: 2405787 | CK44: 85 | CN44: 2405787 | CS44: 85 | CT44: 72708 | CU44: 72119 | CX44: 26587025 | CY44: 24067132 | CZ44: 34304930 | DA44: 34271536 | DB44: 6279424 | DC44: 6279424 | DD44: 16218540 | DE44: 16218540 | DF44: 1077523 | DG44: 1116500 | DJ44: 6973539 | DK44: 6961673 | DL44: 241721 | DM44: 241721 | DP44: 30790747 | DQ44: 30817858 | EP44: 3514183 | EQ44: 3453678 | ER44: 2631524 | ES44: 2934272 | EV44: 1422057 | EW44: 1693564 | EX44: 0 | EY44: 0 | EZ44: 78044 | FA44: 78044 | FH44: 736802 | FI44: 71548 | FJ44: 113921 | FK44: 661195 | FN44: 176430 | FO44: 113137 | FR44: 76303 | FS44: 283003 | FV44: 25800 | FW44: 106073 | FX44: 856859 | FY44: 413333 | FZ44: 27967 | GA44: 33781 | GB44: 3514183 | GC44: 3453678 | GD44: 34304930 | GE44: 34271536
A45: 20006 | B45: 0 | C45: 200340624 | D45: "KARBONAT" AJ | E45: 8 | F45: 11 | G45: 0 | H45: 1 | I45: 2018 | J45: 4 | K45: N | L45: 3 | M45: 30 | N45: 0 | O45: 43776.634 | P45: 5414904 | Q45: 5464121 | R45: 4214575 | S45: 4430994 | T45: 1200329 | U45: 1033127 | AB45: 16724 | AC45: 19173 | AD45: 16724 | AE45: 19173 | AP45: 51856 | AQ45: 6640270 | AV45: 1268909 | AW45: 7692570 | AX45: 858143 | AY45: 1139518 | AZ45: 540896 | BA45: 529986 | BB45: 314208 | BC45: 606493 | BD45: 3039 | BE45: 3039 | BH45: 87596 | BI45: 537642 | BL45: 10567319 | BM45: 22431369 | BP45: 4837238 | BQ45: 2136191 | BV45: 71 | BW45: 0 | BX45: 5681219 | BY45: 20221209 | BZ45: 27231 | CA45: 42463 | CB45: 233 | CC45: 13243 | CF45: 18229 | CG45: 17125 | CH45: 3098 | CI45: 1138 | CJ45: 0 | CK45: 2405787 | CN45: 0 | CO45: 2405787 | CS45: 0 | CT45: 75708 | CU45: 72708 | CX45: 11588766 | CY45: 26587024 | CZ45: 12857675 | DA45: 34279594 | DB45: 914424 | DC45: 6279424 | DD45: 0 | DE45: 16218540 | DF45: 1077758 | DG45: 1077523 | DJ45: 6898759 | DK45: 6973539 | DL45: 241721 | DM45: 241721 | DP45: 9132662 | DQ45: 30790747 | EP45: 3725013 | EQ45: 3488847 | ER45: 2500013 | ES45: 2606188 | EV45: 1251983 | EW45: 1396722 | EZ45: 78044 | FA45: 78044 | FH45: 679874 | FI45: 736802 | FJ45: 228342 | FK45: 113920 | FN45: 142307 | FO45: 176430 | FR45: 95138 | FS45: 76303 | FV45: 25000 | FW45: 25800 | FX45: 1200000 | FY45: 856859 | FZ45: 24325 | GA45: 27967 | GB45: 3725013 | GC45: 3488847 | GD45: 12857675 | GE45: 34279594
A46: 20006 | B46: 0 | C46: 200344745 | D46: "JIZZAX PLASTMASSA" AJ | E46: 8 | F46: 12 | G46: 0 | H46: 1 | I46: 2021 | J46: 4 | K46: N | L46: 2 | M46: 30 | N46: 0 | O46: 44882.644 | P46: 38382514 | Q46: 38532573 | R46: 16682606 | S46: 17099207 | T46: 21699908 | U46: 21433366 | AB46: 8931377 | AC46: 9865145 | AD46: 39392 | AE46: 39392 | AJ46: 6446389 | AK46: 6446389 | AL46: 2445596 | AM46: 3379364 | AV46: 30631285 | AW46: 31298511 | AX46: 14410947 | AY46: 13477267 | AZ46: 1984642 | BA46: 2047813 | BB46: 242707 | BC46: 282587 | BD46: 12176736 | BE46: 11098938 | BF46: 6862 | BG46: 47929 | BH46: 135 | BL46: 13675892 | BM46: 6826328 | BP46: 12958924 | BQ46: 6322878 | BW46: 1752 | BX46: 369519 | BY46: 105843 | BZ46: 36347 | CA46: 67886 | CB46: 29823 | CC46: 30209 | CF46: 86431 | CG46: 64593 | CH46: 194848 | CI46: 233167 | CJ46: 60836 | CK46: 14678 | CN46: 20942 | CO46: 10120 | CR46: 39894 | CS46: 4558 | CT46: 768992 | CU46: 246000 | CX46: 28916802 | CY46: 20564273 | CZ46: 59548087 | DA46: 51862784 | DB46: 15198244 | DC46: 15198244 | DD46: 133802 | DE46: 133802 | DF46: 20235824 | DG46: 20234686 | DJ46: 201232 | DK46: 722592 | DL46: 4549382 | DM46: 4571157 | DP46: 40318484 | DQ46: 40860481 | DR46: 11617579 | DS46: 3245204 | DT46: 3125027 | DU46: 2940027 | DV46: 3125027 | DW46: 2940027 | EJ46: 8444053 | EK46: 256678 | EL46: 48499 | EM46: 48499 | EP46: 7612024 | EQ46: 7757099 | ER46: 7612024 | ES46: 7757099 | EV46: 3131168 | EW46: 2701469 | FH46: 1185260 | FI46: 2231215 | FJ46: 197629 | FK46: 986500 | FN46: 120 | FO46: 6405 | FP46: 917908 | FQ46: 839390 | FR46: 156863 | FS46: 518701 | FZ46: 2023076 | GA46: 473419 | GB46: 19229603 | GC46: 11002303 | GD46: 59548087 | GE46: 51862784
A47: 20006 | B47: 0 | C47: 200344745 | D47: "JIZZAX PLASTMASSA" AJ | E47: 8 | F47: 12 | G47: 0 | H47: 1 | I47: 2020 | J47: 4 | K47: N | L47: 2 | M47: 30 | N47: 0 | O47: 44795.5 | P47: 31171882 | Q47: 38382514 | R47: 16115206 | S47: 16682606 | T47: 15056676 | U47: 21699908 | AB47: 15516710 | AC47: 8931376.8 | AD47: 39391.9 | AE47: 39391.9 | AJ47: 13671542 | AK47: 6446388.9 | AL47: 1805775.9 | AM47: 2445596 | AV47: 30573386 | AW47: 30631285 | AX47: 18951156 | AY47: 14410947 | AZ47: 6179866.9 | BA47: 1984642.3 | BB47: 209452.92 | BC47: 242706.93 | BD47: 12537071 | BE47: 12176736 | BF47: 24765.07 | BG47: 6862.07 | BI47: 134.52 | BL47: 13968809 | BM47: 13675891 | BP47: 12452176 | BQ47: 12958924 | BX47: 217494.24 | BY47: 369518.89 | BZ47: 636535.69 | CA47: 36347.06 | CB47: 25852.59 | CC47: 29822.55 | CF47: 215469.06 | CG47: 86430.89 | CH47: 421280.96 | CI47: 194847.54 | CJ47: 58853.39 | CK47: 60835.45 | CN47: 2123.79 | CO47: 20941.85 | CP47: 5181.45 | CQ47: 0.02 | CR47: 51548.15 | CS47: 39893.58 | CT47: 630985.74 | CU47: 768991.69 | CX47: 33609804 | CY47: 28916800 | CZ47: 64183189 | DA47: 59548085 | DB47: 13979419 | DC47: 15198244 | DE47: 133802.21 | DF47: 20718971 | DG47: 20235824 | DJ47: 3531680.6 | DK47: 201232.05 | DL47: 2959992.4 | DM47: 4549382.5 | DP47: 41190063 | DQ47: 40318485 | DR47: 14000181 | DS47: 11617579 | DT47: 3125027.2 | DU47: 3125027.2 | DV47: 3125027.2 | DW47: 3125027.2 | EJ47: 10826655 | EK47: 8444053 | EL47: 48498.92 | EM47: 48498.92 | EP47: 8992945.4 | EQ47: 7612021.1 | ER47: 8992945.4 | ES47: 7612021.1 | ET47: 8992945.4 | EU47: 7612021.1 | EV47: 5269969.1 | EW47: 3131168.3 | FH47: 289939.29 | FI47: 1185260.3 | FJ47: 62133.37 | FK47: 197629.03 | FN47: 354367.18 | FO47: 119.97 | FP47: 341294.16 | FQ47: 917908.24 | FR47: 627145.58 | FS47: 156863.08 | FZ47: 2048096.8 | GA47: 2023072.2 | GB47: 22993126 | GC47: 19229600 | GD47: 64183189 | GE47: 59548085
A48: 20006 | B48: 0 | C48: 200344745 | D48: "JIZZAX PLASTMASSA" AJ | E48: 8 | F48: 12 | G48: 0 | H48: 1 | I48: 2019 | J48: 4 | K48: N | L48: 1 | M48: 30 | N48: 0 | O48: 43878.736 | P48: 24336306 | Q48: 29205753 | R48: 12827719 | S48: 15181769 | T48: 11508587 | U48: 14023984 | V48: 10000 | X48: 5167 | Z48: 4833 | AB48: 14485514 | AC48: 15516710 | AD48: 38976 | AE48: 39392 | AJ48: 12640762 | AK48: 13671542 | AL48: 1805776 | AM48: 1805776 | AV48: 25998934 | AW48: 29540694 | AX48: 11618268 | AY48: 18951155 | AZ48: 6748271 | BA48: 6179866 | BB48: 112874 | BC48: 209453 | BD48: 4757123 | BE48: 12537071 | BG48: 24765 | BH48: 26142 | BL48: 2919690 | BM48: 13968809 | BP48: 2108706 | BQ48: 12452176 | BV48: 43181 | BX48: 316717 | BY48: 217494 | BZ48: 22963 | CA48: 636536 | CB48: 30787 | CC48: 25853 | CF48: 172003 | CG48: 215469 | CH48: 225333 | CI48: 421281 | CJ48: 6879718 | CK48: 58853 | CN48: 783648 | CO48: 2124 | CP48: 1141598 | CQ48: 5181 | CR48: 4954472 | CS48: 51548 | CT48: 202823 | CU48: 630986 | CX48: 21646641 | CY48: 33609803 | CZ48: 47645575 | DA48: 63150497 | DB48: 7506400 | DC48: 13979419 | DF48: 19733097 | DG48: 19702392 | DJ48: 6756693 | DK48: 3531681 | DL48: 2081584 | DM48: 2959992 | DP48: 36077774 | DQ48: 40173484 | DR48: 6613609 | DS48: 14000181 | DT48: 3225027 | DU48: 3125027 | DV48: 3225027 | DW48: 3125027 | EJ48: 3340083 | EK48: 10826655 | EL48: 48499 | EM48: 48499 | EP48: 4954194 | EQ48: 8976832 | ER48: 4954194 | ES48: 8976832 | EV48: 107813 | EW48: 5269969 | FH48: 283490 | FI48: 289939 | FJ48: 246215 | FK48: 46020 | FN48: 165724 | FO48: 354367 | FP48: 1779340 | FQ48: 341294 | FR48: 411591 | FS48: 627146 | FZ48: 1960021 | GA48: 2048097 | GB48: 11567803 | GC48: 22977013 | GD48: 47645577 | GE48: 63150497
A49: 20006 | B49: 0 | C49: 200344745 | D49: "JIZZAX PLASTMASSA" AJ | E49: 8 | F49: 12 | G49: 0 | H49: 1 | I49: 2018 | J49: 4 | K49: N | L49: 1 | M49: 30 | N49: 0 | O49: 43511.843 | P49: 14830107 | Q49: 23120843 | R49: 7934318 | S49: 12376912 | T49: 6895789 | U49: 10743931 | V49: 10000 | W49: 10000 | X49: 3167 | Y49: 5167 | Z49: 6833 | AA49: 4833 | AB49: 2827768 | AC49: 14485514 | AD49: 38976 | AE49: 38976 | AF49: 0 | AG49: 0 | AH49: 0 | AI49: 0 | AJ49: 2750631 | AK49: 12640762 | AL49: 38161 | AM49: 1805776 | AN49: 0 | AO49: 0 | AP49: 106022 | AQ49: 0 | AR49: 0 | AS49: 0 | AT49: 0 | AU49: 0 | AV49: 9836412 | AW49: 25234278 | AX49: 9990805 | AY49: 11618268 | AZ49: 6765735 | BA49: 6748271 | BB49: 94450 | BC49: 112874 | BD49: 3016983 | BE49: 4757123 | BF49: 113637 | BG49: 0 | BH49: 0 | BI49: 26142 | BJ49: 0 | BK49: 0 | BL49: 5656789 | BM49: 2942496 | BN49: 0 | BO49: 0 | BP49: 2261387 | BQ49: 2108706 | BR49: 0 | BS49: 0 | BT49: 0 | BU49: 0 | BV49: 40647 | BW49: 43181 | BX49: 2660915 | BY49: 316717 | BZ49: 62846 | CA49: 22963 | CB49: 23963 | CC49: 30787 | CD49: 0 | CE49: 0 | CF49: 187720 | CG49: 172003 | CH49: 419311 | CI49: 248139 | CJ49: 4951199 | CK49: 6879718 | CL49: 0 | CM49: 0 | CN49: 325136 | CO49: 783648 | CP49: 4486822 | CQ49: 1141598 | CR49: 139241 | CS49: 4954472 | CT49: 0 | CU49: 202823 | CV49: 0 | CW49: 0 | CX49: 20598793 | CY49: 21669447 | CZ49: 30435205 | DA49: 46903725 | DB49: 706170 | DC49: 7506399 | DD49: 0 | DE49: 0 | DF49: 4333297 | DG49: 18968441 | DH49: 0 | DI49: 0 | DJ49: 11902511 | DK49: 6756693 | DL49: 848028 | DM49: 2081584 | DN49: 0 | DO49: 0 | DP49: 17790006 | DQ49: 35313117 | DR49: 7114914 | DS49: 6613609 | DT49: 4750790 | DU49: 3225027 | DV49: 4750790 | DW49: 3225027 | DX49: 0 | DY49: 0 | DZ49: 0 | EA49: 0 | EB49: 0 | EC49: 0 | ED49: 0 | EE49: 0 | EF49: 0 | EG49: 0 | EH49: 0 | EI49: 0 | EJ49: 1965625 | EK49: 3340083 | EL49: 398499 | EM49: 48499 | EN49: 0 | EO49: 0 | EP49: 5530285 | EQ49: 4976999 | ER49: 3530285 | ES49: 4976999 | ET49: 0 | EU49: 0 | EV49: 107663 | EW49: 107813 | EX49: 0 | EY49: 0 | EZ49: 0 | FA49: 0 | FB49: 0 | FC49: 0 | FD49: 0 | FE49: 0 | FF49: 0 | FG49: 0 | FH49: 469412 | FI49: 283490 | FJ49: 354355 | FK49: 246215 | FL49: 0 | FM49: 0 | FN49: 304875 | FO49: 165724 | FP49: 76102 | FQ49: 1779340 | FR49: 112845 | FS49: 411591 | FT49: 2000000 | FU49: 0 | FV49: 0 | FW49: 0 | FX49: 0 | FY49: 0 | FZ49: 2105033 | GA49: 1982826 | GB49: 12645199 | GC49: 11590608 | GD49: 30435205 | GE49: 46903725
A50: 20006 | B50: 0 | C50: 200378039 | D50: КООП."РАДУГА" | E50: 35 | F50: 9 | G50: 0 | H50: 13 | I50: 2021 | J50: 4 | K50: N | L50: 1 | M50: 30 | N50: 0 | O50: 44582.481 | P50: 78340 | Q50: 78340 | R50: 57055.7 | S50: 60972.7 | T50: 21284.3 | U50: 17367.3 | AV50: 21284.3 | AW50: 17367.3 | AX50: 54655 | AY50: 66638.5 | AZ50: 54655 | BA50: 66638.5 | BL50: 4578.6 | BM50: 4302.7 | BZ50: 4578.6 | CA50: 4302.7 | CJ50: 1677.4 | CN50: 1677.4 | CX50: 60911 | CY50: 70941.2 | CZ50: 82195.3 | DA50: 88308.5 | DB50: 67300 | DC50: 67300 | DJ50: 10395.3 | DK50: -929.7 | DP50: 77695.3 | DQ50: 66370.3 | EP50: 4500 | EQ50: 21938.2 | ER50: 4500 | ES50: 21938.2 | FK50: 39.9 | FR50: 4500 | FS50: 21898.3 | GB50: 4500 | GC50: 21938.2 | GD50: 82195.3 | GE50: 88308.5
A51: 20006 | B51: 0 | C51: 200378039 | D51: КООП."РАДУГА" | E51: 35 | F51: 9 | G51: 0 | H51: 13 | I51: 2020 | J51: 4 | K51: N | L51: 1 | M51: 30 | N51: 0 | O51: 44211.843 | P51: 78340 | Q51: 78340 | R51: 53138.7 | S51: 57055.7 | T51: 25201.3 | U51: 21284.3 | AV51: 25201.3 | AW51: 21284.3 | AX51: 23558.1 | AY51: 54655 | AZ51: 23558.1 | BA51: 54655 | BL51: 11672.8 | BM51: 4578.6 | BX51: 6000 | BZ51: 5672.8 | CA51: 4578.6 | CJ51: 27710.7 | CK51: 1677.4 | CN51: 27710.7 | CO51: 1677.4 | CX51: 62941.6 | CY51: 60911 | CZ51: 88142.9 | DA51: 82195.3 | DB51: 67300 | DC51: 67300 | DJ51: 16345 | DK51: 10395.3 | DP51: 83645 | DQ51: 77695.3 | EP51: 4497.9 | EQ51: 4500 | ER51: 4497.9 | ES51: 4500 | FP51: 4497.9 | FQ51: 4500 | GB51: 4497.9 | GC51: 4500 | GD51: 88142.9 | GE51: 82195.3
A52: 20006 | B52: 0 | C52: 200378039 | D52: КООП."РАДУГА" | E52: 35 | F52: 9 | G52: 0 | H52: 13 | I52: 2019 | J52: 4 | K52: N | L52: 2 | M52: 30 | N52: 0 | O52: 43900.641 | P52: 78340 | Q52: 78340 | R52: 50608.3 | S52: 53138.7 | T52: 27731.7 | U52: 25201.3 | AV52: 27731.7 | AW52: 25201.3 | AY52: 23558.1 | BA52: 23558.1 | BL52: 59931 | BM52: 11672.8 | BX52: 57841.3 | BY52: 6000 | BZ52: 2089.7 | CA52: 5672.8 | CJ52: 11744.6 | CK52: 27710.7 | CN52: 11744.6 | CO52: 27710.7 | CX52: 71675.6 | CY52: 62941.6 | CZ52: 99407.3 | DA52: 88142.9 | DB52: 67300 | DC52: 67300 | DJ52: 27461.6 | DK52: 16345 | DN52: 4645.7 | DP52: 99407.3 | DQ52: 83645 | EQ52: 4497.9 | ES52: 4497.9 | FQ52: 4497.9 | GC52: 4497.9 | GD52: 99407.3 | GE52: 88142.9
A53: 20006 | B53: 0 | C53: 200378039 | D53: КООП."РАДУГА" | E53: 35 | F53: 9 | G53: 0 | H53: 13 | I53: 2018 | J53: 4 | K53: N | L53: 2 | M53: 30 | N53: 0 | O53: 43501.462 | P53: 164858.3 | Q53: 78340 | R53: 46326.8 | S53: 50608.3 | T53: 118531.5 | U53: 27731.7 | AV53: 118531.5 | AW53: 27731.7 | BL53: 23441.5 | BM53: 59931 | BY53: 57841.3 | CA53: 2089.7 | CH53: 23441.5 | CJ53: 24830 | CK53: 11744.6 | CN53: 24830 | CO53: 11744.6 | CX53: 48271.5 | CY53: 71675.6 | CZ53: 166803 | DA53: 99407.3 | DB53: 67300 | DC53: 67300 | DD53: 35000 | DF53: 38547.1 | DJ53: 24011.6 | DK53: 27461.6 | DO53: 4645.7 | DP53: 164858.7 | DQ53: 99407.3 | EP53: 1944.3 | ER53: 1944.3 | FJ53: 1944.3 | GB53: 1944.3 | GD53: 166803 | GE53: 99407.3
A54: 20006 | B54: 0 | C54: 200383721 | D54: "QONIRAT UN ZAVODI" AJ | E54: 35 | F54: 12 | G54: 0 | H54: 1 | I54: 2021 | J54: 4 | K54: N | L54: 2 | M54: 30 | N54: 0 | O54: 44644.416 | P54: 11759499 | Q54: 12381541 | R54: 3082349 | S54: 3698196 | T54: 8677150 | U54: 8683345 | AB54: 1056517 | AC54: 434659 | AD54: 40596 | AE54: 40596 | AH54: 1004921 | AI54: 383063 | AL54: 11000 | AM54: 11000 | AP54: 541025 | AV54: 10274692 | AW54: 9118004 | AX54: 25356337 | AY54: 30450335 | AZ54: 23038561 | BA54: 28140993 | BD54: 2317776 | BE54: 2309341.7 | BL54: 20940766 | BM54: 17117765 | BP54: 4540296 | BQ54: 3764801 | BT54: 1097105 | BU54: 198441 | BV54: 1300 | BW54: 334 | BX54: 14901622 | BY54: 12771859 | BZ54: 15622 | CA54: 11247 | CB54: 54 | CD54: 211657 | CE54: 211657 | CF54: 173110 | CG54: 159426 | CJ54: 48354 | CK54: 142220 | CN54: 35005 | CO54: 57877 | CR54: 13349 | CS54: 84343 | CV54: 1164438 | CW54: 1164438 | CX54: 47509895 | CY54: 48874758 | CZ54: 57784587 | DA54: 57992762 | DB54: 1294661 | DC54: 1294661 | DD54: 51074 | DE54: 51074 | DF54: 5392329 | DG54: 5392329 | DJ54: -9634288 | DK54: -9534939 | DP54: -2896224 | DQ54: -2796875 | DR54: 1770386 | EJ54: 1770386 | EP54: 58910425 | EQ54: 60789637 | ER54: 5790808 | ES54: 4622131 | EV54: 794979 | EW54: 769538 | EZ54: 4071662 | FA54: 2091378 | FJ54: 591345 | FK54: 1144510 | FN54: 94858 | FO54: 391495 | FP54: 23611 | FQ54: 23611 | FR54: 214353 | FS54: 201599 | FT54: 6004840 | FU54: 4312710 | FV54: 47114777 | FW54: 51854796 | GB54: 60680811 | GC54: 60789637 | GD54: 57784587 | GE54: 57992762
A55: 20006 | B55: 0 | C55: 200383721 | D55: "QONIRAT UN ZAVODI" AJ | E55: 35 | F55: 12 | G55: 0 | H55: 1 | I55: 2020 | J55: 4 | K55: N | L55: 2 | M55: 30 | N55: 0 | O55: 44258.49 | P55: 11557219 | Q55: 11759499 | R55: 2502538 | S55: 3082349 | T55: 9054681 | U55: 8677150 | AB55: 1056517 | AC55: 1056517 | AD55: 40596 | AE55: 40596 | AH55: 1004921 | AI55: 1004921 | AL55: 11000 | AM55: 11000 | AQ55: 541025 | AV55: 10111198 | AW55: 10274692 | AX55: 24227714 | AY55: 25356337 | AZ55: 20775824 | BA55: 23038561 | BD55: 3451890 | BE55: 2317776 | BL55: 16416091 | BM55: 20940766 | BP55: 2867699 | BQ55: 4540296 | BT55: 280983 | BU55: 1097105 | BV55: 9608 | BW55: 1300 | BX55: 12796045 | BY55: 14901622 | BZ55: 31522 | CA55: 15622 | CC55: 54 | CD55: 211657 | CE55: 211657 | CF55: 218577 | CG55: 173110 | CJ55: 23731 | CK55: 48354 | CN55: 4787 | CO55: 35005 | CR55: 18944 | CS55: 13349 | CV55: 1164438 | CW55: 1164438 | CX55: 41831974 | CY55: 47509895 | CZ55: 51943172 | DA55: 57784587 | DB55: 1294661 | DC55: 1294661 | DD55: 51074 | DE55: 51074 | DF55: 5392329 | DG55: 5392329 | DJ55: -9725286 | DK55: -9634288 | DP55: -2987222 | DQ55: -2896224 | DR55: 2624902 | DS55: 1770386 | EJ55: 2624902 | EK55: 1770386 | EP55: 52305496 | EQ55: 58910425 | ER55: 6697549 | ES55: 5790808 | EV55: 1860245 | EW55: 794979 | EZ55: 2865575 | FA55: 4071662 | FJ55: 796340 | FK55: 591345 | FN55: 586138 | FO55: 94858 | FP55: 23688 | FQ55: 23611 | FR55: 512427 | FS55: 214353 | FT55: 8124723 | FU55: 6004840 | FV55: 37483224 | FW55: 47114777 | FZ55: 53136 | GB55: 54930398 | GC55: 60680811 | GD55: 51943176 | GE55: 57784587
A56: 20006 | B56: 0 | C56: 200383721 | D56: "QONIRAT UN ZAVODI" AJ | E56: 35 | F56: 12 | G56: 0 | H56: 1 | I56: 2019 | J56: 4 | K56: N | L56: 2 | M56: 30 | N56: 0 | O56: 43951.435 | P56: 11082482 | Q56: 10965525 | R56: 2389176 | S56: 2798240 | T56: 8693306 | U56: 8167285 | AB56: 1230108 | AC56: 1056517 | AD56: 40596 | AE56: 40596 | AH56: 1178512 | AI56: 1004921 | AL56: 11000 | AM56: 11000 | AV56: 9923414 | AW56: 9223802 | AX56: 17260868 | AY56: 24227714 | AZ56: 16336265 | BA56: 20775824 | BD56: 924603 | BE56: 3451890 | BL56: 14821454 | BM56: 16416091 | BP56: 2850376 | BQ56: 2867699 | BT56: 837308 | BU56: 280983 | BV56: 11582 | BW56: 9608 | BX56: 10648369 | BY56: 12796045 | CA56: 31522 | CD56: 211657 | CE56: 211657 | CF56: 262162 | CG56: 218577 | CJ56: 712691 | CK56: 23731 | CN56: 15252 | CO56: 4787 | CR56: 697439 | CS56: 18944 | CV56: 1164438 | CW56: 1164438 | CX56: 33959451 | CY56: 41831974 | CZ56: 43882865 | DA56: 51055776 | DB56: 1294661 | DC56: 1294661 | DD56: 51074 | DE56: 51074 | DF56: 4504932 | DG56: 4504932 | DJ56: -10313909 | DK56: -9725289 | DP56: -4463242 | DQ56: -3874622 | DR56: 4560502 | DS56: 2624902 | EJ56: 4560502 | EK56: 2624902 | EP56: 43785605 | EQ56: 52305496 | ER56: 15348023 | ES56: 6697549 | EV56: 3025792 | EW56: 1860245 | EZ56: 5819780 | FA56: 2865575 | FJ56: 4745945 | FK56: 796340 | FN56: 1462868 | FO56: 586138 | FP56: 75454 | FQ56: 23688 | FR56: 218184 | FS56: 512427 | FT56: 3183949 | FU56: 8124723 | FV56: 25253633 | FW56: 37483224 | GA56: 53136 | GB56: 48346107 | GC56: 54930398 | GD56: 43882865 | GE56: 51055776
A57: 20006 | B57: 0 | C57: 200383721 | D57: "QONIRAT UN ZAVODI" AJ | E57: 35 | F57: 12 | G57: 0 | H57: 1 | I57: 2018 | J57: 4 | K57: N | L57: 2 | M57: 30 | N57: 0 | O57: 43537.694 | P57: 10645834 | Q57: 10392759 | R57: 1965448 | S57: 2239418 | T57: 8680386 | U57: 8153341 | AB57: 428659 | AC57: 1230108 | AD57: 40596 | AE57: 40596 | AH57: 383063 | AI57: 1178512 | AL57: 5000 | AM57: 11000 | AR57: 1164438 | AV57: 10273483 | AW57: 9383449 | AX57: 20275453 | AY57: 17260868 | AZ57: 18467873 | BA57: 16336265 | BD57: 1807580 | BE57: 924603 | BL57: 16632561 | BM57: 14821454 | BP57: 2929486 | BQ57: 2850376 | BT57: 716111 | BU57: 837308 | BV57: 5470 | BW57: 11582 | BX57: 11820268 | BY57: 10648369 | BZ57: 195818 | CB57: 464193 | CD57: 211657 | CE57: 211657 | CF57: 289558 | CG57: 262162 | CJ57: 8379 | CK57: 712691 | CN57: 142 | CO57: 15252 | CR57: 8237 | CS57: 697439 | CW57: 1164438 | CX57: 36916393 | CY57: 33959451 | CZ57: 47189876 | DA57: 43342900 | DB57: 1294661 | DC57: 1294661 | DD57: 51074 | DE57: 51074 | DF57: 3964967 | DG57: 3964967 | DJ57: -10328593 | DK57: -10313909 | DP57: -5017891 | DQ57: -5003207 | DR57: 11797100 | DS57: 4560502 | EJ57: 11797100 | EK57: 4560502 | EP57: 40410667 | EQ57: 43785605 | ER57: 15537729 | ES57: 15348023 | EV57: 1903743 | EW57: 3025792 | EZ57: 5245675 | FA57: 5819780 | FD57: 7249632 | FJ57: 51041 | FK57: 4745945 | FN57: 218660 | FO57: 1462868 | FP57: 66975 | FQ57: 75454 | FR57: 802003 | FS57: 218184 | FU57: 3183949 | FV57: 24872938 | FW57: 25253633 | GB57: 52207767 | GC57: 48346107 | GD57: 47189876 | GE57: 43342900
A58: 20006 | B58: 0 | C58: 200409204 | D58: "URGANCHKORMMASH" AJ | E58: 33 | F58: 1 | G58: 0 | H58: 1 | I58: 2021 | J58: 4 | K58: N | L58: 1 | M58: 30 | N58: 0 | O58: 44603.592 | P58: 5287662 | Q58: 5798419 | R58: 4106078 | S58: 4281553 | T58: 1181584 | U58: 1516866 | AB58: 536581 | AC58: 168692 | AD58: 138692 | AE58: 138692 | AF58: 30000 | AG58: 30000 | AJ58: 367889 | AN58: 423478 | AO58: 180000 | AP58: 1261402 | AQ58: 1272185 | AV58: 3403045 | AW58: 3137743 | AX58: 7452181 | AY58: 15907592 | AZ58: 4990523 | BA58: 10409020 | BD58: 1978315 | BE58: 4842778 | BF58: 483343 | BG58: 655794 | BK58: 1211313 | BL58: 1522446 | BM58: 8437513 | BP58: 1062340 | BQ58: 6837305 | BV58: 15559 | BW58: 8394 | BX58: 81328 | BY58: 1588813 | BZ58: 360968 | CA58: 3001 | CB58: 2251 | CJ58: 102483 | CK58: 154733 | CN58: 11762 | CO58: 51896 | CP58: 90721 | CQ58: 93839 | CS58: 8998 | CX58: 9077110 | CY58: 25711151 | CZ58: 12480155 | DA58: 28848894 | DB58: 650910 | DC58: 650910 | DD58: 80993 | DE58: 80993 | DF58: 968017 | DG58: 966791 | DJ58: 6057594 | DK58: 7521125 | DP58: 7757514 | DQ58: 9219819 | DR58: 1792972 | DS58: 2000000 | EJ58: 1567972 | EL58: 225000 | EM58: 2000000 | EP58: 2929669 | EQ58: 17629075 | ER58: 2929669 | ES58: 5670903 | EV58: 2133294 | EW58: 2437512 | FH58: 116585 | FI58: 163208 | FJ58: 29381 | FK58: 482229 | FO58: 32392 | FP58: 364822 | FQ58: 781746 | FR58: 202319 | FS58: 283461 | FU58: 11958172 | FZ58: 83268 | GA58: 1490355 | GB58: 4722641 | GC58: 19629075 | GD58: 12480155 | GE58: 28848894
A59: 20006 | B59: 0 | C59: 200409204 | D59: "URGANCHKORMMASH" AJ | E59: 33 | F59: 1 | G59: 0 | H59: 1 | I59: 2020 | J59: 4 | K59: N | L59: 1 | M59: 30 | N59: 0 | O59: 44239.646 | P59: 4749054 | Q59: 5287662 | R59: 3847905 | S59: 4106078 | T59: 901149 | U59: 1181584 | AB59: 536581 | AC59: 536581 | AD59: 138692 | AE59: 138692 | AF59: 30000 | AG59: 30000 | AJ59: 367889 | AK59: 367889 | AN59: 243478 | AO59: 423478 | AP59: 704395 | AQ59: 1261402 | AV59: 2385603 | AW59: 3403045 | AX59: 6734395 | AY59: 7452181 | AZ59: 4558598 | BA59: 4990523 | BD59: 1549803 | BE59: 1978315 | BF59: 625994 | BG59: 483343 | BL59: 2506457 | BM59: 1522446 | BP59: 1099700 | BQ59: 1062340 | BV59: 7203 | BW59: 15559 | BX59: 1345021 | BY59: 81328 | BZ59: 54442 | CA59: 360968 | CC59: 2251 | CH59: 91 | CJ59: 120467 | CK59: 102483 | CN59: 113164 | CO59: 11762 | CP59: 7303 | CQ59: 90721 | CX59: 9361319 | CY59: 9077110 | CZ59: 11746922 | DA59: 12480155 | DB59: 650910 | DC59: 650910 | DD59: 80993 | DE59: 80993 | DF59: 907377 | DG59: 968017 | DJ59: 4355181 | DK59: 6057594 | DP59: 5994461 | DQ59: 7757514 | DR59: 4024028 | DS59: 1792972 | EJ59: 3031028 | EK59: 1567972 | EL59: 993000 | EM59: 225000 | EP59: 1728433 | EQ59: 2929669 | ER59: 1728433 | ES59: 2929669 | EV59: 333447 | EW59: 2133294 | EZ59: 91291 | FH59: 205851 | FI59: 116585 | FJ59: 103602 | FK59: 29381 | FN59: 28405 | FP59: 636985 | FQ59: 364822 | FR59: 247844 | FS59: 202319 | FZ59: 81008 | GA59: 83268 | GB59: 5752461 | GC59: 4722641 | GD59: 11746922 | GE59: 12480155
A60: 20006 | B60: 0 | C60: 200409204 | D60: "URGANCHKORMMASH" AJ | E60: 33 | F60: 1 | G60: 0 | H60: 1 | I60: 2019 | J60: 4 | K60: N | L60: 2 | M60: 30 | N60: 0 | O60: 43902.598 | P60: 4355015 | Q60: 4749054 | R60: 3756222 | S60: 3847905 | T60: 598793 | U60: 901149 | AB60: 506260 | AC60: 536581 | AD60: 138371 | AE60: 138692 | AG60: 30000 | AJ60: 367889 | AK60: 367889 | AO60: 423478 | AQ60: 524395 | AV60: 1105053 | AW60: 2385603 | AX60: 5287074 | AY60: 6734395 | AZ60: 4354942 | BA60: 4558598 | BD60: 306138 | BE60: 1549803 | BF60: 625994 | BG60: 625994 | BL60: 1214986 | BM60: 2506457 | BP60: 1100683 | BQ60: 1099700 | BV60: 22074 | BW60: 7203 | BX60: 28131 | BY60: 1345021 | BZ60: 36662 | CA60: 54442 | CB60: 26956 | CH60: 480 | CI60: 91 | CJ60: 366301 | CK60: 120467 | CN60: 167092 | CO60: 113164 | CP60: 126495 | CQ60: 7303 | CR60: 72714 | CX60: 6868361 | CY60: 9361319 | CZ60: 7973414 | DA60: 11746922 | DB60: 650910 | DC60: 650910 | DD60: 80993 | DE60: 80993 | DF60: 907805 | DG60: 907377 | DJ60: 4713434 | DK60: 4355181 | DP60: 6353142 | DQ60: 5994461 | DS60: 4024028 | EK60: 3031028 | EM60: 993000 | EP60: 1620272 | EQ60: 1728433 | ER60: 1620272 | ES60: 1728433 | EV60: 1284535 | EW60: 333447 | FA60: 91291 | FH60: 79686 | FI60: 205851 | FJ60: 14628 | FK60: 103602 | FN60: 3145 | FO60: 28405 | FP60: 150629 | FQ60: 636985 | FR60: 65605 | FS60: 247844 | FZ60: 22044 | GA60: 81008 | GB60: 1620272 | GC60: 5752461 | GD60: 7973414 | GE60: 11746922
A61: 20006 | B61: 0 | C61: 200409204 | D61: "URGANCHKORMMASH" AJ | E61: 33 | F61: 1 | G61: 0 | H61: 1 | I61: 2018 | J61: 4 | K61: N | L61: 1 | M61: 30 | N61: 0 | O61: 43507.708 | P61: 3162390 | Q61: 3136076 | R61: 2659016 | S61: 2658433 | T61: 503374 | U61: 477643 | AB61: 382371 | AC61: 506260 | AD61: 138371 | AE61: 138371 | AJ61: 244000 | AK61: 367889 | AV61: 885745 | AW61: 983903 | AX61: 4369282 | AY61: 5287074 | AZ61: 2884676 | BA61: 4354942 | BD61: 1446872 | BE61: 306138 | BF61: 37734 | BG61: 625994 | BL61: 1179835 | BM61: 1214986 | BP61: 516211 | BQ61: 1100683 | BV61: 8670 | BW61: 22074 | BX61: 614545 | BY61: 28131 | BZ61: 18112 | CA61: 36662 | CB61: 21817 | CC61: 26956 | CH61: 480 | CI61: 480 | CJ61: 872676 | CK61: 366301 | CN61: 826427 | CO61: 167092 | CP61: 46249 | CQ61: 126495 | CS61: 72714 | CX61: 6421793 | CY61: 6868361 | CZ61: 7307538 | DA61: 7852264 | DB61: 650910 | DC61: 650910 | DD61: 80993 | DE61: 80993 | DF61: 799181 | DG61: 786655 | DJ61: 2778548 | DK61: 4713434 | DP61: 4309632 | DQ61: 6231992 | DR61: 1940000 | EL61: 1940000 | EP61: 1057906 | EQ61: 1620272 | ER61: 1057906 | ES61: 1620272 | EV61: 875280 | EW61: 1284535 | FH61: 75213 | FI61: 79686 | FK61: 14628 | FN61: 1055 | FO61: 3145 | FP61: 53114 | FQ61: 150629 | FR61: 45178 | FS61: 65605 | FZ61: 8066 | GA61: 22044 | GB61: 2997906 | GC61: 1620272 | GD61: 7307538 | GE61: 7852264
A62: 20006 | B62: 0 | C62: 200426279 | D62: "BOG'OT DON" AJ | E62: 33 | F62: 11 | G62: 0 | H62: 1 | I62: 2021 | J62: 4 | K62: N | L62: 2 | M62: 30 | N62: 0 | O62: 44621.482 | P62: 11286070 | Q62: 12809820 | R62: 5385799 | S62: 6427276 | T62: 5900271 | U62: 6382544 | V62: 0 | W62: 0 | X62: 0 | Y62: 0 | Z62: 0 | AA62: 0 | AB62: 2129407 | AC62: 2129407 | AD62: 318435 | AE62: 318435 | AF62: 0 | AG62: 0 | AH62: 1810972 | AI62: 1810972 | AJ62: 0 | AK62: 0 | AL62: 0 | AM62: 0 | AN62: 0 | AO62: 0 | AP62: 391305 | AQ62: 0 | AR62: 0 | AS62: 0 | AT62: 0 | AU62: 0 | AV62: 8420983 | AW62: 8511951 | AX62: 28847212 | AY62: 28333023 | AZ62: 27011921 | BA62: 26008199 | BB62: 1574 | BC62: 19195 | BD62: 1788717 | BE62: 2270538 | BF62: 45000 | BG62: 35091 | BH62: 8828 | BI62: 1851706 | BJ62: 0 | BK62: 0 | BL62: 6975164 | BM62: 3972526 | BN62: 0 | BO62: 0 | BP62: 163385 | BQ62: 227754 | BR62: 0 | BS62: 0 | BT62: 3512 | BU62: 226649 | BV62: 3 | BW62: 22099 | BX62: 4664415 | BY62: 3284075 | BZ62: 2029496 | CA62: 210305 | CB62: 1622 | CC62: 130 | CD62: 0 | CE62: 0 | CF62: 0 | CG62: 0 | CH62: 112731 | CI62: 1514 | CJ62: 127870 | CK62: 1394041 | CL62: 0 | CM62: 0 | CN62: 28825 | CO62: 758660 | CP62: 0 | CQ62: 0 | CR62: 99045 | CS62: 635381 | CT62: 0 | CU62: 0 | CV62: 0 | CW62: 0 | CX62: 35959074 | CY62: 35551296 | CZ62: 44380057 | DA62: 44063247 | DB62: 923288 | DC62: 923288 | DD62: 31313 | DE62: 31313 | DF62: 1407977 | DG62: 1405551 | DH62: 0 | DI62: 0 | DJ62: 6085286 | DK62: 5992196 | DL62: 0 | DM62: 0 | DN62: 0 | DO62: 0 | DP62: 8447864 | DQ62: 8352348 | DR62: 83333 | DS62: 0 | DT62: 0 | DU62: 0 | DV62: 0 | DW62: 0 | DX62: 0 | DY62: 0 | DZ62: 0 | EA62: 0 | EB62: 0 | EC62: 0 | ED62: 0 | EE62: 0 | EF62: 0 | EG62: 0 | EH62: 0 | EI62: 0 | EJ62: 83333 | EK62: 0 | EL62: 0 | EM62: 0 | EN62: 0 | EO62: 0 | EP62: 35848860 | EQ62: 35710899 | ER62: 2707972 | ES62: 1854405 | ET62: 0 | EU62: 0 | EV62: 991387 | EW62: 1020213 | EX62: 0 | EY62: 0 | EZ62: 0 | FA62: 0 | FB62: 0 | FC62: 0 | FD62: 0 | FE62: 0 | FF62: 0 | FG62: 0 | FH62: 193216 | FI62: 160961 | FJ62: 1584 | FK62: 545247 | FL62: 0 | FM62: 0 | FN62: 101623 | FO62: 74859 | FP62: 1297228 | FQ62: 39184 | FR62: 47772 | FS62: 0 | FT62: 514400 | FU62: 1688873 | FV62: 32626488 | FW62: 32167621 | FX62: 0 | FY62: 0 | FZ62: 75162 | GA62: 13941 | GB62: 35932193 | GC62: 35710899 | GD62: 44380057 | GE62: 44063247
A63: 20006 | B63: 0 | C63: 200426279 | D63: "BOG'OT DON" AJ | E63: 33 | F63: 11 | G63: 0 | H63: 1 | I63: 2020 | J63: 4 | K63: N | L63: 2 | M63: 30 | N63: 0 | O63: 44240.384 | P63: 10457814 | Q63: 11286070 | R63: 4096436 | S63: 5385799 | T63: 6361378 | U63: 5900271 | V63: 0 | W63: 0 | X63: 0 | Y63: 0 | Z63: 0 | AA63: 0 | AB63: 2023367 | AC63: 2129407 | AD63: 318435 | AE63: 318435 | AF63: 0 | AG63: 0 | AH63: 1704932 | AI63: 1810972 | AJ63: 0 | AK63: 0 | AL63: 0 | AM63: 0 | AN63: 0 | AO63: 0 | AP63: 534369 | AQ63: 391305 | AR63: 0 | AS63: 0 | AT63: 0 | AU63: 0 | AV63: 8919114 | AW63: 8420983 | AX63: 31138060 | AY63: 28847212 | AZ63: 28498152 | BA63: 27011921 | BB63: 810 | BC63: 1574 | BD63: 2639079 | BE63: 1788717 | BF63: 19 | BG63: 45000 | BH63: 3594 | BI63: 8828 | BJ63: 0 | BK63: 0 | BL63: 6628607 | BM63: 6975164 | BN63: 0 | BO63: 0 | BP63: 351075 | BQ63: 163385 | BR63: 0 | BS63: 0 | BT63: 45855 | BU63: 3512 | BV63: 126 | BW63: 3 | BX63: 5673879 | BY63: 4664415 | BZ63: 552146 | CA63: 2029496 | CB63: 5526 | CC63: 1622 | CD63: 0 | CE63: 0 | CF63: 0 | CG63: 0 | CH63: 0 | CI63: 112731 | CJ63: 908457 | CK63: 127870 | CL63: 0 | CM63: 0 | CN63: 681912 | CO63: 28825 | CP63: 0 | CQ63: 0 | CR63: 226545 | CS63: 99045 | CT63: 0 | CU63: 0 | CV63: 0 | CW63: 0 | CX63: 38678718 | CY63: 35959074 | CZ63: 47597832 | DA63: 44380057 | DB63: 1312248 | DC63: 923288 | DD63: 31313 | DE63: 31313 | DF63: 1068173 | DG63: 1407977 | DH63: 0 | DI63: 0 | DJ63: 7386651 | DK63: 6085286 | DL63: 12140 | DM63: 0 | DN63: 0 | DO63: 0 | DP63: 9810525 | DQ63: 8447864 | DR63: 306872 | DS63: 83333 | DT63: 0 | DU63: 0 | DV63: 0 | DW63: 0 | DX63: 0 | DY63: 0 | DZ63: 0 | EA63: 0 | EB63: 0 | EC63: 0 | ED63: 0 | EE63: 0 | EF63: 0 | EG63: 0 | EH63: 0 | EI63: 0 | EJ63: 306872 | EK63: 83333 | EL63: 0 | EM63: 0 | EN63: 0 | EO63: 0 | EP63: 37480435 | EQ63: 35848860 | ER63: 3264670 | ES63: 2707972 | ET63: 0 | EU63: 0 | EV63: 1228196 | EW63: 991387 | EX63: 0 | EY63: 0 | EZ63: 1085214 | FA63: 0 | FB63: 0 | FC63: 0 | FD63: 0 | FE63: 0 | FF63: 0 | FG63: 0 | FH63: 56833 | FI63: 193216 | FJ63: 304217 | FK63: 1584 | FL63: 0 | FM63: 0 | FN63: 269845 | FO63: 101623 | FP63: 5770 | FQ63: 1297228 | FR63: 245827 | FS63: 47772 | FT63: 10738647 | FU63: 514400 | FV63: 23477118 | FW63: 32626488 | FX63: 0 | FY63: 0 | FZ63: 68768 | GA63: 75162 | GB63: 37787307 | GC63: 35932193 | GD63: 47597832 | GE63: 44380057
A64: 20006 | B64: 0 | C64: 200426279 | D64: "BOG'OT DON" AJ | E64: 33 | F64: 11 | G64: 0 | H64: 1 | I64: 2019 | J64: 4 | K64: N | L64: 2 | M64: 30 | N64: 0 | O64: 43880.756 | P64: 8078912 | Q64: 10457814 | R64: 3113722 | S64: 4096436 | T64: 4965190 | U64: 6361378 | V64: 0 | W64: 0 | X64: 0 | Y64: 0 | Z64: 0 | AA64: 0 | AB64: 2523367 | AC64: 2023367 | AD64: 318435 | AE64: 318435 | AF64: 0 | AG64: 0 | AH64: 1204932 | AI64: 1704932 | AJ64: 0 | AK64: 0 | AL64: 1000000 | AM64: 0 | AN64: 0 | AO64: 0 | AP64: 534368 | AQ64: 534368 | AR64: 0 | AS64: 0 | AT64: 0 | AU64: 0 | AV64: 8022925 | AW64: 8919113 | AX64: 17768645 | AY64: 31138060 | AZ64: 16001506 | BA64: 28498152 | BB64: 689 | BC64: 810 | BD64: 1548871 | BE64: 2639079 | BF64: 217579 | BG64: 19 | BH64: 0 | BI64: 3594 | BJ64: 0 | BK64: 0 | BL64: 2995694 | BM64: 6628607 | BN64: 0 | BO64: 0 | BP64: 50532 | BQ64: 351075 | BR64: 0 | BS64: 0 | BT64: 46594 | BU64: 45855 | BV64: 255 | BW64: 126 | BX64: 2787447 | BY64: 5673879 | BZ64: 88235 | CA64: 552146 | CB64: 22631 | CC64: 5526 | CD64: 0 | CE64: 0 | CF64: 0 | CG64: 0 | CH64: 0 | CI64: 0 | CJ64: 429180 | CK64: 908457 | CL64: 0 | CM64: 0 | CN64: 174286 | CO64: 681912 | CP64: 0 | CQ64: 0 | CR64: 254894 | CS64: 226545 | CT64: 0 | CU64: 0 | CV64: 0 | CW64: 0 | CX64: 21193519 | CY64: 38678718 | CZ64: 29216444 | DA64: 47597831 | DB64: 1312248 | DC64: 1312248 | DD64: 31312 | DE64: 31312 | DF64: 796894 | DG64: 1068173 | DH64: 0 | DI64: 0 | DJ64: 1930894 | DK64: 7386651 | DL64: 12140 | DM64: 12140 | DN64: 0 | DO64: 0 | DP64: 4083488 | DQ64: 9810524 | DR64: 1050318 | DS64: 306872 | DT64: 0 | DU64: 0 | DV64: 0 | DW64: 0 | DX64: 0 | DY64: 0 | DZ64: 0 | EA64: 0 | EB64: 0 | EC64: 0 | ED64: 0 | EE64: 0 | EF64: 0 | EG64: 0 | EH64: 0 | EI64: 0 | EJ64: 599604 | EK64: 0 | EL64: 450714 | EM64: 306872 | EN64: 0 | EO64: 0 | EP64: 24082638 | EQ64: 37480435 | ER64: 8855638 | ES64: 3264670 | ET64: 0 | EU64: 0 | EV64: 1164652 | EW64: 1228196 | EX64: 0 | EY64: 0 | EZ64: 5547124 | FA64: 1085214 | FB64: 0 | FC64: 0 | FD64: 0 | FE64: 0 | FF64: 0 | FG64: 0 | FH64: 152952 | FI64: 56833 | FJ64: 1248198 | FK64: 304217 | FL64: 0 | FM64: 0 | FN64: 627804 | FO64: 272566 | FP64: 16197 | FQ64: 5770 | FR64: 68124 | FS64: 245827 | FT64: 5321550 | FU64: 10738647 | FV64: 9905450 | FW64: 23477118 | FX64: 0 | FY64: 0 | FZ64: 30587 | GA64: 66047 | GB64: 25132956 | GC64: 37787307 | GD64: 29216444 | GE64: 47597831
A65: 20006 | B65: 0 | C65: 200426279 | D65: "BOG'OT DON" AJ | E65: 33 | F65: 11 | G65: 0 | H65: 1 | I65: 2018 | J65: 4 | K65: N | L65: 2 | M65: 30 | N65: 0 | O65: 43542.387 | P65: 6466037 | Q65: 8078912 | R65: 2459287 | S65: 3113722 | T65: 4006750 | U65: 4965190 | V65: 0 | W65: 0 | X65: 0 | Y65: 0 | Z65: 0 | AA65: 0 | AB65: 1545048 | AC65: 2523367 | AD65: 318435 | AE65: 318435 | AF65: 0 | AG65: 0 | AH65: 1224612 | AI65: 2204932 | AJ65: 0 | AK65: 0 | AL65: 2001 | AM65: 0 | AN65: 0 | AO65: 0 | AP65: 933275 | AQ65: 534368 | AR65: 0 | AS65: 0 | AT65: 0 | AU65: 0 | AV65: 6485073 | AW65: 8022925 | AX65: 25058211 | AY65: 17768643 | AZ65: 22098827 | BA65: 16001504 | BB65: 5992 | BC65: 689 | BD65: 2953392 | BE65: 1548871 | BF65: 0 | BG65: 217579 | BH65: 0 | BI65: 0 | BJ65: 0 | BK65: 0 | BL65: 3033318 | BM65: 2995972 | BN65: 0 | BO65: 0 | BP65: 13565 | BQ65: 15040 | BR65: 0 | BS65: 0 | BT65: 50861 | BU65: 46594 | BV65: 0 | BW65: 0 | BX65: 2769194 | BY65: 2668955 | BZ65: 57717 | CA65: 88235 | CB65: 0 | CC65: 22631 | CD65: 0 | CE65: 0 | CF65: 45259 | CG65: 36025 | CH65: 96722 | CI65: 118492 | CJ65: 48485 | CK65: 428902 | CL65: 0 | CM65: 0 | CN65: 7340 | CO65: 242352 | CP65: 0 | CQ65: 0 | CR65: 41145 | CS65: 186550 | CT65: 0 | CU65: 0 | CV65: 0 | CW65: 0 | CX65: 28140014 | CY65: 21193517 | CZ65: 34625087 | DA65: 29216442 | DB65: 1312248 | DC65: 1312248 | DD65: 31312 | DE65: 31312 | DF65: 788518 | DG65: 796893 | DH65: 0 | DI65: 0 | DJ65: 109347 | DK65: 1930893 | DL65: 12140 | DM65: 12140 | DN65: 0 | DO65: 0 | DP65: 2253565 | DQ65: 4083486 | DR65: 1575000 | DS65: 1050318 | DT65: 0 | DU65: 0 | DV65: 0 | DW65: 0 | DX65: 0 | DY65: 0 | DZ65: 0 | EA65: 0 | EB65: 0 | EC65: 0 | ED65: 0 | EE65: 0 | EF65: 0 | EG65: 0 | EH65: 0 | EI65: 0 | EJ65: 1575000 | EK65: 1050318 | EL65: 0 | EM65: 0 | EN65: 0 | EO65: 0 | EP65: 30796522 | EQ65: 24082638 | ER65: 7669081 | ES65: 8855638 | ET65: 0 | EU65: 0 | EV65: 749649 | EW65: 109156 | EX65: 0 | EY65: 0 | EZ65: 5250956 | FA65: 5547124 | FB65: 0 | FC65: 0 | FD65: 137393 | FE65: 0 | FF65: 0 | FG65: 0 | FH65: 0 | FI65: 558186 | FJ65: 504662 | FK65: 1248198 | FL65: 0 | FM65: 0 | FN65: 312649 | FO65: 627804 | FP65: 23924 | FQ65: 16197 | FR65: 47466 | FS65: 68124 | FT65: 13529165 | FU65: 5321550 | FV65: 9598276 | FW65: 9905450 | FX65: 0 | FY65: 0 | FZ65: 642382 | GA65: 680849 | GB65: 32371522 | GC65: 25132956 | GD65: 34625087 | GE65: 29216442
A66: 20006 | B66: 0 | C66: 200465215 | D66: "OHANGARONSHIFER" AJ | E66: 27 | F66: 19 | G66: 2 | H66: 1 | I66: 2021 | J66: 4 | K66: N | L66: 1 | M66: 30 | N66: 0 | O66: 44606.561 | P66: 31419033 | Q66: 32324670 | R66: 23453602 | S66: 24808300 | T66: 7965431 | U66: 7516370 | V66: 490721 | W66: 490721 | X66: 490721 | Y66: 490721 | Z66: 0 | AA66: 0 | AB66: 15149736 | AC66: 15143736 | AD66: 172206 | AE66: 172206 | AJ66: 8697836 | AK66: 8697836 | AL66: 6279694 | AM66: 6273694 | AN66: 428852 | AO66: 409825 | AP66: 8922625 | AQ66: 10094487 | AR66: 1167300 | AS66: 1160900 | AV66: 33633944 | AW66: 34325318 | AX66: 8971407 | AY66: 8496520 | AZ66: 8171258 | BA66: 7990819 | BB66: 30400 | BC66: 321207 | BD66: 769749 | BE66: 184494 | BI66: 5372608 | BL66: 8429230 | BM66: 7856079 | BP66: 5096400 | BQ66: 4002490 | BV66: 16544 | BW66: 14709 | BX66: 609646 | BY66: 1510437 | CA66: 55367 | CC66: 9827 | CF66: 5000 | CG66: 0 | CH66: 2701640 | CI66: 2263249 | CJ66: 64965 | CK66: 152686 | CN66: 4463 | CO66: 0 | CP66: 0 | CQ66: 0 | CR66: 60502 | CS66: 152686 | CT66: 3715036 | CU66: 3715036 | CV66: 20340 | CW66: 20340 | CX66: 21200978 | CY66: 25613269 | CZ66: 54834922 | DA66: 59938587 | DB66: 1231330 | DC66: 1231330 | DD66: 19929 | DE66: 19929 | DF66: 16349365 | DG66: 17527477 | DJ66: 11901351 | DK66: 11954651 | DP66: 29501975 | DQ66: 30733387 | EP66: 23784007 | EQ66: 29205200 | ER66: 16276692 | ES66: 21697885 | EV66: 2054797 | EW66: 3163385 | FH66: 8512118 | FI66: 11085104 | FJ66: 1441896 | FK66: 2571106 | FN66: 1452778 | FO66: 1966231 | FP66: 326435 | FQ66: 326435 | FR66: 292168 | FS66: 744856 | FV66: 7507315 | FW66: 7507315 | FZ66: 2196500 | GA66: 1840768 | GB66: 23784007 | GC66: 29205200 | GD66: 53285982 | GE66: 59938587
A67: 20006 | B67: 0 | C67: 200465215 | D67: "OHANGARONSHIFER" AJ | E67: 27 | F67: 19 | G67: 2 | H67: 1 | I67: 2020 | J67: 4 | K67: N | L67: 1 | M67: 30 | N67: 0 | O67: 44242.89 | P67: 30423467 | Q67: 31419033 | R67: 22415455 | S67: 23453602 | T67: 8008012 | U67: 7965431 | V67: 490721 | W67: 490721 | X67: 490721 | Y67: 490721 | Z67: 0 | AA67: 0 | AB67: 15147220 | AC67: 15149736 | AD67: 172206 | AE67: 172206 | AJ67: 8697836 | AK67: 8697836 | AL67: 6277178 | AM67: 6279694 | AN67: 428852 | AO67: 428852 | AP67: 8374237 | AQ67: 8922625 | AR67: 1389317 | AS67: 1167300 | AV67: 33347638 | AW67: 33633944 | AX67: 8366687 | AY67: 8971407 | AZ67: 8179187 | BA67: 8171258 | BB67: 33698 | BC67: 30400 | BD67: 153802 | BE67: 769749 | BL67: 9126268 | BM67: 8429230 | BN67: 6159024 | BP67: 5933157 | BQ67: 5096400 | BV67: 15109 | BW67: 16544 | BX67: 516336 | BY67: 609646 | BZ67: 268572 | CB67: 9827 | CG67: 5000 | CH67: 2383267 | CI67: 2701640 | CJ67: 70336 | CK67: 64965 | CN67: 1504 | CO67: 4463 | CR67: 68832 | CS67: 60502 | CT67: 3715036 | CU67: 3715036 | CV67: 20340 | CW67: 20340 | CX67: 21298667 | CY67: 21200978 | CZ67: 54646305 | DA67: 54834922 | DB67: 1231330 | DC67: 1231330 | DD67: 19929 | DE67: 19929 | DF67: 15050321 | DG67: 16349365 | DJ67: 16653274 | DK67: 14605558 | DP67: 32954854 | DQ67: 32206182 | EP67: 21691451 | EQ67: 22628740 | ER67: 12800137 | ES67: 15474512 | ET67: 5399291 | EV67: 1613515 | EW67: 2020070 | FH67: 5877983 | FI67: 8088205 | FJ67: 874915 | FK67: 1236461 | FN67: 1016380 | FO67: 1417089 | FP67: 326435 | FQ67: 326435 | FR67: 350045 | FS67: 294843 | FT67: 393252 | FV67: 8498062 | FW67: 7154228 | FZ67: 2740864 | GA67: 2091409 | GB67: 21691451 | GC67: 22628740 | GD67: 54646305 | GE67: 54834922
A68: 20006 | B68: 0 | C68: 200465215 | D68: "OHANGARONSHIFER" AJ | E68: 27 | F68: 19 | G68: 2 | H68: 1 | I68: 2019 | J68: 4 | K68: N | L68: 1 | M68: 30 | N68: 0 | O68: 43876.87 | P68: 28398166 | Q68: 30423467 | R68: 21179763 | S68: 22415455 | T68: 7218403 | U68: 8008012 | V68: 490721 | W68: 490721 | X68: 490721 | Y68: 490721 | Z68: 0 | AA68: 0 | AB68: 14547978 | AC68: 15147220 | AD68: 172206 | AE68: 172206 | AF68: 83518 | AJ68: 8697836 | AK68: 8697836 | AL68: 5594418 | AM68: 6277178 | AN68: 464350 | AO68: 428852 | AP68: 7740728 | AQ68: 8374237 | AR68: 1402081 | AS68: 1389317 | AV68: 31373540 | AW68: 33347638 | AX68: 10629329 | AY68: 8366687 | AZ68: 8846533 | BA68: 8179187 | BB68: 33685 | BC68: 33698 | BD68: 1749111 | BE68: 153802 | BH68: 969 | BL68: 6538506 | BM68: 9126268 | BN68: 4495879 | BO68: 6159024 | BP68: 2772648 | BQ68: 5933157 | BV68: 18961 | BW68: 15109 | BX68: 859837 | BY68: 516336 | BZ68: 143994 | CA68: 268572 | CC68: 9827 | CH68: 2743066 | CI68: 2383267 | CJ68: 154376 | CK68: 70336 | CN68: 8982 | CO68: 1504 | CR68: 145394 | CS68: 68832 | CT68: 2408798 | CU68: 3715036 | CV68: 20340 | CW68: 20340 | CX68: 19752318 | CY68: 21298667 | CZ68: 51125858 | DA68: 54646305 | DB68: 1231330 | DC68: 1231330 | DD68: 19929 | DE68: 19929 | DF68: 13559033 | DG68: 15050321 | DJ68: 18701475 | DK68: 16653274 | DP68: 33511767 | DQ68: 32954854 | EP68: 17614091 | EQ68: 21691451 | ER68: 5335797 | ES68: 12800137 | ET68: 1134692 | EU68: 5399291 | EV68: 1483479 | EW68: 1613515 | FH68: 396258 | FI68: 5877983 | FJ68: 547907 | FK68: 874915 | FN68: 615792 | FO68: 1016380 | FP68: 326435 | FQ68: 326435 | FR68: 431055 | FS68: 350045 | FT68: 3712785 | FU68: 393252 | FV68: 8565509 | FW68: 8498062 | FZ68: 1534871 | GA68: 2740864 | GB68: 17614091 | GC68: 21691451 | GD68: 51125858 | GE68: 54646305
A69: 20006 | B69: 0 | C69: 200465215 | D69: "OHANGARONSHIFER" AJ | E69: 27 | F69: 19 | G69: 2 | H69: 1 | I69: 2018 | J69: 4 | K69: N | L69: 1 | M69: 30 | N69: 0 | O69: 43511.949 | P69: 25724216 | Q69: 28078166 | R69: 19309768 | S69: 21175763 | T69: 6414448 | U69: 6902403 | V69: 490721 | W69: 490721 | X69: 477971 | Y69: 490721 | Z69: 12750 | AA69: 0 | AB69: 13192978 | AC69: 14547978 | AD69: 172206 | AE69: 172206 | AG69: 83518 | AJ69: 8697836 | AK69: 8697836 | AL69: 4322936 | AM69: 5594418 | AN69: 371478 | AO69: 464350 | AP69: 7170577 | AQ69: 7740728 | AR69: 1382455 | AS69: 1402081 | AV69: 28544686 | AW69: 31057540 | AX69: 11525497 | AY69: 11092360 | AZ69: 11094738 | BA69: 8888297 | BB69: 3637 | BC69: 556223 | BD69: 427122 | BE69: 1647840 | BH69: 20332 | BI69: 969 | BL69: 1966387 | BM69: 5501849 | BP69: 1255012 | BQ69: 2122797 | BV69: 54687 | BW69: 18961 | BX69: 499564 | BY69: 859837 | BZ69: 58873 | CA69: 143994 | CH69: 98251 | CI69: 2356260 | CJ69: 523640 | CK69: 541692 | CN69: 18663 | CO69: 8982 | CP69: 387316 | CQ69: 387316 | CR69: 117661 | CS69: 145394 | CT69: 1445995 | CU69: 2408798 | CV69: 20340 | CW69: 20340 | CX69: 15502191 | CY69: 19566008 | CZ69: 44046877 | DA69: 50623548 | DB69: 1231330 | DC69: 1231330 | DD69: 19929 | DE69: 19929 | DF69: 11399925 | DG69: 13559033 | DJ69: 20571120 | DK69: 19513831 | DP69: 33222304 | DQ69: 34324123 | EP69: 10824573 | EQ69: 16299425 | ER69: 6824573 | ES69: 4021131 | EV69: 348884 | EW69: 1163479 | FH69: 4184993 | FI69: 369290 | FJ69: 1060823 | FK69: 459113 | FN69: 468143 | FO69: 615791 | FP69: 347374 | FQ69: 326435 | FR69: 246987 | FS69: 431055 | FT69: 4000000 | FU69: 3712785 | FW69: 8565509 | FZ69: 167369 | GA69: 655968 | GB69: 10824573 | GC69: 16299425 | GD69: 44046877 | GE69: 50623548
A70: 20006 | B70: 0 | C70: 200479996 | D70: "SURXONOZIQOVQATSANOATI" AJ | E70: 22 | F70: 7 | G70: 0 | H70: 1 | I70: 2021 | J70: 4 | K70: N | L70: 2 | M70: 30 | N70: 0 | O70: 44607.65 | P70: 42863372 | Q70: 42426003 | R70: 24038566 | S70: 26191008 | T70: 18824807 | U70: 16234995 | AB70: 3213096.6 | AC70: 3213096.6 | AD70: 3837.9 | AE70: 3837.9 | AF70: 214000 | AG70: 214000 | AJ70: 2980258.7 | AK70: 2980258.7 | AL70: 15000 | AM70: 15000 | AP70: 144809.16 | AR70: 1102447.4 | AS70: 1058399 | AV70: 23285160 | AW70: 20506491 | AX70: 41116775 | AY70: 37979476 | AZ70: 8134902.8 | BA70: 4735245 | BD70: 32936469 | BE70: 33198828 | BF70: 45402.62 | BG70: 45402.62 | BH70: 3644 | BI70: -13000 | BL70: 13544133 | BM70: 9879699.5 | BP70: 1215644.4 | BQ70: 1040598 | BV70: 1033900.7 | BW70: 171726 | BX70: 9436526.3 | BY70: 6323212 | BZ70: 1014761.8 | CA70: 2092858 | CB70: 278.52 | CC70: 278.52 | CH70: 843021.33 | CI70: 251027 | CJ70: 30615.61 | CK70: 37.67 | CN70: 12077.46 | CP70: 25.67 | CQ70: 25.67 | CR70: 18512.48 | CS70: 12 | CT70: 126419.21 | CU70: 18013 | CX70: 54821587 | CY70: 47864226 | CZ70: 78106747 | DA70: 68370716 | DB70: 9899234.4 | DC70: 9899234.4 | DF70: 9504260.7 | DG70: 9436566 | DJ70: 577269.16 | DK70: -10557949 | DP70: 19980764 | DQ70: 8777851.4 | DR70: 40902479 | DS70: 35923674 | DT70: 0 | EJ70: 40902479 | EK70: 35923674 | EP70: 17223503 | EQ70: 23669190 | ER70: 17017263 | ES70: 13196407 | EV70: 12842505 | EW70: 9490632 | FH70: 2439148.4 | FI70: 1868159 | FJ70: 636518.16 | FK70: 535700 | FN70: 208482.11 | FO70: 312327 | FP70: 360639.76 | FQ70: 333530 | FR70: 519590.22 | FS70: 545412 | FU70: 6766543 | FV70: 206240 | FW70: 3706240 | FZ70: 10379.76 | GA70: 110647 | GB70: 58125982 | GC70: 59592864 | GD70: 78106747 | GE70: 68370715
A71: 20006 | B71: 0 | C71: 200479996 | D71: "SURXONOZIQOVQATSANOATI" AJ | E71: 22 | F71: 7 | G71: 0 | H71: 1 | I71: 2020 | J71: 4 | K71: N | L71: 1 | M71: 30 | N71: 0 | O71: 44243.655 | P71: 39061621 | Q71: 42863372 | R71: 20188975 | S71: 24038566 | T71: 18872646 | U71: 18824807 | AB71: 2998096.6 | AC71: 3213096.6 | AD71: 3837.9 | AE71: 3837.9 | AF71: 214000 | AG71: 214000 | AJ71: 2765258.7 | AK71: 2980258.7 | AL71: 15000 | AM71: 15000 | AQ71: 144809.16 | AR71: 1203982.2 | AS71: 1102447.4 | AV71: 23074724 | AW71: 23285160 | AX71: 46501596 | AY71: 41116775 | AZ71: 11953246 | BA71: 8134902.8 | BD71: 34502947 | BE71: 32936469 | BF71: 45402.62 | BG71: 45402.62 | BH71: 19288 | BI71: 3644 | BL71: 8091757.7 | BM71: 13544133 | BN71: 203224.2 | BO71: 122234.6 | BP71: 2520988.2 | BQ71: 1215644.4 | BV71: 812767.15 | BW71: 1033900.7 | BX71: 3052273.8 | BY71: 9436526.3 | BZ71: 1690956.4 | CA71: 1014761.8 | CB71: 277.97 | CC71: 278.52 | CH71: 14494.14 | CI71: 843021.33 | CJ71: 53741.73 | CK71: 30615.61 | CN71: 48912.13 | CO71: 12077.46 | CP71: 2319.37 | CQ71: 25.67 | CR71: 2510.23 | CS71: 18512.48 | CT71: 66003.38 | CU71: 126419.21 | CX71: 54732387 | CY71: 54821587 | CZ71: 77807111 | DA71: 78106747 | DB71: 9899234.4 | DC71: 9899234.4 | DF71: 8039897 | DG71: 9504260.7 | DJ71: 10922364 | DK71: 577269.16 | DP71: 28861495 | DQ71: 19980764 | DR71: 34000000 | DS71: 40902479 | DT71: 0 | EJ71: 34000000 | EK71: 40902479 | EP71: 14945616 | EQ71: 17223503 | ER71: 14945616 | ES71: 17017263 | ET71: 952828.3 | EU71: 352828.3 | EV71: 9415121.2 | EW71: 12842505 | FH71: 207333.95 | FI71: 2439148.4 | FJ71: 545995.59 | FK71: 636518.16 | FN71: 427030.97 | FO71: 208482.11 | FP71: 3782474.1 | FQ71: 360639.76 | FR71: 523643.43 | FS71: 519590.22 | FW71: 206240 | FZ71: 44016.85 | GA71: 10379.76 | GB71: 48945616 | GC71: 58125982 | GD71: 77807111 | GE71: 78106747
A72: 20006 | B72: 0 | C72: 200479996 | D72: "SURXONOZIQOVQATSANOATI" AJ | E72: 22 | F72: 7 | G72: 0 | H72: 1 | I72: 2019 | J72: 4 | K72: N | L72: 1 | M72: 30 | N72: 0 | O72: 44121.698 | P72: 37130555 | Q72: 39061621 | R72: 17842659 | S72: 20188975 | T72: 19287896 | U72: 18872646 | AB72: 540878 | AC72: 2998096 | AD72: 3838 | AE72: 3838 | AF72: 522040 | AG72: 214000 | AK72: 2765258 | AL72: 15000 | AM72: 15000 | AP72: 314350 | AR72: 1364486 | AS72: 1203982 | AV72: 21507610 | AW72: 23074724 | AX72: 28454223 | AY72: 46501596 | AZ72: 23309040 | BA72: 11953246 | BD72: 5099780 | BE72: 34502947 | BF72: 45403 | BG72: 45403 | BI72: 19288 | BL72: 12897358 | BM72: 8091757 | BO72: 203224.2 | BP72: 365465 | BQ72: 2520988 | BV72: 664766 | BW72: 812767 | BX72: 4085228 | BY72: 3052274 | BZ72: 1990148 | CA72: 1690956 | CB72: 14000 | CC72: 278 | CH72: 5777751 | CI72: 14494 | CJ72: 362015 | CK72: 53742 | CN72: 7352 | CO72: 48912 | CP72: 313578 | CQ72: 2319 | CR72: 41085 | CS72: 2511 | CT72: 75247 | CU72: 66004 | CX72: 41788843 | CY72: 54732387 | CZ72: 63296453 | DA72: 77807111 | DB72: 9899234 | DC72: 9899234 | DF72: 7064585 | DG72: 8039897 | DJ72: 16547725 | DK72: 10922364 | DP72: 33511544 | DQ72: 28861495 | DR72: 20553847 | DS72: 34000000 | EJ72: 20553847 | EK72: 34000000 | EP72: 9231062 | EQ72: 14945616 | ER72: 9231062 | ES72: 14945616 | EU72: 952828.3 | EV72: 5724617 | EW72: 9415121 | FH72: 11876 | FI72: 207334 | FJ72: 777466 | FK72: 545996 | FN72: 1346408 | FO72: 427031 | FP72: 321713 | FQ72: 3782474 | FR72: 1017398 | FS72: 523643 | FZ72: 31584 | GA72: 44017 | GB72: 29784909 | GC72: 48945616 | GD72: 63296453 | GE72: 77807111
A73: 20006 | B73: 0 | C73: 200479996 | D73: "SURXONOZIQOVQATSANOATI" AJ | E73: 22 | F73: 7 | G73: 0 | H73: 1 | I73: 2018 | J73: 4 | K73: N | L73: 3 | M73: 30 | N73: 0 | O73: 43580.428 | P73: 20294851 | Q73: 37130555 | R73: 12990910 | S73: 17842659 | T73: 7303941 | U73: 19287896 | AB73: 584978 | AC73: 540878 | AD73: 3838 | AE73: 3838 | AF73: 566140 | AG73: 522040 | AL73: 15000 | AM73: 15000 | AP73: 869843 | AQ73: 314350 | AR73: 1418036 | AS73: 1364486 | AV73: 10176798 | AW73: 21507610 | AX73: 18556785 | AY73: 28454223 | AZ73: 12321617 | BA73: 23309040 | BD73: 5796967 | BE73: 5099780 | BF73: 438201 | BG73: 45403 | BH73: 164068 | BL73: 18794827 | BM73: 12897358 | BQ73: 365465 | BV73: 1284 | BW73: 664766 | BX73: 1314383 | BY73: 4085228 | BZ73: 143318 | CA73: 1990148 | CC73: 14000 | CF73: 944226 | CH73: 16391616 | CI73: 5777751 | CJ73: 101126 | CK73: 362015 | CN73: 13281 | CO73: 7352 | CP73: 83899 | CQ73: 313578 | CR73: 3946 | CS73: 41085 | CT73: 75247 | CU73: 75247 | CX73: 37692053 | CY73: 41788843 | CZ73: 47868851 | DA73: 63296453 | DB73: 9899234 | DC73: 9899234 | DF73: 4578690 | DG73: 7064585 | DJ73: 7050215 | DK73: 16547725 | DP73: 21528139 | DQ73: 33511544 | DR73: 10770000 | DS73: 20553847 | DT73: 0 | EJ73: 10770000 | EK73: 20553847 | EP73: 15570712 | EQ73: 9231062 | ER73: 14601357 | ES73: 9231062 | EV73: 11479200 | EW73: 5724617 | FH73: 173899 | FI73: 11876 | FJ73: 923743 | FK73: 777466 | FN73: 808948 | FO73: 1346408 | FP73: 688200 | FQ73: 321713 | FR73: 494748 | FS73: 1017398 | FT73: 936000 | FV73: 33355 | FZ73: 32619 | GA73: 31584 | GB73: 26340712 | GC73: 29784909 | GD73: 47868851 | GE73: 63296453
A74: 20006 | B74: 0 | C74: 200523324 | D74: "O'ZINTERIMPEKS" AJ | E74: 26 | F74: 2 | G74: 0 | H74: 1 | I74: 2021 | J74: 4 | K74: N | L74: 2 | M74: 30 | N74: 0 | O74: 44739.706 | P74: 3120776 | R74: 2107316 | T74: 1013460 | U74: 0 | V74: 39050 | X74: 39050 | Z74: 0 | AB74: 48187813 | AC74: 48187813 | AD74: 22962676 | AE74: 22962676 | AF74: 5297503 | AG74: 5297503 | AH74: 1221321 | AI74: 1221321 | AJ74: 915700 | AK74: 915700 | AL74: 17790613 | AM74: 17790613 | AR74: 5749837 | AS74: 5749837 | AV74: 54951110 | AW74: 53937650 | AX74: 998239 | AZ74: 68213 | BF74: 930026 | BL74: 16386095 | BM74: 14275366 | BW74: 1200 | BY74: 44816.74 | BZ74: 197923 | CA74: 1385.49 | CB74: 23413 | CC74: 15858.6 | CH74: 16164759 | CI74: 14212105 | CJ74: 2225166 | CK74: 1363559.3 | CN74: 2196798 | CO74: 1348692.9 | CP74: 9849 | CQ74: 9849 | CR74: 18519 | CS74: 5017.39 | CT74: 5079679 | CU74: 5109679 | CX74: 24689179 | CY74: 20748604 | CZ74: 79640289 | DA74: 74686254 | DB74: 12904341 | DC74: 12904341 | DF74: 2422411 | DG74: 2422411 | DJ74: 9884968 | DK74: 9625402 | DL74: 621630 | DM74: 621630 | DN74: 2119355 | DO74: 2119355 | DP74: 27952705 | DQ74: 27693139 | EP74: 51687584 | EQ74: 46993115 | ER74: 7083714 | ES74: 5798479.6 | EV74: 1406630 | EW74: 76289.63 | FB74: 44603870 | FC74: 41194636 | FH74: 5704790 | FI74: 5704790 | FJ74: -1078870 | FN74: 17400 | FO74: 17400 | FP74: 367080 | FR74: 29660 | FZ74: 637024 | GB74: 51687584 | GC74: 46993115 | GD74: 79640289 | GE74: 74686254
A75: 20006 | B75: 0 | C75: 200523324 | D75: "O'ZINTERIMPEKS" AJ | E75: 26 | F75: 2 | G75: 0 | H75: 1 | I75: 2020 | J75: 4 | K75: N | L75: 2 | M75: 30 | N75: 0 | O75: 44672.568 | P75: 3120776 | Q75: 3120776 | R75: 2078429 | S75: 2107316 | T75: 1042347 | U75: 1013460 | V75: 39050 | W75: 39050 | X75: 39050 | Y75: 39050 | Z75: 0 | AA75: 0 | AB75: 48255015 | AC75: 48187813 | AD75: 22962676 | AE75: 22962676 | AF75: 5297503 | AG75: 5297503 | AH75: 1221321 | AI75: 1221321 | AJ75: 982902 | AK75: 915700 | AL75: 17790613 | AM75: 17790613 | AR75: 5749836 | AS75: 5749837 | AV75: 55047198 | AW75: 54951110 | AX75: 998238 | AY75: 998239 | AZ75: 68213 | BA75: 68213 | BF75: 930025 | BG75: 930026 | BL75: 16513483 | BM75: 16386095 | BX75: 23675 | BZ75: 289316 | CA75: 197923 | CB75: 21733 | CC75: 23413 | CH75: 16178759 | CI75: 16164759 | CJ75: 2115163 | CK75: 2225166 | CN75: 2104576 | CO75: 2196798 | CP75: 9893 | CQ75: 9849 | CR75: 694 | CS75: 18519 | CT75: 5061680 | CU75: 5079679 | CX75: 24688564 | CY75: 24689179 | CZ75: 79735762 | DA75: 79640289 | DB75: 12904341 | DC75: 12904341 | DF75: 2422411 | DG75: 2422411 | DJ75: 9759242 | DK75: 9884968 | DL75: 621630 | DM75: 621630 | DN75: 2119355 | DO75: 2119355 | DP75: 27826979 | DQ75: 27952705 | EP75: 51908783 | EQ75: 51687584 | ER75: 7304905 | ES75: 7083714 | EV75: 1406632 | EW75: 1406630 | FB75: 44603878 | FC75: 44603870 | FH75: 5704798 | FI75: 5704790 | FJ75: 40915 | FK75: -1078870 | FN75: 517 | FO75: 17400 | FP75: 35336 | FQ75: 367080 | FR75: 29683 | FS75: 29660 | FZ75: 87024 | GA75: 637024 | GB75: 51908783 | GC75: 51687584 | GD75: 79735762 | GE75: 79640289
A76: 20006 | B76: 0 | C76: 200523324 | D76: "O'ZINTERIMPEKS" AJ | E76: 26 | F76: 2 | G76: 0 | H76: 1 | I76: 2019 | J76: 4 | K76: N | L76: 1 | M76: 30 | N76: 0 | O76: 43876.596 | P76: 3120776 | Q76: 3120776 | R76: 2020654 | S76: 2078429 | T76: 1100122 | U76: 1042347 | V76: 39050 | W76: 39050 | X76: 39050 | Y76: 39050 | Z76: 0 | AA76: 0 | AB76: 54030485 | AC76: 48255015 | AD76: 22498860 | AE76: 22962676 | AF76: 11420914 | AG76: 5297503 | AH76: 1337196 | AI76: 1221321 | AJ76: 982902 | AK76: 982902 | AL76: 17790613 | AM76: 17790613 | AR76: 5780047 | AS76: 5749836 | AV76: 60910654 | AW76: 55047198 | AX76: 998238 | AY76: 998238 | AZ76: 68213 | BA76: 68213 | BF76: 930025 | BG76: 930025 | BL76: 10898354 | BM76: 16513483 | BX76: 16530 | BY76: 23675 | BZ76: 255742 | CA76: 289316 | CB76: 21141 | CC76: 21733 | CH76: 10604941 | CI76: 16178759 | CJ76: 870336 | CK76: 2115163 | CN76: 364600 | CO76: 2104576 | CP76: 505730 | CQ76: 9893 | CR76: 6 | CS76: 694 | CT76: 5061680 | CU76: 5061680 | CX76: 17828608 | CY76: 24688564 | CZ76: 78739262 | DA76: 79735762 | DB76: 12904341 | DC76: 12904341 | DF76: 2393855 | DG76: 2422411 | DJ76: 8364735 | DK76: 9759242 | DL76: 621630 | DM76: 621630 | DN76: 1576788 | DO76: 2119355 | DP76: 25861349 | DQ76: 27826979 | DR76: 0 | DS76: 0 | EP76: 52877913 | EQ76: 51908783 | ER76: 8277748 | ES76: 7304905 | EV76: 1466145 | EW76: 1406632 | FB76: 44600165 | FC76: 44603878 | FH76: 5704798 | FI76: 5704798 | FJ76: 39699 | FK76: 40915 | FN76: 362 | FO76: 517 | FP76: 35336 | FQ76: 35336 | FR76: 33855 | FS76: 29683 | FZ76: 997553 | GA76: 87024 | GB76: 52877913 | GC76: 51908783 | GD76: 78739262 | GE76: 79735762
A77: 20006 | B77: 0 | C77: 200523324 | D77: "O'ZINTERIMPEKS" AJ | E77: 26 | F77: 2 | G77: 0 | H77: 1 | I77: 2018 | J77: 4 | K77: N | L77: 1 | M77: 30 | N77: 0 | O77: 43508.892 | P77: 1965287 | Q77: 3120776 | R77: 1965287 | S77: 2020654 | T77: 0 | U77: 1100122 | V77: 39050 | W77: 39050 | X77: 39050 | Y77: 39050 | Z77: 0 | AA77: 0 | AB77: 50291187 | AC77: 54030485 | AD77: 21882468 | AE77: 22498860 | AF77: 8539436 | AG77: 11420914 | AH77: 1337196 | AI77: 1337196 | AJ77: 982902 | AK77: 982902 | AL77: 17549185 | AM77: 17790613 | AR77: 13009140 | AS77: 5780047 | AV77: 63300327 | AW77: 60910654 | AX77: 975475 | AY77: 998238 | AZ77: 45450 | BA77: 68213 | BF77: 930025 | BG77: 930025 | BL77: 52824958 | BM77: 10898354 | BP77: 11556 | BX77: 52312 | BY77: 16530 | BZ77: 350029 | CA77: 255742 | CB77: 58046 | CC77: 21141 | CH77: 52353015 | CI77: 10604941 | CJ77: 4072216 | CK77: 870336 | CN77: 2542 | CO77: 364600 | CP77: 4069668 | CQ77: 505730 | CR77: 6 | CS77: 6 | CT77: 6359852 | CU77: 5061680 | CX77: 64232501 | CY77: 17828608 | CZ77: 127532828 | DA77: 78739262 | DB77: 12904341 | DC77: 12904341 | DF77: 2386872 | DG77: 2393855 | DJ77: 9395351 | DK77: 8364735 | DL77: 621630 | DM77: 621630 | DO77: 1576788 | DP77: 25308194 | DQ77: 25861349 | DR77: 7200000 | DS77: 0 | EL77: 7200000 | EP77: 95024634 | EQ77: 52877913 | ER77: 9000050 | ES77: 8277748 | EV77: 1649126 | EW77: 1466145 | FB77: 86024584 | FC77: 44600165 | FH77: 5644692 | FI77: 5704798 | FJ77: 139087 | FK77: 39699 | FN77: 372 | FO77: 362 | FP77: 284454 | FQ77: 35336 | FR77: 36274 | FS77: 33855 | FZ77: 1246045 | GA77: 997553 | GB77: 102224634 | GC77: 52877913 | GD77: 127532828 | GE77: 78739262
A78: 20006 | B78: 0 | C78: 200547509 | D78: "POD'EMNIK" AJ | E78: 26 | F78: 8 | G78: 0 | H78: 1 | I78: 2021 | J78: 4 | K78: N | L78: 1 | M78: 30 | N78: 0 | O78: 44607.667 | P78: 1424383.8 | Q78: 696922.34 | R78: 1278348 | S78: 660280.16 | T78: 146035.84 | U78: 36642.18 | V78: 563.93 | W78: 563.93 | X78: 343.06 | Y78: 399.45 | Z78: 220.87 | AA78: 164.48 | AB78: 1820505.6 | AC78: 1820505.6 | AD78: 1225.26 | AE78: 1225.26 | AF78: 29482 | AG78: 29482 | AL78: 1789798.4 | AM78: 1789798.4 | AV78: 1966762.3 | AW78: 1857312.3 | AX78: 634535.23 | AY78: 158862.31 | AZ78: 530179.4 | BA78: 92399.48 | BD78: 104355.83 | BE78: 66462.83 | BL78: 359921.31 | BM78: 565384.22 | BP78: 3447.35 | BQ78: 14289.89 | BV78: 4508.23 | BW78: 50316.56 | BX78: 44473.66 | CB78: 69.54 | CC78: 5364.99 | CF78: 20369.64 | CH78: 287052.89 | CI78: 495412.78 | CJ78: 5702.6 | CK78: 1161.81 | CN78: 4836.68 | CO78: 269.34 | CP78: 865.92 | CQ78: 892.47 | CX78: 1000159.1 | CY78: 725408.34 | CZ78: 2966921.5 | DA78: 2582720.6 | DB78: 600372.72 | DC78: 600372.72 | DD78: 233683.01 | DE78: 233683.01 | DF78: 637139.73 | DG78: 572362.34 | DJ78: 676313.75 | DK78: 174534.2 | DP78: 2147509.2 | DQ78: 1580952.3 | EP78: 819412.25 | EQ78: 1001768.3 | ER78: 534367.74 | ES78: 716723.83 | EV78: 4800 | EW78: 28358.38 | FI78: 502080 | FJ78: 182707.7 | FK78: 141774.13 | FN78: 53882.22 | FO78: 2607.68 | FR78: 243079.18 | FS78: 24656.4 | FV78: 285044.51 | FW78: 285044.51 | FZ78: 49898.64 | GA78: 17247.24 | GB78: 819412.25 | GC78: 1001768.3 | GD78: 2966921.5 | GE78: 2582720.6
A79: 20006 | B79: 0 | C79: 200547509 | D79: "POD'EMNIK" AJ | E79: 26 | F79: 8 | G79: 0 | H79: 1 | I79: 2020 | J79: 4 | K79: N | L79: 1 | M79: 30 | N79: 0 | O79: 44241.852 | P79: 4907855 | Q79: 1424383.8 | R79: 3348420.9 | S79: 1278348 | T79: 1559434.1 | U79: 146035.84 | V79: 563.93 | W79: 563.93 | X79: 286.67 | Y79: 343.06 | Z79: 277.26 | AA79: 220.87 | AB79: 2293495.2 | AC79: 1820505.6 | AD79: 1225.26 | AE79: 1225.26 | AF79: 29482 | AG79: 29482 | AL79: 2262787.9 | AM79: 1789798.4 | AV79: 3853206.5 | AW79: 1966762.3 | AX79: 1276329.8 | AY79: 634535.23 | AZ79: 609738.38 | BA79: 530179.4 | BB79: 591389.04 | BD79: 75202.39 | BE79: 104355.83 | BL79: 443063.72 | BM79: 488674.31 | BP79: 252.53 | BQ79: 3447.35 | BV79: 1218.3 | BW79: 4508.23 | BX79: 44473.66 | BY79: 44473.66 | CB79: 30153.17 | CC79: 69.54 | CF79: 33905.38 | CG79: 20369.64 | CH79: 333060.68 | CI79: 415805.89 | CJ79: 92203.55 | CK79: 5702.6 | CN79: 91417.02 | CO79: 4836.68 | CP79: 786.53 | CQ79: 865.92 | CX79: 1811597.1 | CY79: 1128912.1 | CZ79: 5664803.6 | DA79: 3095674.5 | DB79: 600372.72 | DC79: 600372.72 | DD79: 233683.01 | DE79: 233683.01 | DF79: 2478202.1 | DG79: 637139.73 | DJ79: 1233826.2 | DK79: 676344.35 | DP79: 4546084.1 | DQ79: 2147539.8 | EP79: 1118758.5 | EQ79: 948134.64 | ER79: 1118758.5 | ES79: 663090.13 | EV79: 58700 | EW79: 4800 | FH79: 122277.32 | FJ79: 556981.88 | FK79: 182707.7 | FN79: 53882.22 | FO79: 32504.92 | FR79: 134698.21 | FS79: 243079.18 | FW79: 285044.51 | FZ79: 192218.91 | GA79: 199998.33 | GB79: 1118758.5 | GC79: 948134.64 | GD79: 5664842.6 | GE79: 3095674.5
A80: 20006 | B80: 0 | C80: 200547509 | D80: "POD'EMNIK" AJ | E80: 26 | F80: 8 | G80: 0 | H80: 1 | I80: 2019 | J80: 4 | K80: N | L80: 2 | M80: 30 | N80: 0 | O80: 44145.625 | P80: 6975013.8 | Q80: 4907855 | R80: 4129032.1 | S80: 3348420.9 | T80: 2845981.8 | U80: 1559434.1 | V80: 563.93 | W80: 563.93 | X80: 230.27 | Y80: 286.67 | Z80: 333.66 | AA80: 277.26 | AB80: 869717.27 | AC80: 2293495.2 | AD80: 1225.26 | AE80: 1225.26 | AF80: 29482 | AG80: 29482 | AL80: 839010.01 | AM80: 2262787.9 | AP80: 299851.76 | AV80: 4015884.5 | AW80: 3853206.5 | AX80: 2612862.4 | AY80: 1276329.8 | AZ80: 717222.23 | BA80: 609738.38 | BB80: 1057348.5 | BC80: 591389.04 | BD80: 838291.65 | BE80: 75202.39 | BL80: 556196.55 | BM80: 443063.72 | BP80: 174031.51 | BQ80: 252.53 | BV80: 6837.33 | BW80: 1218.3 | BX80: 170694.59 | BY80: 44473.66 | CB80: 13357.51 | CC80: 30153.17 | CF80: 17852.05 | CG80: 33905.38 | CH80: 173423.56 | CI80: 333060.68 | CJ80: 5109.08 | CK80: 92203.55 | CN80: 4432.44 | CO80: 91417.02 | CP80: 676.64 | CQ80: 786.53 | CX80: 3174168 | CY80: 1811597.1 | CZ80: 7190052.5 | DA80: 5664803.6 | DB80: 600372.72 | DC80: 600372.72 | DD80: 233683.01 | DE80: 233683.01 | DF80: 4354046.6 | DG80: 2478202.1 | DJ80: -1312450.7 | DK80: 1233787.3 | DP80: 3875651.7 | DQ80: 4546045.1 | EP80: 3314700.8 | EQ80: 1118758.5 | ER80: 2609700.8 | ES80: 1118758.5 | EV80: 90970.69 | EW80: 58700 | FH80: 1115600 | FI80: 122277.32 | FJ80: 201512.21 | FK80: 556981.88 | FN80: 60594.91 | FO80: 53882.22 | FR80: 763601.19 | FS80: 134698.21 | FV80: 705000 | FZ80: 377421.77 | GA80: 192218.89 | GB80: 3314700.8 | GC80: 1118758.5 | GD80: 7190352.5 | GE80: 5664803.6
A81: 20006 | B81: 0 | C81: 200547509 | D81: "POD'EMNIK" AJ | E81: 26 | F81: 8 | G81: 0 | H81: 1 | I81: 2018 | J81: 4 | K81: N | L81: 1 | M81: 30 | N81: 0 | O81: 43509.779 | P81: 6977452.9 | Q81: 6975013.8 | R81: 3407369.9 | S81: 4129032.1 | T81: 3570082.9 | U81: 2845981.8 | V81: 563.93 | W81: 563.93 | X81: 173.88 | Y81: 230.27 | Z81: 390.05 | AA81: 333.66 | AB81: 869717.27 | AC81: 869717.27 | AD81: 1225.26 | AE81: 1225.26 | AF81: 29482 | AG81: 29482 | AL81: 839010.01 | AM81: 839010.01 | AQ81: 299851.76 | AV81: 4440190.2 | AW81: 4015884.5 | AX81: 2736088.6 | AY81: 2614391.8 | AZ81: 794340.87 | BA81: 717828.08 | BB81: 1265432.2 | BC81: 1058272 | BD81: 676315.54 | BE81: 838291.65 | BH81: 2069.49 | BL81: 298427.65 | BM81: 597778.25 | BP81: 121172.79 | BQ81: 174031.51 | BV81: 6449.87 | BW81: 7101.86 | BX81: 64031.33 | BY81: 201759.48 | BZ81: 9927.1 | CB81: 9927.1 | CC81: 13357.51 | CF81: 2463.32 | CG81: 18607.52 | CH81: 84456.14 | CI81: 182920.37 | CJ81: 67567.17 | CK81: 5121.7 | CL81: 21.09 | CN81: 62002.91 | CO81: 4432.44 | CR81: 5543.17 | CS81: 689.26 | CX81: 3104153 | CY81: 3217291.7 | CZ81: 7544343.2 | DA81: 7233176.2 | DB81: 600372.72 | DC81: 600372.72 | DD81: 233683.01 | DE81: 233683.01 | DJ81: 4354285.1 | DK81: 4354046.6 | DL81: -878752.77 | DM81: -1320456.9 | DP81: 4309588 | DQ81: 3867645.5 | EP81: 3234755.1 | EQ81: 3365530.7 | ER81: 2669755.1 | ES81: 2627860 | EV81: 736294.05 | EW81: 99837.29 | FH81: 1445850.5 | FI81: 1115300 | FJ81: 166649.3 | FK81: 201525.13 | FN81: 29274.13 | FO81: 61101.15 | FP81: 0.54 | FR81: 240797.13 | FS81: 763398.43 | FV81: 565000 | FW81: 737670.75 | FZ81: 50889.48 | GA81: 386697.96 | GB81: 3234755.1 | GC81: 3365530.7 | GD81: 7544343.2 | GE81: 7233176.2
A82: 20006 | B82: 0 | C82: 200547548 | D82: "TOSHKENT YOG`-MOY KOMBINATI" AJ | E82: 26 | F82: 8 | G82: 2 | H82: 8 | I82: 2021 | J82: 4 | K82: N | L82: 2 | M82: 30 | N82: 0 | O82: 44810.702 | P82: 76939676 | Q82: 73962550 | R82: 49748046 | S82: 49767908 | T82: 27191630 | U82: 24194642 | AB82: 421666 | AC82: 421666 | AD82: 421666 | AE82: 421666 | AN82: 667059 | AO82: 667059 | AV82: 28280355 | AW82: 25283367 | AX82: 10411023 | AY82: 10941521 | AZ82: 5378759 | BA82: 5383776 | BB82: 4079948 | BC82: 5455115 | BD82: 952316 | BE82: 102630 | BH82: 220743 | BI82: 217409 | BL82: 11138612 | BM82: 9433635 | BN82: 584280 | BO82: 584280 | BP82: 2855108 | BQ82: 2931892 | BX82: 1669487 | BY82: 1519757 | BZ82: 1579148 | CA82: 52215 | CB82: 16433 | CC82: 2598 | CF82: 86148 | CG82: 97009 | CH82: 4932288 | CI82: 4830164 | CK82: 95167 | CO82: 94931 | CS82: 236 | CT82: 800000 | CU82: 800000 | CV82: 52985 | CW82: 54540 | CX82: 22623363 | CY82: 21542272 | CZ82: 50903718 | DA82: 46825639 | DB82: 13874967 | DC82: 13874967 | DD82: 6495071 | DE82: 6495071 | DF82: 18370343 | DG82: 18357331 | DJ82: -18416532 | DK82: -12884140 | DP82: 20323849 | DQ82: 25843229 | EP82: 30579869 | EQ82: 20982410 | ER82: 8430186 | ES82: 14367318 | ET82: 8430186 | EV82: 2012203 | EW82: 2044694 | EZ82: 138308 | FA82: 140670 | FH82: 78645 | FI82: 114194 | FJ82: 178411 | FK82: 4225536 | FL82: 302939 | FM82: 397765 | FP82: 282927 | FQ82: 282927 | FR82: 939355 | FS82: 4831925 | FT82: 15534591 | FV82: 6615092 | FW82: 6615092 | FZ82: 4497398 | GA82: 2329607 | GB82: 30579869 | GC82: 20982410 | GD82: 50903718 | GE82: 46825639
A83: 20006 | B83: 0 | C83: 200547548 | D83: "TOSHKENT YOG`-MOY KOMBINATI" AJ | E83: 26 | F83: 8 | G83: 2 | H83: 8 | I83: 2020 | J83: 4 | K83: N | L83: 1 | M83: 30 | N83: 0 | O83: 44238.7 | P83: 70895093 | Q83: 76939676 | R83: 43903029 | S83: 49748046 | T83: 26992064 | U83: 27191630 | AB83: 2653081 | AC83: 421666 | AL83: 2653081 | AM83: 421666 | AN83: 638558 | AO83: 667059 | AV83: 30283703 | AW83: 28280355 | AX83: 38965211 | AY83: 10411023 | AZ83: 13202487 | BA83: 5378759 | BB83: 1233118 | BC83: 4079948 | BD83: 24529606 | BE83: 952316 | BH83: 229493 | BI83: 220743 | BL83: 18131449 | BM83: 11138612 | BN83: 584280 | BO83: 584280 | BP83: 3374892 | BQ83: 2855108 | BX83: 3293396 | BY83: 1669487 | BZ83: 4499306 | CA83: 1579148 | CB83: 42474 | CC83: 16433 | CD83: 0 | CE83: 0 | CF83: 115996 | CG83: 86148 | CH83: 6805385 | CI83: 4932288 | CJ83: 25277 | CN83: 25277 | CT83: 1686420 | CU83: 800000 | CV83: 52985 | CW83: 52985 | CX83: 59090835 | CY83: 22623363 | CZ83: 89374538 | DA83: 50903718 | DB83: 13874967 | DC83: 13874967 | DD83: 6495071 | DE83: 6495071 | DF83: 16031898 | DG83: 18370343 | DJ83: 1681264 | DK83: -18416532 | DP83: 38083200 | DQ83: 20323849 | DR83: 58235 | DT83: 58235 | EN83: 58235 | EP83: 51233103 | EQ83: 30579869 | ER83: 14332385 | ES83: 8430186 | EV83: 10116012 | EW83: 2012203 | EZ83: 55369 | FA83: 138308 | FH83: 286199 | FI83: 78645 | FJ83: 130294 | FK83: 178411 | FL83: 510002 | FM83: 302939 | FO83: 0 | FP83: 1253648 | FQ83: 282927 | FR83: 1252049 | FS83: 939355 | FT83: 36900718 | FU83: 15534591 | FW83: 6615092 | FZ83: 728812 | GA83: 4497398 | GB83: 51291338 | GC83: 30579869 | GD83: 89374538 | GE83: 50903718
A84: 20006 | B84: 0 | C84: 200547548 | D84: "TOSHKENT YOG`-MOY KOMBINATI" AJ | E84: 26 | F84: 8 | G84: 2 | H84: 8 | I84: 2019 | J84: 4 | K84: N | L84: 2 | M84: 30 | N84: 0 | O84: 44084.611 | P84: 64899876 | Q84: 70895093 | R84: 40337438 | S84: 43903029 | T84: 24562438 | U84: 26992064 | AB84: 4796080 | AC84: 2653081 | AL84: 4796080 | AM84: 2653081 | AN84: 299642 | AO84: 638558 | AV84: 29658160 | AW84: 30283703 | AX84: 16056620 | AY84: 38965211 | AZ84: 8638156 | BA84: 13202487 | BC84: 1233118 | BD84: 7418464 | BE84: 24529606 | BH84: 275209 | BI84: 229493 | BL84: 11428839 | BM84: 18131449 | BN84: 584280 | BO84: 584280 | BP84: 2470183 | BQ84: 3374892 | BX84: 2609481 | BY84: 3293396 | BZ84: 2231244 | CA84: 4499306 | CB84: 15670 | CC84: 42474 | CF84: 181148 | CG84: 115996 | CH84: 3921113 | CI84: 6805385 | CJ84: 9296358 | CK84: 25277 | CN84: 128431 | CO84: 25277 | CQ84: 0 | CR84: 9167927 | CT84: 800000 | CU84: 1686420 | CV84: 52985 | CW84: 52985 | CX84: 37910011 | CY84: 59090835 | CZ84: 67568171 | DA84: 89374538 | DB84: 11202934 | DC84: 13874967 | DE84: 6495071 | DF84: 14775995 | DG84: 16031898 | DJ84: 7095192 | DK84: 1681264 | DP84: 33074121 | DQ84: 38083200 | DR84: 1646083 | DS84: 58235 | DT84: 426739 | DU84: 58235 | EJ84: 1219344 | EK84: 0 | EN84: 426739 | EO84: 58235 | EP84: 32847967 | EQ84: 51233103 | ER84: 19957057 | ES84: 14332385 | ET84: 645984 | EU84: 0 | EV84: 4962836 | EW84: 10116012 | FA84: 55369 | FH84: 277698 | FI84: 286199 | FJ84: 1428984 | FK84: 130294 | FL84: 1346869 | FM84: 510002 | FP84: 9942450 | FQ84: 1253648 | FR84: 1376424 | FS84: 1252049 | FT84: 12890910 | FU84: 36900718 | FZ84: 621796 | GA84: 728812 | GB84: 34494050 | GC84: 51291338 | GD84: 67568171 | GE84: 89374538
A85: 20006 | B85: 0 | C85: 200547548 | D85: "TOSHKENT YOG`-MOY KOMBINATI" AJ | E85: 26 | F85: 8 | G85: 2 | H85: 8 | I85: 2018 | J85: 4 | K85: N | L85: 2 | M85: 30 | N85: 0 | O85: 43661.393 | P85: 41699734 | Q85: 64899876 | R85: 29438260 | S85: 40337438 | T85: 12261474 | U85: 24562438 | AB85: 3775580 | AC85: 4796080 | AL85: 3775580 | AM85: 4796080 | AN85: 198257 | AO85: 299642 | AP85: 7481572 | AQ85: 0 | AV85: 23716883 | AW85: 29658160 | AX85: 16739618 | AY85: 16056620 | AZ85: 7064760 | BA85: 8638156 | BD85: 9674858 | BE85: 7418464 | BH85: 45521 | BI85: 275209 | BL85: 6691341 | BM85: 11428839 | BN85: 813268 | BO85: 584280 | BP85: 1330565 | BQ85: 2470183 | BX85: 3563105 | BY85: 2609481 | BZ85: 270545 | CA85: 2231244 | CB85: 15192 | CC85: 15670 | CF85: 282944 | CG85: 181148 | CH85: 1228990 | CI85: 3921113 | CJ85: 11135958 | CK85: 9296358 | CN85: 1060504 | CO85: 128431 | CR85: 10075454 | CS85: 9167927 | CT85: 800000 | CU85: 800000 | CV85: 52985 | CW85: 52985 | CX85: 35465423 | CY85: 37910011 | CZ85: 59182306 | DA85: 67568171 | DB85: 11202934 | DC85: 11202934 | DF85: 10104841 | DG85: 14775995 | DJ85: 6485941 | DK85: 7095192 | DP85: 27793716 | DQ85: 33074121 | DR85: 3084646 | DS85: 1646083 | DT85: 707253 | DU85: 426739 | EJ85: 2377393 | EK85: 1219344 | EN85: 707253 | EO85: 426739 | EP85: 28303944 | EQ85: 32847967 | ER85: 18503944 | ES85: 19957057 | ET85: 948611 | EU85: 645984 | EV85: 2415843 | EW85: 4962836 | EZ85: 151925 | FH85: 190648 | FI85: 277698 | FJ85: 3294405 | FK85: 1428984 | FL85: 503153 | FM85: 1346869 | FN85: 497358 | FP85: 9661378 | FQ85: 9942450 | FR85: 1065307 | FS85: 1376424 | FT85: 9800000 | FU85: 12890910 | FZ85: 723927 | GA85: 621796 | GB85: 31388590 | GC85: 34494050 | GD85: 59182306 | GE85: 67568171
A86: 20006 | B86: 0 | C86: 200587450 | D86: "TO`YTEPA METALL QURILMALARI " AJ | E86: 27 | F86: 23 | G86: 0 | H86: 1 | I86: 2021 | J86: 4 | K86: N | L86: 2 | M86: 30 | N86: 0 | O86: 44620.448 | P86: 3258166 | Q86: 8039379 | R86: 2730293 | S86: 3060294 | T86: 527873 | U86: 4979085 | AB86: 8258551 | AC86: 8258551 | AD86: 9130 | AE86: 9130 | AL86: 8249421 | AM86: 8249421 | AV86: 8786424 | AW86: 13237636 | AX86: 0 | AY86: 3848005 | AZ86: 0 | BA86: 3848005 | BL86: 532536 | BM86: 3713831 | BP86: 425889 | BQ86: 2150009 | BT86: 34530 | BU86: 34530 | BX86: 28497 | BY86: 750000 | BZ86: 32931 | CA86: 715485 | CB86: 27 | CC86: 0 | CH86: 10662 | CI86: 63807 | CJ86: 8141 | CK86: 913806 | CN86: 7991 | CO86: 913656 | CR86: 150 | CS86: 150 | CX86: 540677 | CY86: 8475642 | CZ86: 9327101 | DA86: 21713278 | DB86: 1217227 | DC86: 1211114 | DF86: 3917079 | DG86: 3917079 | DH86: 6113 | DI86: 6113 | DJ86: 2755594 | DK86: 2810307 | DM86: 11769600 | DP86: 7883787 | DQ86: 19701987 | EP86: 1443314 | EQ86: 2011291 | ER86: 1443314 | ES86: 2011291 | EV86: 65484 | EW86: 1795230 | EZ86: 5741 | FA86: 5741 | FH86: 1075000 | FI86: 0 | FJ86: 134557 | FK86: 12863 | FN86: 7972 | FO86: 11945 | FP86: 72376 | FQ86: 0 | FR86: 81911 | FS86: 132899 | FV86: 0 | FZ86: 273 | GA86: 52613 | GB86: 1443314 | GC86: 2011291 | GD86: 9327101 | GE86: 21713278
A87: 20006 | B87: 0 | C87: 200587450 | D87: "TO`YTEPA METALL QURILMALARI " AJ | E87: 27 | F87: 23 | G87: 0 | H87: 1 | I87: 2020 | J87: 4 | K87: N | L87: 1 | M87: 30 | N87: 0 | O87: 44226.617 | P87: 4576400 | Q87: 3258166 | R87: 3303834 | S87: 2730293 | T87: 1272566 | U87: 527873 | AB87: 8258551 | AC87: 8258551 | AD87: 9130 | AE87: 9130 | AL87: 8249421 | AM87: 8249421 | AV87: 9531117 | AW87: 8786424 | AX87: 1406791 | AY87: 0 | AZ87: 1406791 | BL87: 1068358 | BM87: 532536 | BP87: 869755 | BQ87: 425889 | BT87: 34530 | BU87: 34530 | BX87: 4000 | BY87: 28497 | BZ87: 148944 | CA87: 32931 | CB87: 467 | CC87: 27 | CH87: 10662 | CI87: 10662 | CJ87: 4187 | CK87: 8141 | CN87: 4037 | CO87: 7991 | CR87: 150 | CS87: 150 | CX87: 2479336 | CY87: 540677 | CZ87: 12010453 | DA87: 9327101 | DB87: 1217227 | DC87: 1217227 | DF87: 4195034 | DG87: 3917079 | DH87: 6113 | DI87: 6113 | DJ87: 3071354 | DK87: 2880746 | DP87: 8477502 | DQ87: 8008939 | EP87: 3532951 | EQ87: 1318162 | ER87: 2037951 | ES87: 1318162 | EV87: 96989 | EW87: 65484 | EZ87: 5741 | FA87: 5741 | FH87: 924001 | FI87: 1075000 | FJ87: 593836 | FK87: 9405 | FN87: 6601 | FO87: 7972 | FP87: 379052 | FQ87: 72376 | FR87: 31731 | FS87: 81911 | FV87: 1495000 | GA87: 273 | GB87: 3532951 | GC87: 1318162 | GD87: 12010453 | GE87: 9327101
A88: 20006 | B88: 0 | C88: 200587450 | D88: "TO`YTEPA METALL QURILMALARI " AJ | E88: 27 | F88: 23 | G88: 0 | H88: 1 | I88: 2019 | J88: 4 | K88: N | L88: 2 | M88: 30 | N88: 0 | O88: 44222.518 | P88: 15688439 | Q88: 4576400 | R88: 10558236 | S88: 3303834 | T88: 5130203 | U88: 1272566 | AB88: 9130 | AC88: 8258551 | AD88: 9130 | AE88: 9130 | AM88: 8249421 | AP88: 12400 | AV88: 5151733 | AW88: 9531117 | AX88: 7104767 | AY88: 1406791 | AZ88: 1670715 | BA88: 1406791 | BB88: 459968 | BD88: 4974084 | BH88: 1890 | BL88: 1068749 | BM88: 1068358 | BP88: 372794 | BQ88: 869755 | BT88: 34530 | BU88: 34530 | BX88: 113509 | BY88: 4000 | BZ88: 4332 | CA88: 148944 | CB88: 805 | CC88: 467 | CF88: 303794 | CH88: 238985 | CI88: 10662 | CJ88: 44556 | CK88: 4187 | CN88: 42447 | CO88: 4037 | CR88: 2109 | CS88: 150 | CT88: 204653 | CX88: 8424615 | CY88: 2479336 | CZ88: 13576348 | DA88: 12010453 | DB88: 1217227 | DC88: 1217227 | DF88: 3536157 | DG88: 4195034 | DH88: -6113 | DI88: 6113 | DJ88: 1245220 | DK88: 3071354 | DP88: 6004717 | DQ88: 8477502 | EP88: 7571631 | EQ88: 3532951 | ER88: 7383248 | ES88: 2037951 | EV88: 118428 | EW88: 96989 | EZ88: 5741 | FA88: 5741 | FH88: 6556153 | FI88: 924001 | FJ88: 68260 | FK88: 593836 | FN88: 140641 | FO88: 6601 | FP88: 31598 | FQ88: 379052 | FR88: 425221 | FS88: 31731 | FV88: 188383 | FW88: 1495000 | FZ88: 37206 | GB88: 7571631 | GC88: 3532951 | GD88: 13576348 | GE88: 12010453
A89: 20006 | B89: 0 | C89: 200587450 | D89: "TO`YTEPA METALL QURILMALARI " AJ | E89: 27 | F89: 23 | G89: 0 | H89: 1 | I89: 2018 | J89: 4 | K89: N | L89: 1 | M89: 30 | N89: 0 | O89: 43509.472 | P89: 15805653 | Q89: 15688439 | R89: 9844831 | S89: 10558236 | T89: 5960822 | U89: 5130203 | AB89: 9130 | AC89: 9130 | AD89: 9130 | AE89: 9130 | AQ89: 12400 | AV89: 5969952 | AW89: 5151733 | AX89: 9133630 | AY89: 7104767 | AZ89: 6716432 | BA89: 1670715 | BB89: 704710 | BC89: 459968 | BD89: 1712488 | BE89: 4974084 | BH89: 1586 | BI89: 1890 | BL89: 1364539 | BM89: 1068749 | BP89: 96478 | BQ89: 372794 | BT89: 14515 | BU89: 34530 | BX89: 630291 | BY89: 113509 | BZ89: 17 | CA89: 4332 | CB89: 652 | CC89: 805 | CF89: 305818 | CG89: 303794 | CH89: 316768 | CI89: 238985 | CJ89: 917282 | CK89: 44556 | CN89: 894941 | CO89: 42447 | CR89: 22341 | CS89: 2109 | CU89: 204653 | CX89: 11417037 | CY89: 8424615 | CZ89: 17386989 | DA89: 13576348 | DB89: 1217227 | DC89: 1217227 | DF89: 3573158 | DG89: 3536157 | DH89: 6113 | DI89: 6113 | DJ89: 26106 | DK89: 1245220 | DP89: 4810378 | DQ89: 5992491 | EP89: 12576611 | EQ89: 7583857 | ER89: 12328395 | ES89: 7395474 | EV89: 530854 | EW89: 118428 | EZ89: 10846 | FA89: 5741 | FH89: 11329277 | FI89: 6568379 | FJ89: 141757 | FK89: 68260 | FN89: 73135 | FO89: 140641 | FP89: 31598 | FQ89: 31598 | FR89: 195112 | FS89: 425221 | FV89: 248216 | FW89: 188383 | FZ89: 15816 | GA89: 37206 | GB89: 12576611 | GC89: 7583857 | GD89: 17386989 | GE89: 13576348
A90: 20006 | B90: 0 | C90: 200595877 | D90: "YEROSTIGAZ" AJ | E90: 27 | F90: 16 | G90: 0 | H90: 1 | I90: 2021 | J90: 4 | K90: N | L90: 2 | M90: 30 | N90: 0 | O90: 44619.886 | P90: 7161829 | Q90: 7163161 | R90: 3979643 | S90: 4386868 | T90: 3182186 | U90: 2776293 | V90: 1949 | W90: 1949 | X90: 891 | Y90: 1200 | Z90: 1058 | AA90: 749 | AB90: 20437 | AC90: 20437 | AD90: 205 | AE90: 205 | AH90: 20232 | AI90: 20232 | AV90: 3203681 | AW90: 2797479 | AX90: 1753197 | AY90: 1459124 | AZ90: 1753197 | BA90: 1459124 | BH90: 149357 | BI90: 143389 | BL90: 5941938 | BM90: 10302419 | BP90: 5789622 | BQ90: 7008656 | BX90: 58786 | BY90: 3189567 | BZ90: 15433 | CA90: 20609 | CB90: 434 | CC90: 1379 | CH90: 77663 | CI90: 82208 | CJ90: 1216812 | CK90: 5330 | CN90: 1214484 | CO90: 5318 | CR90: 2328 | CS90: 12 | CV90: 12330 | CW90: 12330 | CX90: 9073634 | CY90: 11922592 | CZ90: 12277315 | DA90: 14720071 | DB90: 677310 | DC90: 677310 | DD90: 601753 | DE90: 601753 | DF90: 5049241 | DG90: 5049241 | DJ90: 5150926 | DK90: 7081657 | DP90: 11479230 | DQ90: 13409961 | EP90: 798085 | EQ90: 1310110 | ER90: 798085 | ES90: 1281711 | EV90: 1407 | EW90: 209123 | FI90: 3863 | FJ90: 326445 | FK90: 353265 | FO90: 2 | FP90: 84563 | FQ90: 4640 | FR90: 369298 | FS90: 685363 | FW90: 28399 | FZ90: 16372 | GA90: 25455 | GB90: 798085 | GC90: 1310110 | GD90: 12277315 | GE90: 14720071
A91: 20006 | B91: 0 | C91: 200595877 | D91: "YEROSTIGAZ" AJ | E91: 27 | F91: 16 | G91: 0 | H91: 1 | I91: 2020 | J91: 4 | K91: N | L91: 1 | M91: 30 | N91: 0 | O91: 44242.694 | P91: 6994308.8 | Q91: 7161828.6 | R91: 3560122.5 | S91: 3979642.7 | T91: 3434186.4 | U91: 3182185.9 | V91: 1948.56 | W91: 1948.56 | X91: 581.85 | Y91: 890.53 | Z91: 1366.71 | AA91: 1058.03 | AB91: 205.33 | AC91: 20436.85 | AD91: 205.33 | AE91: 205.33 | AF91: 0 | AG91: 0 | AH91: 0 | AI91: 20231.52 | AJ91: 0 | AK91: 0 | AL91: 0 | AM91: 0 | AN91: 0 | AO91: 0 | AP91: 0 | AQ91: 0 | AR91: 0 | AS91: 0 | AT91: 0 | AU91: 0 | AV91: 3435758.4 | AW91: 3203680.8 | AX91: 1862462.7 | AY91: 1753196.7 | AZ91: 1862462.7 | BA91: 1753196.7 | BB91: 0 | BC91: 0 | BD91: 0 | BE91: 0 | BF91: 0 | BG91: 0 | BH91: 5002.61 | BI91: 149357.09 | BJ91: 0 | BK91: 0 | BL91: 1793026.9 | BM91: 5941937.6 | BN91: 0 | BO91: 0 | BP91: 689173.49 | BQ91: 5789621.6 | BR91: 0 | BS91: 0 | BT91: 0 | BU91: 0 | BV91: 0 | BW91: 0 | BX91: 997079.53 | BY91: 58785.69 | BZ91: 6000.23 | CA91: 15433.17 | CB91: 1933.9 | CC91: 434.1 | CD91: 0 | CE91: 0 | CF91: 0 | CG91: 0 | CH91: 98839.7 | CI91: 77663.03 | CJ91: 108439.44 | CK91: 1216812.5 | CL91: 0 | CM91: 0 | CN91: 107106.14 | CO91: 1214484.5 | CP91: 0 | CQ91: 0 | CR91: 1333.3 | CS91: 2328.02 | CT91: 0 | CU91: 0 | CV91: 12330.13 | CW91: 12330.13 | CX91: 3781261.8 | CY91: 9073634 | CZ91: 7217020.2 | DA91: 12277315 | DB91: 677310 | DC91: 677310 | DD91: 601753.05 | DE91: 601753.05 | DF91: 4842600.4 | DG91: 5049241.3 | DH91: 0 | DI91: 0 | DJ91: 398402.65 | DK91: 5150925.9 | DL91: 0 | DM91: 0 | DN91: 0 | DO91: 0 | DP91: 6520066.1 | DQ91: 11479230 | DR91: 0 | DS91: 0 | DT91: 0 | DU91: 0 | DV91: 0 | DW91: 0 | DX91: 0 | DY91: 0 | DZ91: 0 | EA91: 0 | EB91: 0 | EC91: 0 | ED91: 0 | EE91: 0 | EF91: 0 | EG91: 0 | EH91: 0 | EI91: 0 | EJ91: 0 | EK91: 0 | EL91: 0 | EM91: 0 | EN91: 0 | EO91: 0 | EP91: 696954.05 | EQ91: 798084.58 | ER91: 696954.05 | ES91: 798084.58 | ET91: 0 | EU91: 0 | EV91: 8673.84 | EW91: 1407.06 | EX91: 0 | EY91: 0 | EZ91: 0 | FA91: 0 | FB91: 0 | FC91: 0 | FD91: 0 | FE91: 0 | FF91: 0 | FG91: 0 | FH91: 0 | FI91: 0 | FJ91: 383718.41 | FK91: 326445.24 | FL91: 0 | FM91: 0 | FN91: 34198.19 | FO91: 0 | FP91: 0 | FQ91: 84563.23 | FR91: 244663.57 | FS91: 369296.67 | FT91: 0 | FU91: 0 | FV91: 0 | FW91: 0 | FX91: 0 | FY91: 0 | FZ91: 25700.04 | GA91: 16372.38 | GB91: 696954.05 | GC91: 798084.58 | GD91: 7217020.2 | GE91: 12277315
A92: 20006 | B92: 0 | C92: 200595877 | D92: "YEROSTIGAZ" AJ | E92: 27 | F92: 16 | G92: 0 | H92: 1 | I92: 2019 | J92: 4 | K92: N | L92: 1 | M92: 30 | N92: 0 | O92: 43876.893 | P92: 6566119 | Q92: 6565983.8 | R92: 3117837.5 | S92: 3368444.2 | T92: 3448281.4 | U92: 3197539.6 | V92: 1948.56 | W92: 1948.56 | X92: 273.16 | Y92: 581.85 | Z92: 1675.4 | AA92: 1366.71 | AB92: 205.33 | AC92: 205.33 | AD92: 205.33 | AE92: 205.33 | AF92: 0 | AG92: 0 | AH92: 0 | AI92: 0 | AJ92: 0 | AK92: 0 | AL92: 0 | AM92: 0 | AN92: 0 | AO92: 0 | AP92: 0 | AQ92: 0 | AR92: 0 | AS92: 0 | AT92: 0 | AU92: 0 | AV92: 3450162.1 | AW92: 3199111.6 | AX92: 2042345.2 | AY92: 1862462.7 | AZ92: 2042345.2 | BA92: 1862462.7 | BB92: 0 | BC92: 0 | BD92: 0 | BE92: 0 | BF92: 0 | BG92: 0 | BH92: 118759.5 | BI92: 5002.61 | BJ92: 0 | BK92: 0 | BL92: 608726.32 | BM92: 1793026.9 | BN92: 0 | BO92: 0 | BP92: 54164.39 | BQ92: 689173.49 | BR92: 0 | BS92: 0 | BT92: 0 | BU92: 0 | BV92: 0 | BW92: 0 | BX92: 499684.08 | BY92: 997079.53 | BZ92: 0 | CA92: 6000.23 | CB92: 0.47 | CC92: 1933.9 | CD92: 0 | CE92: 0 | CF92: 0 | CG92: 0 | CH92: 54877.38 | CI92: 98839.7 | CJ92: 1.32 | CK92: 108439.44 | CL92: 0 | CM92: 0 | CN92: 0 | CO92: 107106.14 | CP92: 0 | CQ92: 0 | CR92: 1.32 | CS92: 1333.3 | CT92: 0 | CU92: 0 | CV92: 12330.13 | CW92: 12330.13 | CX92: 2782162.5 | CY92: 3781261.8 | CZ92: 6232324.7 | DA92: 6980373.4 | DB92: 677310 | DC92: 677310 | DD92: 601753.05 | DE92: 601753.05 | DF92: 4574681.8 | DG92: 4605953.6 | DH92: 0 | DI92: 0 | DJ92: -3155119.3 | DK92: 398402.65 | DL92: 0 | DM92: 0 | DN92: 0 | DO92: 0 | DP92: 2698625.5 | DQ92: 6283419.3 | DR92: 0 | DS92: 0 | DT92: 0 | DU92: 0 | DV92: 0 | DW92: 0 | DX92: 0 | DY92: 0 | DZ92: 0 | EA92: 0 | EB92: 0 | EC92: 0 | ED92: 0 | EE92: 0 | EF92: 0 | EG92: 0 | EH92: 0 | EI92: 0 | EJ92: 0 | EK92: 0 | EL92: 0 | EM92: 0 | EN92: 0 | EO92: 0 | EP92: 3533699.1 | EQ92: 696954.05 | ER92: 3531971.1 | ES92: 696954.05 | ET92: 0 | EU92: 0 | EV92: 908460.4 | EW92: 8673.84 | EX92: 0 | EY92: 0 | EZ92: 0 | FA92: 0 | FB92: 0 | FC92: 0 | FD92: 0 | FE92: 0 | FF92: 0 | FG92: 0 | FH92: 1717.07 | FI92: 0 | FJ92: 1056823.3 | FK92: 383718.41 | FL92: 0 | FM92: 0 | FN92: 595957.14 | FO92: 34198.19 | FP92: 0 | FQ92: 0 | FR92: 913961.13 | FS92: 244663.57 | FT92: 0 | FU92: 0 | FV92: 1728 | FW92: 0 | FX92: 0 | FY92: 0 | FZ92: 55052.09 | GA92: 25700.04 | GB92: 3533699.1 | GC92: 696954.05 | GD92: 6232324.7 | GE92: 6980373.4
A93: 20006 | B93: 0 | C93: 200595877 | D93: "YEROSTIGAZ" AJ | E93: 27 | F93: 16 | G93: 0 | H93: 1 | I93: 2018 | J93: 4 | K93: N | L93: 1 | M93: 30 | N93: 0 | O93: 43507.829 | P93: 6291881 | Q93: 6291764 | R93: 2759272 | S93: 3006686 | T93: 3532609 | U93: 3285078 | V93: 1375 | W93: 1949 | X93: 242 | Y93: 273 | Z93: 1133 | AA93: 1676 | AB93: 205 | AC93: 205 | AD93: 205 | AE93: 205 | AF93: 0 | AG93: 0 | AH93: 0 | AI93: 0 | AJ93: 0 | AK93: 0 | AL93: 0 | AM93: 0 | AN93: 0 | AO93: 0 | AP93: 0 | AQ93: 0 | AR93: 0 | AS93: 0 | AT93: 0 | AU93: 0 | AV93: 3533947 | AW93: 3286959 | AX93: 2092362 | AY93: 2042345 | AZ93: 2092362 | BA93: 2042345 | BB93: 0 | BC93: 0 | BD93: 0 | BE93: 0 | BF93: 0 | BG93: 0 | BH93: 54369 | BI93: 118760 | BJ93: 0 | BK93: 0 | BL93: 39785 | BM93: 608726 | BN93: 0 | BO93: 0 | BP93: 4865 | BQ93: 54164 | BR93: 0 | BS93: 0 | BT93: 0 | BU93: 0 | BV93: 20 | BW93: 0 | BX93: 17355 | BY93: 499684 | BZ93: 13222 | CA93: 0 | CB93: 442 | CC93: 1 | CD93: 0 | CE93: 0 | CF93: 0 | CG93: 0 | CH93: 3881 | CI93: 54877 | CJ93: 4067 | CK93: 1 | CL93: 0 | CM93: 0 | CN93: 0 | CO93: 0 | CP93: 0 | CQ93: 0 | CR93: 4067 | CS93: 1 | CT93: 0 | CU93: 0 | CV93: 12330 | CW93: 12330 | CX93: 2202913 | CY93: 2782162 | CZ93: 5736860 | DA93: 6069121 | DB93: 677310 | DC93: 677310 | DD93: 601753 | DE93: 601753 | DF93: 4381316 | DG93: 4411478 | DH93: 0 | DI93: 0 | DJ93: -3356669 | DK93: -3155119 | DL93: 0 | DM93: 0 | DN93: 0 | DO93: 0 | DP93: 2303710 | DQ93: 2535422 | DR93: 0 | DS93: 0 | DT93: 0 | DU93: 0 | DV93: 0 | DW93: 0 | DX93: 0 | DY93: 0 | DZ93: 0 | EA93: 0 | EB93: 0 | EC93: 0 | ED93: 0 | EE93: 0 | EF93: 0 | EG93: 0 | EH93: 0 | EI93: 0 | EJ93: 0 | EK93: 0 | EL93: 0 | EM93: 0 | EN93: 0 | EO93: 0 | EP93: 3433150 | EQ93: 3533699 | ER93: 3431422 | ES93: 3531971 | ET93: 0 | EU93: 0 | EV93: 1881561 | EW93: 908461 | EX93: 0 | EY93: 0 | EZ93: 0 | FA93: 0 | FB93: 0 | FC93: 0 | FD93: 0 | FE93: 0 | FF93: 0 | FG93: 0 | FH93: 932773 | FI93: 1717 | FJ93: 180195 | FK93: 1056823 | FL93: 0 | FM93: 0 | FN93: 156022 | FO93: 595957 | FP93: 0 | FQ93: 0 | FR93: 267262 | FS93: 913961 | FT93: 0 | FU93: 0 | FV93: 1728 | FW93: 1728 | FX93: 0 | FY93: 0 | FZ93: 13609 | GA93: 55052 | GB93: 3433150 | GC93: 3533699 | GD93: 5736860 | GE93: 6069121
A94: 20006 | B94: 0 | C94: 200607109 | D94: "1-TEMIR BETON MAHSULOTLARI ZAVODI" AJ | E94: 27 | F94: 6 | G94: 0 | H94: 1 | I94: 2021 | J94: 4 | K94: N | L94: 1 | M94: 30 | N94: 0 | O94: 44607.758 | P94: 5151976 | Q94: 5146852.6 | R94: 4646746 | S94: 4783810.1 | T94: 505230 | U94: 363042.5 | AB94: 5052 | AC94: 5051.7 | AD94: 5052 | AE94: 5051.7 | AT94: 169904 | AU94: 157903.7 | AV94: 680186 | AW94: 525997.9 | AX94: 2513448 | AY94: 2659169.7 | AZ94: 754829 | BA94: 764123.5 | BD94: 1758619 | BE94: 1895046.2 | BH94: 9007 | BI94: 8919.2 | BL94: 268553 | BM94: 174320.7 | BP94: 157761 | BQ94: 81628 | BW94: 1150 | BX94: 12239 | BY94: 53383.9 | BZ94: 60206 | CA94: 26590.4 | CB94: 27591 | CC94: 6810.5 | CF94: 7295 | CH94: 3461 | CI94: 4757.9 | CJ94: 5213 | CK94: 5397.7 | CN94: 4072 | CO94: 2550.8 | CP94: 916 | CQ94: 948 | CR94: 225 | CS94: 1898.9 | CX94: 2796221 | CY94: 2847807.3 | CZ94: 3476407 | DA94: 3373805.2 | DB94: 1280769 | DC94: 1280769 | DD94: 19503 | DE94: 19502.6 | DF94: 932831 | DG94: 932764.6 | DJ94: 385287 | DK94: -112814.1 | DP94: 2618390 | DQ94: 2120222.1 | EP94: 858017 | EQ94: 1253583.1 | ER94: 858017 | ES94: 986583.1 | EV94: 289146 | EW94: 294020.1 | FH94: 220550 | FI94: 451364.7 | FJ94: 83021 | FK94: 51638.4 | FN94: 4140 | FO94: 4207.4 | FP94: 52605 | FQ94: 24295.2 | FR94: 206310 | FS94: 157810.9 | FW94: 267000 | FZ94: 2245 | GA94: 3246.4 | GB94: 858017 | GC94: 1253583.1 | GD94: 3476407 | GE94: 3373805.2
A95: 20006 | B95: 0 | C95: 200607109 | D95: "1-TEMIR BETON MAHSULOTLARI ZAVODI" AJ | E95: 27 | F95: 6 | G95: 0 | H95: 1 | I95: 2020 | J95: 4 | K95: N | L95: 1 | M95: 30 | N95: 0 | O95: 44239.647 | P95: 5080203 | Q95: 5151976 | R95: 4493206 | S95: 4646746 | T95: 586997 | U95: 505230 | AB95: 5052 | AC95: 5052 | AD95: 5052 | AE95: 5052 | AP95: 30608 | AU95: 169904 | AV95: 622657 | AW95: 680186 | AX95: 3055134 | AY95: 2513448 | AZ95: 1037906 | BA95: 754829 | BD95: 2017228 | BE95: 1758619 | BH95: 4168 | BI95: 9007 | BL95: 348498 | BM95: 268553 | BP95: 77408 | BQ95: 157761 | BX95: 159619 | BY95: 12239 | BZ95: 73901 | CA95: 60206 | CB95: 218 | CC95: 27591 | CF95: 3174 | CG95: 7295 | CH95: 34178 | CI95: 3461 | CJ95: 678446 | CK95: 5213 | CN95: 391541 | CO95: 4072 | CP95: 286058 | CQ95: 916 | CR95: 847 | CS95: 225 | CX95: 4086246 | CY95: 2796221 | CZ95: 4708903 | DA95: 3476407 | DB95: 1280769 | DC95: 1280769 | DD95: 19503 | DE95: 19503 | DF95: 894929 | DG95: 932831 | DJ95: 882490 | DK95: 385287 | DP95: 3077691 | DQ95: 2618390 | EP95: 1631212 | EQ95: 858017 | ER95: 1631212 | ES95: 858017 | EV95: 38359 | EW95: 289146 | FH95: 491392 | FI95: 220550 | FJ95: 129966 | FK95: 83021 | FN95: 105803 | FO95: 4140 | FP95: 33050 | FQ95: 52605 | FR95: 823841 | FS95: 206310 | FZ95: 8801 | GA95: 2245 | GB95: 1631212 | GC95: 858017 | GD95: 4708903 | GE95: 3476407
A96: 20006 | B96: 0 | C96: 200607109 | D96: "1-TEMIR BETON MAHSULOTLARI ZAVODI" AJ | E96: 27 | F96: 6 | G96: 0 | H96: 1 | I96: 2019 | J96: 4 | K96: N | L96: 1 | M96: 30 | N96: 0 | O96: 43866.421 | P96: 4340442 | Q96: 4667639 | R96: 3926349 | S96: 4125381 | T96: 414093 | U96: 542258 | AB96: 5052 | AC96: 5052 | AD96: 5052 | AE96: 5052 | AQ96: 30608 | AV96: 419145 | AW96: 577918 | AX96: 2654661 | AY96: 3055134 | AZ96: 780715 | BA96: 1037906 | BD96: 1873946 | BE96: 2017228 | BH96: 1628 | BI96: 4168 | BL96: 907397 | BM96: 348498 | BP96: 198134 | BQ96: 77408 | BX96: 695944 | BY96: 159619 | BZ96: 203 | CA96: 73901 | CC96: 218 | CG96: 3174 | CH96: 13116 | CI96: 34178 | CJ96: 135424 | CK96: 678446 | CN96: 132123 | CO96: 391541 | CP96: 1530 | CQ96: 286058 | CR96: 1771 | CS96: 847 | CX96: 3699110 | CY96: 4086246 | CZ96: 4118255 | DA96: 4664164 | DB96: 1280769 | DC96: 1280769 | DD96: 19503 | DE96: 19503 | DF96: 826365 | DG96: 850190 | DJ96: 478434 | DK96: 882490 | DP96: 2605071 | DQ96: 3032952 | EP96: 1513184 | EQ96: 1631212 | ER96: 1513184 | ES96: 1631212 | EV96: 46343 | EW96: 38359 | FH96: 746226 | FI96: 491392 | FJ96: 170741 | FK96: 129966 | FN96: 125527 | FO96: 105803 | FP96: 26772 | FQ96: 33050 | FR96: 393287 | FS96: 823841 | FZ96: 4288 | GA96: 8801 | GB96: 1513184 | GC96: 1631212 | GD96: 4118255 | GE96: 4664164
A97: 20006 | B97: 0 | C97: 200607109 | D97: "1-TEMIR BETON MAHSULOTLARI ZAVODI" AJ | E97: 27 | F97: 6 | G97: 0 | H97: 1 | I97: 2018 | J97: 4 | K97: N | L97: 1 | M97: 30 | N97: 0 | O97: 43508.473 | P97: 4175146 | Q97: 4163402 | R97: 3492637 | S97: 3772824 | T97: 682509 | U97: 390578 | AB97: 5052 | AC97: 5052 | AD97: 5052 | AE97: 5052 | AV97: 687561 | AW97: 395630 | AX97: 1821729 | AY97: 2654661 | AZ97: 637774 | BA97: 780715 | BD97: 1183955 | BE97: 1873946 | BH97: 7868 | BI97: 1628 | BJ97: 131807 | BL97: 1028236 | BM97: 907397 | BP97: 654069 | BQ97: 198134 | BX97: 356700 | BY97: 695944 | BZ97: 371 | CA97: 203 | CB97: 5518 | CF97: 2719 | CH97: 8859 | CI97: 13116 | CJ97: 6069 | CK97: 135424 | CN97: 2443 | CO97: 132123 | CP97: 1490 | CQ97: 1530 | CR97: 2136 | CS97: 1771 | CX97: 2995709 | CY97: 3699110 | CZ97: 3683270 | DA97: 4094740 | DB97: 1280769 | DC97: 1280769 | DD97: 19503 | DE97: 19503 | DF97: 804483 | DG97: 802850 | DJ97: 1783 | DK97: 478434 | DP97: 2106538 | DQ97: 2581556 | EP97: 1576732 | EQ97: 1513184 | ER97: 1576732 | ES97: 1513184 | EV97: 244902 | EW97: 46343 | FH97: 661671 | FI97: 746226 | FJ97: 164386 | FK97: 170741 | FN97: 15406 | FO97: 125527 | FP97: 191055 | FQ97: 26772 | FR97: 298287 | FS97: 393287 | FZ97: 1025 | GA97: 4288 | GB97: 1576732 | GC97: 1513184 | GD97: 3683270 | GE97: 4094740
A98: 20006 | B98: 0 | C98: 200663071 | D98: "SUVMASH" AJ | E98: 26 | F98: 11 | G98: 0 | H98: 1 | I98: 2021 | J98: 4 | K98: N | L98: 1 | M98: 30 | N98: 0 | O98: 44606.577 | P98: 18139681 | Q98: 18371924 | R98: 13156994 | S98: 14166883 | T98: 4982687 | U98: 4205041 | V98: 30893 | W98: 30893 | X98: 1389 | Y98: 1389 | Z98: 29504 | AA98: 29504 | AB98: 14488 | AC98: 14338 | AD98: 14338 | AE98: 14338 | AL98: 150 | AM98: 0 | AP98: 20955 | AQ98: 96415 | AV98: 5047634 | AW98: 4345298 | AX98: 17414116 | AY98: 21446621 | AZ98: 9463635 | BA98: 9819867 | BD98: 7950481 | BE98: 11626754 | BH98: 34247 | BI98: 33992 | BL98: 7576180 | BM98: 5995765 | BP98: 5432508 | BQ98: 3388967 | BV98: 257 | BW98: 802 | BX98: 797052 | BY98: 53984 | BZ98: 422703 | CA98: 684740 | CH98: 923660 | CI98: 1867272 | CJ98: 1436055 | CK98: 1268217 | CN98: 1340655 | CO98: 1227142 | CP98: 95400 | CQ98: 41075 | CX98: 26460598 | CY98: 28744595 | CZ98: 31508232 | DA98: 33089893 | DB98: 1132920 | DC98: 1132920 | DF98: 2029380 | DG98: 2029380 | DJ98: 24216111 | DK98: 25714574 | DL98: 1370814 | DM98: 1370814 | DP98: 28749225 | DQ98: 30247688 | EP98: 2759007 | EQ98: 2842205 | ER98: 2759007 | ES98: 2842205 | EV98: 1505111 | EW98: 1874682 | FH98: 668945 | FI98: 919936 | FJ98: 33980 | FN98: 89219 | FO98: 146 | FP98: 5503 | FQ98: 5024 | FZ98: 456249 | GA98: 42417 | GB98: 2759007 | GC98: 2842205 | GD98: 31508232 | GE98: 33089893
A99: 20006 | B99: 0 | C99: 200663071 | D99: "SUVMASH" AJ | E99: 26 | F99: 11 | G99: 0 | H99: 1 | I99: 2020 | J99: 4 | K99: N | L99: 1 | M99: 30 | N99: 0 | O99: 44239.734 | P99: 17682493 | Q99: 18139681 | R99: 12740317 | S99: 13156994 | T99: 4942176 | U99: 4982687 | V99: 1389 | W99: 30893 | X99: 1389 | Y99: 1389 | Z99: 0 | AA99: 29504 | AB99: 14488 | AC99: 14488 | AD99: 14338 | AE99: 14338 | AL99: 150 | AM99: 150 | AQ99: 20955 | AV99: 4956664 | AW99: 5047634 | AX99: 12864880 | AY99: 17414116 | AZ99: 8286954 | BA99: 9463635 | BD99: 4577926 | BE99: 7950481 | BH99: 31425 | BI99: 34247 | BL99: 10173396 | BM99: 7576180 | BP99: 7415924 | BQ99: 5432508 | BV99: 188 | BW99: 257 | BX99: 357812 | BY99: 797052 | BZ99: 1709776 | CA99: 422703 | CH99: 689696 | CI99: 923660 | CJ99: 1740349 | CK99: 1436055 | CN99: 1719833 | CO99: 1340655 | CP99: 20516 | CQ99: 95400 | CX99: 24810050 | CY99: 26460598 | CZ99: 29766714 | DA99: 31508232 | DB99: 1132920 | DC99: 1132920 | DF99: 2089918 | DG99: 2029380 | DJ99: 20156569 | DK99: 24216111 | DL99: 1370814 | DM99: 1370814 | DP99: 24750221 | DQ99: 28749225 | EP99: 5016493 | EQ99: 2759007 | ER99: 5016493 | ES99: 2759007 | EV99: 3975140 | EW99: 1505111 | FH99: 329634 | FI99: 668945 | FJ99: 80165 | FK99: 33980 | FN99: 69492 | FO99: 89219 | FP99: 5164 | FQ99: 5503 | FR99: 189350 | FZ99: 367548 | GA99: 456249 | GB99: 5016493 | GC99: 2759007 | GD99: 29766714 | GE99: 31508232
A100: 20006 | B100: 0 | C100: 200663071 | D100: "SUVMASH" AJ | E100: 26 | F100: 11 | G100: 0 | H100: 1 | I100: 2019 | J100: 4 | K100: N | L100: 1 | M100: 30 | N100: 0 | O100: 43873.706 | P100: 15264011 | Q100: 16739895 | R100: 11603380 | S100: 12087498 | T100: 3660631 | U100: 4652397 | V100: 1389 | W100: 1389 | X100: 1389 | Y100: 1389 | Z100: 0 | AA100: 0 | AB100: 14488 | AC100: 14488 | AD100: 14338 | AE100: 14338 | AL100: 150 | AM100: 150 | AV100: 3675119 | AW100: 4666885 | AX100: 11278158 | AY100: 12864880 | AZ100: 6442306 | BA100: 8286954 | BB100: 77849 | BC100: 0 | BD100: 4692116 | BE100: 4577926 | BF100: 65887 | BH100: 28686 | BI100: 31425 | BL100: 11268562 | BM100: 10173396 | BP100: 2929151 | BQ100: 7415924 | BV100: 315 | BW100: 188 | BX100: 4863524 | BY100: 357812 | BZ100: 404382 | CA100: 1709776 | CH100: 3071190 | CI100: 689696 | CJ100: 1745517 | CK100: 1740349 | CN100: 1506848 | CO100: 1719833 | CP100: 189371 | CQ100: 20516 | CR100: 49298 | CX100: 24320923 | CY100: 24810050 | CZ100: 27996042 | DA100: 29476935 | DB100: 1132920 | DC100: 1132920 | DF100: 1810187 | DG100: 1800139 | DJ100: 19051065 | DK100: 20156569 | DL100: 1370814 | DM100: 1370814 | DP100: 23364986 | DQ100: 24460442 | EP100: 4631056 | EQ100: 5016493 | ER100: 4631056 | ES100: 5016493 | EV100: 2781292 | EW100: 3975140 | FH100: 234982 | FI100: 329634 | FJ100: 354674 | FK100: 80165 | FN100: 245463 | FO100: 69492 | FP100: 4248 | FQ100: 5164 | FR100: 140855 | FS100: 189350 | FZ100: 869542 | GA100: 367548 | GB100: 4631056 | GC100: 5016493 | GD100: 27996042 | GE100: 29476935
...

Sheet Profit and loss
A1: PACKAGE | B1: TAXCODE | C1: TIN | D1: NAME | E1: NS10_CODE | F1: NS11_CODE | G1: NS13_CODE | H1: NA1_CODE | I1: YEAR | J1: PERIOD | K1: PTYPE | L1: TYPE | M1: STATE | O1: MAX(T.DATESENT) | P1: SUM010 | Q1: SUM020 | R1: SUM030 | S1: SUM030Z | T1: SUM040 | U1: SUM050 | V1: SUM060 | W1: SUM070 | X1: SUM080 | Y1: SUM090 | Z1: SUM100 | AA1: SUM100Z | AB1: SUM110 | AC1: SUM120 | AD1: SUM130 | AE1: SUM140 | AF1: SUM150 | AG1: SUM160 | AH1: SUM170 | AI1: SUM180 | AJ1: SUM190 | AK1: SUM200 | AL1: SUM210 | AM1: SUM220 | AN1: SUM220Z | AO1: SUM230 | AP1: SUM230 | AQ1: SUM240 | AR1: SUM240Z | AS1: SUM250 | AT1: SUM260 | AU1: SUM270 | AV1: SUM270Z
A2: 20025 | B2: 0 | C2: 200240131 | D2: "ANDIJONYOG'MOY" AJ | E2: 3 | F2: 1 | G2: 0 | H2: 1 | I2: 2021 | J2: 4 | K2: N | L2: 2 | M2: 30 | N2: 0 | O2: 44660.811 | P2: 101080227 | Q2: 75297418 | R2: 25782809 | S2: 0 | T2: 5219808 | U2: 295680 | V2: 1805401 | W2: 3118727 | Y2: 35610 | Z2: 20598611 | AA2: 0 | AB2: 247477 | AF2: 247477 | AH2: 20783912 | AI2: 2126491 | AK2: 18657421 | AM2: 62176 | AN2: 0 | AQ2: 62176 | AR2: 0 | AS2: 56615 | AU2: 5561 | AV2: 0
A3: 20025 | B3: 0 | C3: 200240131 | D3: "ANDIJONYOG'MOY" AJ | E3: 3 | F3: 1 | G3: 0 | H3: 1 | I3: 2020 | J3: 4 | K3: N | L3: 1 | M3: 30 | N3: 0 | O3: 44240.648 | P3: 76293638 | Q3: 72244429 | R3: 4049209 | S3: 0 | T3: 8693549 | U3: 708304 | V3: 2009000 | W3: 5976245 | Y3: 311350 | Z3: 0 | AA3: 4332990 | AB3: 296990 | AC3: 96282 | AD3: 570 | AF3: 142300 | AG3: 57838 | AH3: 8417753 | AI3: 3798598 | AK3: 4619155 | AM3: 0 | AN3: 12453753 | AQ3: 0 | AR3: 12453753 | AU3: -12453753 | AV3: 12453753
A4: 20025 | B4: 0 | C4: 200240131 | D4: "ANDIJONYOG'MOY" AJ | E4: 3 | F4: 1 | G4: 0 | H4: 1 | I4: 2019 | J4: 4 | K4: N | L4: 1 | M4: 30 | N4: 0 | O4: 43875.635 | P4: 93799529 | Q4: 75800349 | R4: 17999180 | S4: 0 | T4: 10882200 | U4: 955488 | V4: 2867001 | W4: 7059711 | Y4: 272504 | Z4: 7389484 | AA4: 0 | AB4: 392717 | AD4: 84133 | AF4: 141023 | AG4: 167561 | AH4: 4585699 | AI4: 3376109 | AJ4: 0 | AK4: 1209590 | AM4: 3196502 | AN4: 0 | AQ4: 3196502 | AR4: 0 | AS4: 854141 | AU4: 2342361 | AV4: 0
A5: 20025 | B5: 0 | C5: 200240131 | D5: "ANDIJONYOG'MOY" AJ | E5: 3 | F5: 1 | G5: 0 | H5: 1 | I5: 2018 | J5: 4 | K5: N | L5: 1 | M5: 30 | N5: 0 | O5: 43508.603 | P5: 66647988 | Q5: 46636809 | R5: 20011179 | S5: 0 | T5: 15802849 | U5: 1076413 | V5: 2477643 | W5: 12248793 | Y5: 66481 | Z5: 4274811 | AA5: 0 | AB5: 403019 | AC5: 76816 | AD5: 30130 | AF5: 75090 | AG5: 220983 | AH5: 1663297 | AI5: 1663297 | AM5: 3014533 | AN5: 0 | AQ5: 3014533 | AR5: 0 | AS5: 951071 | AU5: 2063462 | AV5: 0
A6: 20025 | B6: 0 | C6: 200244553 | D6: "ASAKA YOG'" AJ | E6: 3 | F6: 15 | G6: 0 | H6: 1 | I6: 2021 | J6: 4 | K6: N | L6: 1 | M6: 30 | N6: 0 | O6: 44606.9 | P6: 90405974 | Q6: 83754323 | R6: 6651651 | S6: 0 | T6: 5642973 | U6: 1041388 | V6: 1126192 | W6: 3475393 | Y6: 339565 | Z6: 1348243 | AA6: 0 | AB6: 857 | AF6: 857 | AH6: 4178771 | AI6: 4027618 | AK6: 151153 | AM6: 0 | AN6: 2829671 | AQ6: 0 | AR6: 2829671 | AU6: -2829671 | AV6: 2829671
A7: 20025 | B7: 0 | C7: 200244553 | D7: "ASAKA YOG'" AJ | E7: 3 | F7: 15 | G7: 0 | H7: 1 | I7: 2020 | J7: 4 | K7: N | L7: 2 | M7: 30 | N7: 0 | O7: 44378.716 | P7: 77239658 | Q7: 71659999 | R7: 5579659 | S7: 0 | T7: 6129208 | U7: 805103 | V7: 1231877 | W7: 4092228 | Y7: 529254 | Z7: 0 | AA7: 20295 | AB7: 328897 | AC7: 232300 | AD7: 227 | AF7: 96370 | AH7: 4063813 | AI7: 3833249 | AK7: 230564 | AM7: 0 | AN7: 3755211 | AQ7: 0 | AR7: 3755211 | AU7: -3755211 | AV7: 3755211
A8: 20025 | B8: 0 | C8: 200244553 | D8: "ASAKA YOG'" AJ | E8: 3 | F8: 15 | G8: 0 | H8: 1 | I8: 2019 | J8: 4 | K8: N | L8: 2 | M8: 30 | N8: 0 | O8: 43885.464 | P8: 103017104 | Q8: 87247086 | R8: 15770018 | S8: 0 | T8: 11319467 | U8: 1318861 | V8: 2149890 | W8: 7850716 | Y8: 1587803 | Z8: 6038354 | AA8: 0 | AB8: 170476 | AD8: 87587 | AF8: 82889 | AH8: 3329474 | AI8: 3013105 | AK8: 316369 | AM8: 2879356 | AN8: 0 | AQ8: 2879356 | AR8: 0 | AS8: 551210 | AU8: 2328146 | AV8: 0
A9: 20025 | B9: 0 | C9: 200244553 | D9: "ASAKA YOG'" AJ | E9: 3 | F9: 15 | G9: 0 | H9: 1 | I9: 2018 | J9: 4 | K9: N | L9: 1 | M9: 30 | N9: 0 | O9: 43507.654 | P9: 63034963 | Q9: 44074251 | R9: 18960712 | S9: 0 | T9: 14757134 | U9: 895395 | V9: 2182399 | W9: 11679340 | Y9: 385711 | Z9: 4589289 | AA9: 0 | AB9: 72523 | AF9: 72523 | AH9: 1405585 | AI9: 712256 | AK9: 693329 | AM9: 3256227 | AN9: 0 | AQ9: 3256227 | AR9: 0 | AS9: 823989 | AU9: 2432238 | AV9: 0
A10: 20025 | B10: 0 | C10: 200323067 | D10: "GULISTON EKSTRAKT-YOG'" AJ | E10: 24 | F10: 10 | G10: 2 | H10: 1 | I10: 2021 | J10: 4 | K10: N | L10: 1 | M10: 30 | N10: 0 | O10: 44621.65 | P10: 33745425 | Q10: 32141407 | R10: 1604017.9 | S10: 0 | T10: 3491507.8 | U10: 361174.5 | V10: 1057227.8 | W10: 2073105.5 | Y10: 661899.1 | Z10: 0 | AA10: 1225590.8 | AH10: 5846944.7 | AI10: 5846944.7 | AM10: 0 | AN10: 7072535.5 | AQ10: 0 | AR10: 7072535.5 | AU10: -7072535.5 | AV10: 7072535.5
A11: 20025 | B11: 0 | C11: 200323067 | D11: "GULISTON EKSTRAKT-YOG'" AJ | E11: 24 | F11: 10 | G11: 2 | H11: 1 | I11: 2020 | J11: 4 | K11: N | L11: 2 | M11: 30 | N11: 0 | O11: 44595.654 | P11: 44607013 | Q11: 46877465 | R11: 0 | S11: 2270451.6 | T11: 5186927.8 | U11: 557570.25 | V11: 1304641.8 | W11: 3324715.8 | Z11: 0 | AA11: 7457379.4 | AB11: 137311.65 | AF11: 137311.65 | AH11: 9845259.9 | AI11: 6693266.3 | AK11: 3151993.7 | AM11: 0 | AN11: 17165328 | AQ11: 0 | AR11: 17165328 | AU11: -17165328 | AV11: 17165328
A12: 20025 | B12: 0 | C12: 200323067 | D12: "GULISTON EKSTRAKT-YOG'" AJ | E12: 24 | F12: 10 | G12: 2 | H12: 1 | I12: 2019 | J12: 4 | K12: N | L12: 1 | M12: 30 | N12: 0 | O12: 44594.936 | P12: 79332626 | Q12: 66950507 | R12: 12382119 | S12: 0 | T12: 9065972 | U12: 1643798.2 | V12: 1691684.9 | W12: 5730488.9 | Y12: 543632.89 | Z12: 3859779.4 | AA12: 0 | AB12: 166758.79 | AF12: 166758.79 | AH12: 2999686.2 | AI12: 2553790 | AK12: 445896.17 | AM12: 1026852 | AN12: 0 | AQ12: 1026852 | AR12: 0 | AS12: 507917.49 | AU12: 518934.53 | AV12: 0
A13: 20025 | B13: 0 | C13: 200323067 | D13: "GULISTON EKSTRAKT-YOG'" AJ | E13: 24 | F13: 10 | G13: 2 | H13: 1 | I13: 2018 | J13: 4 | K13: N | L13: 2 | M13: 30 | N13: 0 | O13: 43620.446 | P13: 97033863 | Q13: 62460696 | R13: 34573167 | S13: 0 | T13: 17086356 | U13: 1845059 | V13: 3231691 | W13: 12009606 | Y13: 4003513 | Z13: 21490324 | AA13: 0 | AB13: 166410 | AF13: 166410 | AH13: 2213662 | AI13: 992462 | AK13: 1221200 | AM13: 19443072 | AN13: 0 | AQ13: 19443072 | AR13: 0 | AS13: 3048057 | AU13: 16395015 | AV13: 0
A14: 20025 | B14: 0 | C14: 200466854 | D14: "YANGIYO'L YOG'-MOY" AJ | E14: 27 | F14: 22 | G14: 0 | H14: 8 | I14: 2021 | J14: 4 | K14: N | L14: 1 | M14: 30 | N14: 0 | O14: 44624.645 | P14: 52984737 | Q14: 44885047 | R14: 8099689.3 | S14: 0 | T14: 14216258 | U14: 632145.61 | V14: 1540493.8 | W14: 12043619 | Y14: 207612.23 | Z14: 0 | AA14: 5908956.4 | AB14: 892245.84 | AD14: 435482.4 | AF14: 456763.44 | AH14: 1229110.1 | AI14: 936844.26 | AK14: 292265.88 | AM14: 0 | AN14: 6245820.7 | AO14: 632213.4 | AQ14: 0 | AR14: 5613607.3 | AS14: 72724.36 | AU14: -5686331.7 | AV14: 5686331.7
A15: 20025 | B15: 0 | C15: 200466854 | D15: "YANGIYO'L YOG'-MOY" AJ | E15: 27 | F15: 22 | G15: 0 | H15: 8 | I15: 2020 | J15: 4 | K15: N | L15: 1 | M15: 30 | N15: 0 | O15: 44264.48 | P15: 74845843 | Q15: 66011936 | R15: 8833906.8 | S15: 0 | T15: 13246712 | U15: 914490.4 | V15: 1549350.7 | W15: 10782871 | Y15: 1014300 | Z15: 0 | AA15: 3398505 | AB15: 2078420.4 | AD15: 490712.16 | AF15: 1587708.2 | AH15: 2625300.6 | AI15: 2467219.5 | AK15: 158081.18 | AM15: 0 | AN15: 3945385.3 | AQ15: 0 | AR15: 3945385.3 | AS15: 0 | AU15: -3945385.3 | AV15: 3945385.3
A16: 20025 | B16: 0 | C16: 200466854 | D16: "YANGIYO'L YOG'-MOY" AJ | E16: 27 | F16: 22 | G16: 0 | H16: 8 | I16: 2019 | J16: 4 | K16: N | L16: 2 | M16: 30 | N16: 0 | O16: 43997.68 | P16: 97998105 | Q16: 77347963 | R16: 20650142 | S16: 0 | T16: 16871148 | U16: 1019684.5 | V16: 1751020.7 | W16: 14100443 | Y16: 758393.94 | Z16: 4537387.9 | AA16: 0 | AB16: 2738899.9 | AD16: 128878.32 | AF16: 2610021.6 | AH16: 1013142.3 | AI16: 647106.39 | AK16: 366035.94 | AL16: -0.01 | AM16: 6263145.5 | AN16: 0 | AO16: 3557747.1 | AQ16: 9820892.5 | AR16: 0 | AS16: 1392652.6 | AU16: 8428239.9 | AV16: 0
A17: 20025 | B17: 0 | C17: 200466854 | D17: "YANGIYO'L YOG'-MOY" AJ | E17: 27 | F17: 22 | G17: 0 | H17: 8 | I17: 2018 | J17: 4 | K17: N | L17: 1 | M17: 30 | N17: 0 | O17: 43544.577 | P17: 1.0098734e+08 | Q17: 68261108 | R17: 32726231 | S17: 0 | T17: 18726064 | U17: 1011860.7 | V17: 1488125.9 | W17: 16226078 | Y17: 2120524.8 | Z17: 16120692 | AA17: 0 | AB17: 1206206.8 | AF17: 1206206.8 | AH17: 1171350.5 | AI17: 354341.5 | AK17: 817009 | AM17: 16155548 | AN17: 0 | AQ17: 16155548 | AR17: 0 | AS17: 2529312.5 | AU17: 13626235 | AV17: 0
A18: 20025 | B18: 0 | C18: 200670095 | D18: "QARSHI YOG'-EKSTRAKSIYA" AJ | E18: 10 | F18: 1 | G18: 0 | H18: 1 | I18: 2021 | J18: 4 | K18: N | L18: 2 | M18: 30 | N18: 0 | O18: 44621.474 | P18: 35499083 | Q18: 40433151 | R18: 0 | S18: 4934068 | T18: 3297448 | U18: 525711 | V18: 842017 | W18: 1929720 | Y18: 1645784 | Z18: 0 | AA18: 6585732 | AH18: 3219476 | AI18: 3098555 | AL18: 120921 | AM18: 0 | AN18: 9805208 | AQ18: 0 | AR18: 9805208 | AU18: -9805208 | AV18: 9805208
A19: 20025 | B19: 0 | C19: 200670095 | D19: "QARSHI YOG'-EKSTRAKSIYA" AJ | E19: 10 | F19: 1 | G19: 0 | H19: 1 | I19: 2020 | J19: 4 | K19: N | L19: 2 | M19: 30 | N19: 0 | O19: 44257.582 | P19: 43652138 | Q19: 36591361 | R19: 7060777 | S19: 0 | T19: 5066561 | U19: 608108 | V19: 525999 | W19: 3932454 | Y19: 411765 | Z19: 2405981 | AA19: 0 | AB19: 449977 | AF19: 449977 | AH19: 2713414 | AI19: 1418471 | AK19: 1210768 | AL19: 84175 | AM19: 142544 | AN19: 0 | AQ19: 142544 | AR19: 0 | AS19: 94674 | AU19: 47870 | AV19: 0
A20: 20025 | B20: 0 | C20: 200670095 | D20: "QARSHI YOG'-EKSTRAKSIYA" AJ | E20: 10 | F20: 1 | G20: 0 | H20: 1 | I20: 2019 | J20: 4 | K20: N | L20: 2 | M20: 30 | N20: 0 | O20: 43882.717 | P20: 42997556 | Q20: 37310743 | R20: 5686813 | S20: 0 | T20: 6236683 | U20: 736754 | V20: 924979 | W20: 4574950 | Y20: 134350 | Z20: 0 | AA20: 415520 | AB20: 247622 | AC20: 1045 | AF20: 246577 | AH20: 9121558 | AI20: 7991987 | AK20: 153008 | AL20: 976563 | AM20: 0 | AN20: 9289456 | AQ20: 0 | AR20: 9289456 | AS20: 0 | AU20: -9289456 | AV20: 9289456
A21: 20025 | B21: 0 | C21: 200670095 | D21: "QARSHI YOG'-EKSTRAKSIYA" AJ | E21: 10 | F21: 1 | G21: 0 | H21: 1 | I21: 2018 | J21: 4 | K21: N | L21: 1 | M21: 30 | N21: 0 | O21: 43511.606 | P21: 68277406 | Q21: 51607017 | R21: 16670389 | S21: 0 | T21: 10124673 | U21: 957366 | V21: 975220 | W21: 8192087 | Y21: 291328 | Z21: 6837044 | AA21: 0 | AB21: 1357567 | AC21: 119977 | AF21: 1237590 | AH21: 5215432 | AI21: 2701544 | AK21: 2513888 | AM21: 2979179 | AN21: 0 | AQ21: 2979179 | AR21: 0 | AS21: 905210 | AT21: 0 | AU21: 2073969 | AV21: 0
A22: 20025 | B22: 0 | C22: 200930049 | D22: YOG`GAR AJ | E22: 35 | F22: 9 | G22: 0 | H22: 1 | I22: 2021 | J22: 4 | K22: N | L22: 2 | M22: 30 | N22: 0 | O22: 44612.999 | P22: 23992920 | Q22: 23804662 | R22: 188258 | S22: 0 | T22: 5483339 | U22: 165841 | V22: 1266143 | W22: 4051355 | Y22: 5639799 | Z22: 344718 | AA22: 0 | AB22: 3096 | AF22: 3096 | AH22: 269643 | AI22: 269617 | AK22: 26 | AM22: 78171 | AN22: 0 | AQ22: 78171 | AR22: 0 | AS22: 32823 | AU22: 45348 | AV22: 0
A23: 60132 | B23: 0 | C23: 200930049 | D23: YOG`GAR AJ | E23: 35 | F23: 9 | G23: 0 | H23: 1 | I23: 2020 | J23: 4 | K23: N | L23: 1 | M23: 30 | N23: 0 | O23: 44209.602 | P23: 53693302 | Q23: 45715709 | R23: 7977593 | S23: 0 | T23: 5318752 | U23: 557967 | V23: 1902791 | W23: 2857994 | Y23: 315800 | Z23: 2974641 | AA23: 0 | AH23: 665713 | AI23: 355897 | AK23: 309816 | AM23: 2308928 | AN23: 0 | AQ23: 2308928 | AR23: 0 | AS23: 346339 | AU23: 1962589 | AV23: 0
A24: 20025 | B24: 0 | C24: 200930049 | D24: YOG`GAR AJ | E24: 35 | F24: 9 | G24: 0 | H24: 1 | I24: 2019 | J24: 4 | K24: N | L24: 1 | M24: 30 | N24: 0 | O24: 43879.828 | P24: 60828502 | Q24: 50575089 | R24: 10253413 | S24: 0 | T24: 6498182 | U24: 462144 | V24: 2241914 | W24: 3794124 | Y24: 178422 | Z24: 3933653 | AA24: 0 | AB24: 121846 | AF24: 121846 | AH24: 685293 | AI24: 507175 | AK24: 178118 | AM24: 3370206 | AN24: 0 | AQ24: 3370206 | AR24: 0 | AS24: 471501 | AU24: 2898705 | AV24: 0
A25: 20025 | B25: 0 | C25: 200930049 | D25: YOG`GAR AJ | E25: 35 | F25: 9 | G25: 0 | H25: 1 | I25: 2018 | J25: 4 | K25: N | L25: 1 | M25: 30 | N25: 0 | O25: 43879.828 | P25: 60828502 | Q25: 50575089 | R25: 10253413 | S25: 0 | T25: 6498182 | U25: 462144 | V25: 2241914 | W25: 3794124 | Y25: 178422 | Z25: 3933653 | AA25: 0 | AB25: 121846 | AF25: 121846 | AH25: 685293 | AI25: 507175 | AK25: 178118 | AM25: 3370206 | AN25: 0 | AQ25: 3370206 | AR25: 0 | AS25: 471501 | AU25: 2898705 | AV25: 0
A26: 20025 | B26: 0 | C26: 200595877 | D26: "YEROSTIGAZ" AJ | E26: 27 | F26: 16 | G26: 0 | H26: 1 | I26: 2021 | J26: 4 | K26: N | L26: 2 | M26: 30 | N26: 0 | O26: 44619.89 | P26: 21449155 | Q26: 14529833 | R26: 6919322 | S26: 0 | T26: 4672023 | V26: 2209183 | W26: 2462840 | Y26: 298968 | Z26: 2546267 | AA26: 0 | AB26: 292 | AF26: 292 | AH26: 292 | AK26: 292 | AM26: 2546267 | AN26: 0 | AQ26: 2546267 | AR26: 0 | AS26: 615536 | AU26: 1930731 | AV26: 0
A27: 20025 | B27: 0 | C27: 200595877 | D27: "YEROSTIGAZ" AJ | E27: 27 | F27: 16 | G27: 0 | H27: 1 | I27: 2020 | J27: 4 | K27: N | L27: 1 | M27: 30 | N27: 0 | O27: 44242.591 | P27: 24902329 | Q27: 15060457 | R27: 9841871.9 | S27: 0 | T27: 3796116.1 | V27: 1972435.2 | W27: 1823680.9 | Y27: 31466.37 | Z27: 6077222.2 | AA27: 0 | AB27: 0.03 | AC27: 0 | AD27: 0 | AE27: 0 | AF27: 0.03 | AG27: 0 | AH27: 0.02 | AI27: 0 | AJ27: 0 | AK27: 0.02 | AL27: 0 | AM27: 6077222.2 | AN27: 0 | AQ27: 6077222.2 | AR27: 0 | AS27: 926296.26 | AT27: 0 | AU27: 5150925.9 | AV27: 0
A28: 20025 | B28: 0 | C28: 200595877 | D28: "YEROSTIGAZ" AJ | E28: 27 | F28: 16 | G28: 0 | H28: 1 | I28: 2019 | J28: 4 | K28: N | L28: 1 | M28: 30 | N28: 0 | O28: 43876.925 | P28: 18343213 | Q28: 11314444 | R28: 7028769 | S28: 0 | T28: 2982945.2 | U28: 0 | V28: 1230976.4 | W28: 1751968.8 | X28: 0 | Y28: 50667.19 | Z28: 4096491 | AA28: 0 | AB28: 17.86 | AC28: 15.6 | AD28: 0 | AE28: 0 | AF28: 2.26 | AG28: 0 | AH28: 0.01 | AI28: 0 | AJ28: 0 | AK28: 0.01 | AL28: 0 | AM28: 4096508.9 | AN28: 0 | AO28: 0 | AP28: 0 | AQ28: 4096508.9 | AR28: 0 | AS28: 542986.91 | AT28: 0 | AU28: 3553522 | AV28: 0
A29: 20025 | B29: 0 | C29: 200595877 | D29: "YEROSTIGAZ" AJ | E29: 27 | F29: 16 | G29: 0 | H29: 1 | I29: 2018 | J29: 4 | K29: N | L29: 1 | M29: 30 | N29: 0 | O29: 43507.675 | P29: 10951388 | Q29: 8209637 | R29: 2741751 | S29: 0 | T29: 2503369 | U29: 0 | V29: 915543 | W29: 1587826 | X29: 0 | Y29: 36588 | Z29: 274970 | AA29: 0 | AB29: 13 | AC29: 11 | AD29: 2 | AE29: 0 | AF29: 0 | AG29: 0 | AH29: 0 | AI29: 0 | AJ29: 0 | AK29: 0 | AL29: 0 | AM29: 274983 | AN29: 0 | AO29: 0 | AP29: 0 | AQ29: 274983 | AR29: 0 | AS29: 73433 | AT29: 0 | AU29: 201550 | AV29: 0
A30: 20025 | B30: 0 | C30: 200002854 | D30: "JANUBSANOATMONTAJ" AJ | E30: 12 | F30: 1 | G30: 0 | H30: 1 | I30: 2021 | J30: 4 | K30: N | L30: 2 | M30: 30 | N30: 0 | O30: 44691.537 | P30: 34264573 | Q30: 26010021 | R30: 8254552 | S30: 0 | T30: 6417400 | U30: 435825 | V30: 2841215 | W30: 3140360 | Y30: 353175 | Z30: 2190327 | AA30: 0 | AB30: 5927 | AF30: 0 | AG30: 5927 | AH30: 0 | AI30: 0 | AK30: 0 | AL30: 0 | AM30: 2196254 | AN30: 0 | AQ30: 2196254 | AR30: 0 | AS30: 504543 | AU30: 1691711 | AV30: 0
A31: 20025 | B31: 0 | C31: 200002854 | D31: "JANUBSANOATMONTAJ" AJ | E31: 12 | F31: 1 | G31: 0 | H31: 1 | I31: 2020 | J31: 4 | K31: N | L31: 2 | M31: 30 | N31: 0 | O31: 44303.411 | P31: 37609264 | Q31: 30775773 | R31: 6833491 | S31: 0 | T31: 7436637 | U31: 957719 | V31: 3652343 | W31: 2826575 | Y31: 2844687 | Z31: 2241541 | AA31: 0 | AB31: 45216 | AC31: 647 | AD31: 24113 | AF31: 15939 | AG31: 4517 | AH31: 2136 | AL31: 2136 | AM31: 2284621 | AN31: 0 | AQ31: 2284621 | AR31: 0 | AS31: 486680 | AU31: 1797941 | AV31: 0
A32: 20025 | B32: 0 | C32: 200002854 | D32: "JANUBSANOATMONTAJ" AJ | E32: 12 | F32: 1 | G32: 0 | H32: 1 | I32: 2019 | J32: 4 | K32: N | L32: 2 | M32: 30 | N32: 0 | O32: 44013.63 | P32: 47743058 | Q32: 35086439 | R32: 12656619 | S32: 0 | T32: 6835704 | U32: 387694 | V32: 3459898 | W32: 2988112 | Y32: 1333618 | Z32: 7154533 | AA32: 0 | AB32: 15411 | AC32: 280 | AD32: 11458 | AF32: 859 | AG32: 2814 | AH32: 0 | AM32: 7169944 | AN32: 0 | AQ32: 7169944 | AR32: 0 | AS32: 915513 | AU32: 6254431 | AV32: 0
A33: 20025 | B33: 0 | C33: 200002854 | D33: "JANUBSANOATMONTAJ" AJ | E33: 12 | F33: 1 | G33: 0 | H33: 1 | I33: 2018 | J33: 4 | K33: N | L33: 2 | M33: 30 | N33: 0 | O33: 43550.78 | P33: 77632363 | Q33: 74011850 | R33: 3620513 | S33: 0 | T33: 2911375 | U33: 157304 | V33: 1876806 | W33: 877265 | Y33: 2720282 | Z33: 3429420 | AA33: 0 | AB33: 3903 | AC33: 161 | AF33: 3537 | AG33: 205 | AH33: 3954 | AI33: 0 | AK33: 2661 | AL33: 1293 | AM33: 3429369 | AN33: 0 | AQ33: 3429369 | AR33: 0 | AS33: 56482 | AT33: 498846 | AU33: 2874041 | AV33: 0
A34: 20025 | B34: 0 | C34: 200049218 | D34: "O'ZELEKTROTERM" AJ | E34: 14 | F34: 1 | G34: 0 | H34: 1 | I34: 2021 | J34: 4 | K34: N | L34: 2 | M34: 30 | N34: 0 | O34: 44876.737 | P34: 1511638 | Q34: 178186 | R34: 1333452 | S34: 0 | T34: 1496113 | V34: 742966 | W34: 753147 | Y34: 13980 | Z34: 0 | AA34: 148681 | AB34: 120696 | AC34: 120696 | AM34: 0 | AN34: 27985 | AQ34: 0 | AR34: 27985 | AS34: 0 | AT34: 45926 | AU34: -73911 | AV34: 73911
A35: 20025 | B35: 0 | C35: 200049218 | D35: "O'ZELEKTROTERM" AJ | E35: 14 | F35: 1 | G35: 0 | H35: 1 | I35: 2020 | J35: 4 | K35: N | L35: 1 | M35: 30 | N35: 0 | O35: 44244.668 | P35: 1389691 | Q35: 478186 | R35: 911505 | S35: 0 | T35: 970564 | V35: 565954 | W35: 404610 | Y35: 2564 | Z35: 0 | AA35: 56495 | AB35: 120696 | AC35: 120696 | AM35: 64201 | AN35: 0 | AQ35: 64201 | AR35: 0 | AS35: 1869 | AT35: 45926 | AU35: 16406 | AV35: 0
A36: 20025 | B36: 0 | C36: 200049218 | D36: "O'ZELEKTROTERM" AJ | E36: 14 | F36: 1 | G36: 0 | H36: 1 | I36: 2019 | J36: 4 | K36: N | L36: 2 | M36: 30 | N36: 0 | O36: 44081.749 | P36: 969943 | Q36: 173918 | R36: 796025 | S36: 0 | T36: 964599 | V36: 504851 | W36: 459748 | Y36: 8 | Z36: 0 | AA36: 168566 | AB36: 2302 | AC36: 2302 | AM36: 0 | AN36: 166264 | AQ36: 0 | AR36: 166264 | AT36: 38798 | AU36: -205062 | AV36: 205062
A37: 20025 | B37: 0 | C37: 200049218 | D37: "O'ZELEKTROTERM" AJ | E37: 14 | F37: 1 | G37: 0 | H37: 1 | I37: 2018 | J37: 4 | K37: N | L37: 1 | M37: 30 | N37: 0 | O37: 43510.724 | P37: 734968 | Q37: 91381 | R37: 643587 | S37: 0 | T37: 586259 | V37: 384540 | W37: 201719 | Y37: 4532 | Z37: 61860 | AA37: 0 | AB37: 86640 | AC37: 86640 | AM37: 148500 | AN37: 0 | AQ37: 148500 | AR37: 0 | AT37: 36975 | AU37: 111525 | AV37: 0
A38: 20025 | B38: 0 | C38: 200049541 | D38: "NAMANGANMASH" AJ | E38: 14 | F38: 1 | G38: 0 | H38: 1 | I38: 2021 | J38: 4 | K38: N | L38: 1 | M38: 30 | N38: 0 | O38: 44607.858 | P38: 14097876 | Q38: 11694909 | R38: 2402967 | S38: 0 | T38: 1943755 | U38: 96054 | V38: 1178117 | W38: 669584 | Y38: 614616 | Z38: 1073828 | AA38: 0 | AB38: 5694 | AF38: 5694 | AH38: 4260 | AK38: 4260 | AM38: 1075262 | AN38: 0 | AQ38: 1075262 | AR38: 0 | AS38: 189353 | AU38: 885909 | AV38: 0
A39: 20025 | B39: 0 | C39: 200049541 | D39: "NAMANGANMASH" AJ | E39: 14 | F39: 1 | G39: 0 | H39: 1 | I39: 2020 | J39: 4 | K39: N | L39: 2 | M39: 30 | N39: 0 | O39: 44323.528 | P39: 14166948 | Q39: 10838421 | R39: 3328527 | S39: 0 | T39: 1943300 | U39: 58538 | V39: 1061533 | W39: 823229 | Y39: 333112 | Z39: 1718339 | AA39: 0 | AB39: 12426 | AC39: 174 | AF39: 12252 | AH39: 587 | AK39: 587 | AM39: 1730178 | AN39: 0 | AQ39: 1730178 | AR39: 0 | AS39: 324788 | AU39: 1405390 | AV39: 0
A40: 20025 | B40: 0 | C40: 200049541 | D40: "NAMANGANMASH" AJ | E40: 14 | F40: 1 | G40: 0 | H40: 1 | I40: 2019 | J40: 4 | K40: N | L40: 1 | M40: 30 | N40: 0 | O40: 43875.672 | P40: 8165257 | Q40: 6408279 | R40: 1756978 | S40: 0 | T40: 1689420 | U40: 49925 | V40: 990640 | W40: 648855 | Y40: 684899 | Z40: 752457 | AA40: 0 | AB40: 6518 | AC40: 75 | AF40: 4564 | AG40: 1879 | AH40: 364 | AK40: 364 | AM40: 758611 | AN40: 0 | AQ40: 758611 | AR40: 0 | AS40: 100710 | AU40: 657901 | AV40: 0
A41: 20025 | B41: 0 | C41: 200049541 | D41: "NAMANGANMASH" AJ | E41: 14 | F41: 1 | G41: 0 | H41: 1 | I41: 2018 | J41: 4 | K41: N | L41: 2 | M41: 30 | N41: 0 | O41: 43616.431 | P41: 9564426 | Q41: 7546666 | R41: 2017760 | S41: 0 | T41: 1534367 | U41: 41737 | V41: 778970 | W41: 713660 | Y41: 802450 | Z41: 1285843 | AA41: 0 | AB41: 5256 | AC41: 43 | AF41: 5213 | AH41: 25391 | AI41: 21517 | AK41: 3874 | AM41: 1265708 | AN41: 0 | AQ41: 1265708 | AR41: 0 | AS41: 188010 | AU41: 1077698 | AV41: 0
A42: 20025 | B42: 0 | C42: 200340624 | D42: "KARBONAT" AJ | E42: 8 | F42: 11 | G42: 0 | H42: 1 | I42: 2021 | J42: 4 | K42: N | L42: 1 | M42: 30 | N42: 0 | O42: 44607.779 | P42: 52475060 | Q42: 25932415 | R42: 26542645 | S42: 0 | T42: 22129298 | U42: 13022471 | V42: 4210760 | W42: 4896067 | Y42: 2741345 | Z42: 7154692 | AA42: 0 | AB42: 745722 | AC42: 4527 | AF42: 741195 | AH42: 2888609 | AI42: 2063838 | AK42: 824771 | AM42: 5011805 | AN42: 0 | AQ42: 5011805 | AR42: 0 | AS42: 219398 | AU42: 4792407 | AV42: 0
A43: 20025 | B43: 0 | C43: 200340624 | D43: "KARBONAT" AJ | E43: 8 | F43: 11 | G43: 0 | H43: 1 | I43: 2020 | J43: 4 | K43: N | L43: 1 | M43: 30 | N43: 0 | O43: 44242.725 | P43: 25367107 | Q43: 11595084 | R43: 13772023 | S43: 0 | T43: 9970089.3 | U43: 4836157.3 | V43: 1662312.3 | W43: 3471619.8 | Y43: 904128.46 | Z43: 4706062.5 | AA43: 0 | AB43: 299296.04 | AC43: 1133.82 | AF43: 298162.22 | AH43: 505195.6 | AI43: 175875.37 | AK43: 329320.23 | AM43: 4500162.9 | AN43: 0 | AQ43: 4500162.9 | AR43: 0 | AS43: 303916.29 | AU43: 4196246.6 | AV43: 0
A44: 20025 | B44: 0 | C44: 200340624 | D44: "KARBONAT" AJ | E44: 8 | F44: 11 | G44: 0 | H44: 1 | I44: 2019 | J44: 4 | K44: N | L44: 1 | M44: 30 | N44: 0 | O44: 43875.568 | P44: 6303595 | Q44: 3802173 | R44: 2501422 | S44: 0 | T44: 2705715 | V44: 382575 | W44: 2323140 | Y44: 377168 | Z44: 172875 | AA44: 0 | AB44: 1263 | AC44: 1263 | AH44: 123594 | AI44: 123594 | AM44: 50544 | AN44: 0 | AQ44: 50544 | AR44: 0 | AS44: 37665 | AU44: 12879 | AV44: 0
A45: 20025 | B45: 0 | C45: 200340624 | D45: "KARBONAT" AJ | E45: 8 | F45: 11 | G45: 0 | H45: 1 | I45: 2018 | J45: 4 | K45: N | L45: 3 | M45: 30 | N45: 0 | O45: 43776.673 | P45: 3100883 | Q45: 2509133 | R45: 591750 | S45: 0 | T45: 1098023 | V45: 329481 | W45: 768542 | Y45: 875582 | Z45: 369309 | AA45: 0 | AB45: 2676 | AC45: 227 | AG45: 2449 | AH45: 245765 | AI45: 245765 | AM45: 126220 | AN45: 0 | AQ45: 126220 | AR45: 0 | AS45: 33101 | AU45: 93119 | AV45: 0
A46: 20025 | B46: 0 | C46: 200344745 | D46: "JIZZAX PLASTMASSA" AJ | E46: 8 | F46: 12 | G46: 0 | H46: 1 | I46: 2021 | J46: 4 | K46: N | L46: 2 | M46: 30 | N46: 0 | O46: 44882.644 | P46: 21201386 | Q46: 16844838 | R46: 4356548 | S46: 0 | T46: 4367370 | V46: 2386638 | W46: 1980732 | Y46: 2013378 | Z46: 2002556 | AA46: 0 | AB46: 91836 | AF46: 91805 | AG46: 31 | AH46: 1244278 | AI46: 951213 | AK46: 292076 | AL46: 989 | AM46: 850114 | AN46: 0 | AQ46: 850114 | AR46: 0 | AS46: 127517 | AU46: 722597 | AV46: 0
A47: 20025 | B47: 0 | C47: 200344745 | D47: "JIZZAX PLASTMASSA" AJ | E47: 8 | F47: 12 | G47: 0 | H47: 1 | I47: 2020 | J47: 4 | K47: N | L47: 2 | M47: 30 | N47: 0 | O47: 44795.497 | P47: 29744018 | Q47: 21358493 | R47: 8385525.4 | S47: 0 | T47: 5370719 | V47: 2693600.8 | W47: 2677118.2 | Y47: 362563.56 | Z47: 3377369.9 | AA47: 0 | AB47: 88005.18 | AD47: 46.91 | AF47: 87958.27 | AH47: 3180018.5 | AI47: 2561774.1 | AK47: 617094.16 | AL47: 1150.23 | AM47: 285356.6 | AN47: 0 | AQ47: 285356.6 | AR47: 0 | AS47: 84124.53 | AU47: 201232.07 | AV47: 0
A48: 20025 | B48: 0 | C48: 200344745 | D48: "JIZZAX PLASTMASSA" AJ | E48: 8 | F48: 12 | G48: 0 | H48: 1 | I48: 2019 | J48: 4 | K48: N | L48: 1 | M48: 30 | N48: 0 | O48: 43878.724 | P48: 29856558 | Q48: 19496797 | R48: 10359761 | S48: 0 | T48: 5693203 | V48: 3267506 | W48: 2425697 | Y48: 658077 | Z48: 5324635 | AA48: 0 | AB48: 139437 | AF48: 138021 | AG48: 1416 | AH48: 1510539 | AI48: 1189706 | AK48: 320833 | AM48: 3953533 | AN48: 0 | AQ48: 3953533 | AR48: 0 | AS48: 359469 | AT48: 62086 | AU48: 3531978 | AV48: 0
A49: 20025 | B49: 0 | C49: 200344745 | D49: "JIZZAX PLASTMASSA" AJ | E49: 8 | F49: 12 | G49: 0 | H49: 1 | I49: 2018 | J49: 4 | K49: N | L49: 2 | M49: 30 | N49: 0 | O49: 43551.837 | P49: 38672037 | Q49: 34270280 | R49: 4401757 | S49: 0 | T49: 6481063 | U49: 0 | V49: 4709136 | W49: 1771927 | X49: 0 | Y49: 11708909 | Z49: 9629603 | AA49: 0 | AB49: 575716 | AC49: 0 | AD49: 0 | AE49: 0 | AF49: 575716 | AG49: 0 | AH49: 1037978 | AI49: 633356 | AJ49: 0 | AK49: 404622 | AL49: 0 | AM49: 9167341 | AN49: 0 | AO49: 0 | AP49: 0 | AQ49: 9167341 | AR49: 0 | AS49: 2410351 | AT49: 0 | AU49: 6756990 | AV49: 0
A50: 20025 | B50: 0 | C50: 200378039 | D50: КООП."РАДУГА" | E50: 35 | F50: 9 | G50: 0 | H50: 13 | I50: 2021 | J50: 4 | K50: N | L50: 1 | M50: 30 | N50: 0 | O50: 44581.5 | P50: 2400 | Q50: 1200 | R50: 1200 | S50: 0 | T50: 9119.5 | V50: 9119.5 | Z50: 0 | AA50: 7919.5 | AM50: 0 | AN50: 7919.5 | AQ50: 0 | AR50: 7919.5 | AS50: 136 | AT50: 3270 | AU50: -11325.5 | AV50: 11325.5
A51: 60132 | B51: 0 | C51: 200378039 | D51: КООП."РАДУГА" | E51: 35 | F51: 9 | G51: 0 | H51: 13 | I51: 2020 | J51: 4 | K51: N | L51: 1 | M51: 30 | N51: 0 | O51: 44211.81 | P51: 16000 | Q51: 5600 | R51: 10400 | S51: 0 | T51: 8495.1 | V51: 8380.1 | W51: 115 | Z51: 1904.9 | AA51: 0 | AM51: 1904.9 | AN51: 0 | AQ51: 1904.9 | AR51: 0 | AS51: 1200 | AT51: 6654.6 | AU51: -5949.7 | AV51: 5949.7
A52: 20025 | B52: 0 | C52: 200378039 | D52: КООП."РАДУГА" | E52: 35 | F52: 9 | G52: 0 | H52: 13 | I52: 2019 | J52: 4 | K52: N | L52: 2 | M52: 30 | N52: 0 | O52: 43900.634 | P52: 15000 | Q52: 7200 | R52: 7800 | S52: 0 | T52: 21746.7 | V52: 20967.1 | W52: 779.6 | Z52: 0 | AA52: 13946.7 | AB52: 10000 | AG52: 10000 | AM52: 0 | AN52: 3946.7 | AQ52: 0 | AR52: 3946.7 | AS52: 200 | AT52: 6970.5 | AU52: -11117.2 | AV52: 11117.2
A53: 20025 | B53: 0 | C53: 200378039 | D53: КООП."РАДУГА" | E53: 35 | F53: 9 | G53: 0 | H53: 13 | I53: 2018 | J53: 4 | K53: N | L53: 1 | M53: 30 | N53: 0 | O53: 43491.518 | P53: 370500 | Q53: 299603.9 | R53: 70896.1 | S53: 0 | T53: 50642.6 | V53: 50642.6 | Z53: 20253.5 | AA53: 0 | AB53: 15000 | AG53: 15000 | AM53: 35253.5 | AN53: 0 | AQ53: 35253.5 | AR53: 0 | AT53: 31803.5 | AU53: 3450 | AV53: 0
A54: 20025 | B54: 0 | C54: 200383721 | D54: "QONIRAT UN ZAVODI" AJ | E54: 35 | F54: 12 | G54: 0 | H54: 1 | I54: 2021 | J54: 4 | K54: N | L54: 2 | M54: 30 | N54: 0 | O54: 44644.414 | P54: 40387789 | Q54: 35463326 | R54: 4924463 | S54: 0 | T54: 3807296 | U54: 35408 | V54: 1274445 | W54: 2497443 | Y54: 118208 | Z54: 1235375 | AA54: 0 | AH54: 1090904 | AI54: 1090904 | AM54: 144471 | AN54: 0 | AQ54: 144471 | AR54: 0 | AS54: 45121 | AT54: 0 | AU54: 99350 | AV54: 0
A55: 20025 | B55: 0 | C55: 200383721 | D55: "QONIRAT UN ZAVODI" AJ | E55: 35 | F55: 12 | G55: 0 | H55: 1 | I55: 2020 | J55: 4 | K55: N | L55: 2 | M55: 30 | N55: 0 | O55: 44258.486 | P55: 41633330 | Q55: 36720732 | R55: 4912598 | S55: 0 | T55: 3589239 | U55: 50698 | V55: 974219 | W55: 2564322 | Y55: 106706 | Z55: 1430065 | AA55: 0 | AB55: 0 | AH55: 1251141 | AI55: 1251141 | AM55: 178924 | AN55: 0 | AQ55: 178924 | AR55: 0 | AS55: 87923 | AU55: 91001 | AV55: 0
A56: 20025 | B56: 0 | C56: 200383721 | D56: "QONIRAT UN ZAVODI" AJ | E56: 35 | F56: 12 | G56: 0 | H56: 1 | I56: 2019 | J56: 4 | K56: N | L56: 2 | M56: 30 | N56: 0 | O56: 43951.437 | P56: 29296530 | Q56: 23817611 | R56: 5478919 | S56: 0 | T56: 3613251 | U56: 40138 | V56: 756278 | W56: 2816835 | Y56: 104145 | Z56: 1969813 | AA56: 0 | AB56: 803 | AC56: 803 | AH56: 1184669 | AI56: 1184669 | AM56: 785947 | AN56: 0 | AQ56: 785947 | AR56: 0 | AS56: 197327 | AU56: 588620 | AV56: 0
A57: 20025 | B57: 0 | C57: 200383721 | D57: "QONIRAT UN ZAVODI" AJ | E57: 35 | F57: 12 | G57: 0 | H57: 1 | I57: 2018 | J57: 4 | K57: N | L57: 2 | M57: 30 | N57: 0 | O57: 43537.697 | P57: 25250629 | Q57: 19016971 | R57: 6233658 | S57: 0 | T57: 4412874 | U57: 39542 | V57: 623979 | W57: 3749353 | Y57: 107812 | Z57: 1928596 | AA57: 0 | AB57: 433 | AC57: 433 | AH57: 1911955 | AI57: 1911955 | AM57: 17074 | AN57: 0 | AQ57: 17074 | AR57: 0 | AS57: 2390 | AU57: 14684 | AV57: 0
A58: 20025 | B58: 0 | C58: 200409204 | D58: "URGANCHKORMMASH" AJ | E58: 33 | F58: 1 | G58: 0 | H58: 1 | I58: 2021 | J58: 4 | K58: N | L58: 1 | M58: 30 | N58: 0 | O58: 44603.593 | P58: 18553837 | Q58: 12568921 | R58: 5984916 | S58: 0 | T58: 2697374 | U58: 360460 | V58: 1193197 | W58: 1143717 | Y58: 220078 | Z58: 3507620 | AA58: 0 | AB58: 62160 | AF58: 11396 | AG58: 50764 | AH58: 898792 | AI58: 898792 | AM58: 2670988 | AN58: 0 | AQ58: 2670988 | AR58: 0 | AS58: 432567 | AU58: 2238421 | AV58: 0
A59: 20025 | B59: 0 | C59: 200409204 | D59: "URGANCHKORMMASH" AJ | E59: 33 | F59: 1 | G59: 0 | H59: 1 | I59: 2020 | J59: 4 | K59: N | L59: 1 | M59: 30 | N59: 0 | O59: 44239.643 | P59: 19566651 | Q59: 15140572 | R59: 4426079 | S59: 0 | T59: 1923526 | U59: 382440 | V59: 861280 | W59: 679806 | Y59: 188820 | Z59: 2691373 | AA59: 0 | AB59: 241868 | AF59: 241868 | AH59: 622818 | AI59: 622818 | AM59: 2310423 | AN59: 0 | AQ59: 2310423 | AR59: 0 | AS59: 373199 | AU59: 1937224 | AV59: 0
A60: 20025 | B60: 0 | C60: 200409204 | D60: "URGANCHKORMMASH" AJ | E60: 33 | F60: 1 | G60: 0 | H60: 1 | I60: 2019 | J60: 4 | K60: N | L60: 1 | M60: 30 | N60: 0 | O60: 43871.589 | P60: 9154203 | Q60: 6907306 | R60: 2246897 | S60: 0 | T60: 1587903 | U60: 202879 | V60: 851690 | W60: 533334 | Y60: 87904 | Z60: 746898 | AA60: 0 | AB60: 40684 | AC60: 267 | AF60: 24094 | AG60: 16323 | AH60: 116010 | AI60: 115594 | AK60: 416 | AM60: 671572 | AN60: 0 | AQ60: 671572 | AR60: 0 | AS60: 84543 | AU60: 587029 | AV60: 0
A61: 20025 | B61: 0 | C61: 200409204 | D61: "URGANCHKORMMASH" AJ | E61: 33 | F61: 1 | G61: 0 | H61: 1 | I61: 2018 | J61: 4 | K61: N | L61: 1 | M61: 30 | N61: 0 | O61: 43507.722 | P61: 10807949 | Q61: 7092160 | R61: 3715789 | S61: 0 | T61: 973968 | U61: 148502 | V61: 532670 | W61: 292796 | Y61: 99552 | Z61: 2841373 | AA61: 0 | AB61: 147132 | AC61: 12674 | AD61: 30790 | AF61: 103668 | AH61: 72569 | AI61: 56086 | AK61: 16483 | AM61: 2915936 | AN61: 0 | AQ61: 2915936 | AR61: 0 | AT61: 552732 | AU61: 2363204 | AV61: 0
A62: 20025 | B62: 0 | C62: 200426279 | D62: "BOG'OT DON" AJ | E62: 33 | F62: 11 | G62: 0 | H62: 1 | I62: 2021 | J62: 4 | K62: N | L62: 1 | M62: 30 | N62: 0 | O62: 44604.411 | P62: 62633044 | Q62: 59532109 | R62: 3100935 | S62: 0 | T62: 4034646 | U62: 89488 | V62: 1637132 | W62: 2308026 | X62: 0 | Y62: 1168465 | Z62: 234754 | AA62: 0 | AB62: 68717 | AC62: 1514 | AD62: 67203 | AE62: 0 | AF62: 0 | AG62: 0 | AH62: 44385 | AI62: 27428 | AJ62: 0 | AK62: 16957 | AL62: 0 | AM62: 259086 | AN62: 0 | AO62: 0 | AP62: 0 | AQ62: 259086 | AR62: 0 | AS62: 49016 | AT62: 0 | AU62: 210070 | AV62: 0
A63: 20025 | B63: 0 | C63: 200426279 | D63: "BOG'OT DON" AJ | E63: 33 | F63: 11 | G63: 0 | H63: 1 | I63: 2020 | J63: 4 | K63: N | L63: 1 | M63: 30 | N63: 0 | O63: 44237.65 | P63: 79424518 | Q63: 70087493 | R63: 9337025 | S63: 0 | T63: 9412491 | U63: 82188 | V63: 1613551 | W63: 7716752 | X63: 0 | Y63: 1255186 | Z63: 1179720 | AA63: 0 | AB63: 64838 | AC63: 7731 | AD63: 57107 | AE63: 0 | AF63: 0 | AG63: 0 | AH63: 318822 | AI63: 252345 | AJ63: 0 | AK63: 66477 | AL63: 0 | AM63: 925736 | AN63: 0 | AO63: 0 | AP63: 0 | AQ63: 925736 | AR63: 0 | AS63: 166417 | AT63: 0 | AU63: 759319 | AV63: 0
A64: 20025 | B64: 0 | C64: 200426279 | D64: "BOG'OT DON" AJ | E64: 33 | F64: 11 | G64: 0 | H64: 1 | I64: 2019 | J64: 4 | K64: N | L64: 2 | M64: 30 | N64: 0 | O64: 43939.528 | P64: 57203873 | Q64: 42854596 | R64: 14349277 | S64: 0 | T64: 7078850 | U64: 74423 | V64: 1077270 | W64: 5927157 | X64: 0 | Y64: 0 | Z64: 7270427 | AA64: 0 | AB64: 326972 | AC64: 60000 | AD64: 73359 | AE64: 0 | AF64: 9471 | AG64: 184142 | AH64: 588435 | AI64: 579013 | AJ64: 0 | AK64: 9422 | AL64: 0 | AM64: 7008964 | AN64: 0 | AO64: 0 | AP64: 0 | AQ64: 7008964 | AR64: 0 | AS64: 706378 | AT64: 0 | AU64: 6302586 | AV64: 0
A65: 20025 | B65: 0 | C65: 200426279 | D65: "BOG'OT DON" AJ | E65: 33 | F65: 11 | G65: 0 | H65: 1 | I65: 2018 | J65: 4 | K65: N | L65: 2 | M65: 30 | N65: 0 | O65: 43542.393 | P65: 48861321 | Q65: 38708885 | R65: 10152436 | S65: 0 | T65: 5355935 | U65: 165157 | V65: 613480 | W65: 4577298 | X65: 0 | Y65: 78390 | Z65: 4874891 | AA65: 0 | AB65: 19634 | AC65: 19634 | AD65: 0 | AE65: 0 | AF65: 0 | AG65: 0 | AH65: 2728632 | AI65: 2706702 | AJ65: 0 | AK65: 0 | AL65: 21930 | AM65: 2165893 | AN65: 0 | AO65: 0 | AP65: 0 | AQ65: 2165893 | AR65: 0 | AS65: 284070 | AT65: 0 | AU65: 1881823 | AV65: 0
A66: 20025 | B66: 0 | C66: 200465215 | D66: "OHANGARONSHIFER" AJ | E66: 27 | F66: 19 | G66: 2 | H66: 1 | I66: 2021 | J66: 4 | K66: N | L66: 1 | M66: 30 | N66: 0 | O66: 44606.565 | P66: 7896157 | Q66: 7185503 | R66: 710654 | S66: 0 | T66: 655105 | U66: 30907 | V66: 167178 | W66: 457020 | Y66: 7157 | Z66: 62706 | AA66: 0 | AM66: 62706 | AN66: 0 | AQ66: 62706 | AR66: 0 | AS66: 9406 | AU66: 53300 | AV66: 0
A67: 20025 | B67: 0 | C67: 200465215 | D67: "OHANGARONSHIFER" AJ | E67: 27 | F67: 19 | G67: 2 | H67: 1 | I67: 2020 | J67: 4 | K67: N | L67: 1 | M67: 30 | N67: 0 | O67: 44242.915 | P67: 11789878 | Q67: 11153224 | R67: 636654 | S67: 0 | T67: 4586036 | U67: 423611 | V67: 1719326 | W67: 2443099 | Y67: 132622 | Z67: 0 | AA67: 3816760 | AB67: 0 | AH67: 0 | AI67: 0 | AM67: 0 | AN67: 3816760 | AQ67: 0 | AR67: 3816760 | AU67: -3816760 | AV67: 3816760
A68: 20025 | B68: 0 | C68: 200465215 | D68: "OHANGARONSHIFER" AJ | E68: 27 | F68: 19 | G68: 2 | H68: 1 | I68: 2019 | J68: 4 | K68: N | L68: 1 | M68: 30 | N68: 0 | O68: 43985.73 | P68: 15252184 | Q68: 13125293 | R68: 2126891 | S68: 0 | T68: 6187079 | U68: 473194 | V68: 1921562 | W68: 3792323 | Y68: 2352794 | Z68: 0 | AA68: 1707394 | AB68: 14726 | AC68: 14726 | AH68: 415647 | AI68: 415647 | AM68: 0 | AN68: 2108315 | AQ68: 0 | AR68: 2108315 | AU68: -2108315 | AV68: 2108315
A69: 20025 | B69: 0 | C69: 200465215 | D69: "OHANGARONSHIFER" AJ | E69: 27 | F69: 19 | G69: 2 | H69: 1 | I69: 2018 | J69: 4 | K69: N | L69: 1 | M69: 30 | N69: 0 | O69: 43511.93 | P69: 25076723 | Q69: 21254517 | R69: 3822206 | S69: 0 | T69: 4392126 | U69: 249442 | V69: 1228039 | W69: 2914645 | Y69: 901323 | Z69: 331403 | AA69: 0 | AB69: 13094 | AC69: 10463 | AF69: 2631 | AH69: 1153002 | AI69: 889930 | AK69: 263072 | AM69: 0 | AN69: 808505 | AQ69: 0 | AR69: 808505 | AU69: -808505 | AV69: 808505
A70: 20025 | B70: 0 | C70: 200479996 | D70: "SURXONOZIQOVQATSANOATI" AJ | E70: 22 | F70: 7 | G70: 0 | H70: 1 | I70: 2021 | J70: 4 | K70: N | L70: 1 | M70: 30 | N70: 0 | O70: 44607.69 | P70: 50909955 | Q70: 48849026 | R70: 2060929 | S70: 0 | T70: 6942785 | U70: 862756 | V70: 1553632 | W70: 4526397 | Y70: 551168 | Z70: 0 | AA70: 4330688 | AB70: 948 | AC70: 353 | AF70: 595 | AH70: 6805480 | AI70: 6797202 | AK70: 8278 | AM70: 0 | AN70: 11135220 | AQ70: 0 | AR70: 11135220 | AU70: -11135220 | AV70: 11135220
